Workbook
Name BalanceForChart2: 'RE Calculations'!$F$23:INDEX('RE Calculations'!$F$23:$F$73,COUNT('RE Calculations'!$D$23:$D$73))
Name CoCForChart6: 'RE Calculations'!$J$136:INDEX('RE Calculations'!$J$136:$J$186,COUNT('RE Calculations'!$J$136:$J$186))
Name CostsForChart5: 'RE Calculations'!$E$136:INDEX('RE Calculations'!$E$136:$E$186,COUNT('RE Calculations'!$C$136:$C$186))
Name CumInterestForChart2: 'RE Calculations'!$E$23:INDEX('RE Calculations'!$E$23:$E$73,COUNT('RE Calculations'!$D$23:$D$73))
Name CumPrincipalForChart2: 'RE Calculations'!$D$23:INDEX('RE Calculations'!$D$23:$D$73,COUNT('RE Calculations'!$D$23:$D$73))
Name EqValueForChart3: 'RE Calculations'!$D$80:INDEX('RE Calculations'!$D$80:$D$130,COUNT('RE Calculations'!$C$80:$C$130))
Name GrossROIForChart4: 'RE Calculations'!$J$79:INDEX('RE Calculations'!$J$79:$J$130,COUNT('RE Calculations'!$H$79:$H$130))
Name HoldPeriodForChart1: 'RE Calculations'!$O$23:INDEX('RE Calculations'!$O$23:$O$73,COUNT('RE Calculations'!$L$23:$L$73))
Name HoldPeriodForChart2: 'RE Calculations'!$I$23:INDEX('RE Calculations'!$I$23:$I$73,COUNT('RE Calculations'!$D$23:$D$73))
Name HoldPeriodForChart3: 'RE Calculations'!$E$80:INDEX('RE Calculations'!$E$80:$E$130,COUNT('RE Calculations'!$C$80:$C$130))
Name HoldPeriodForChart4: 'RE Calculations'!$L$79:INDEX('RE Calculations'!$L$79:$L$130,COUNT('RE Calculations'!$H$79:$H$130))
Name HoldPeriodForChart5: 'RE Calculations'!$G$136:INDEX('RE Calculations'!$G$136:$G$186,COUNT('RE Calculations'!$C$136:$C$186))
Name HoldPeriodForChart6: 'RE Calculations'!$M$136:INDEX('RE Calculations'!$M$136:$M$186,COUNT('RE Calculations'!$J$136:$J$186))
Name InterestForChart1: 'RE Calculations'!$M$23:INDEX('RE Calculations'!$M$23:$M$73,COUNT('RE Calculations'!$L$23:$L$73))
Name LoanForChart5: 'RE Calculations'!$F$136:INDEX('RE Calculations'!$F$136:$F$186,COUNT('RE Calculations'!$C$136:$C$186))
Name NetROIForChart4: 'RE Calculations'!$K$79:INDEX('RE Calculations'!$K$79:$K$130,COUNT('RE Calculations'!$H$79:$H$130))
Name PrincipalForChart1: 'RE Calculations'!$L$23:INDEX('RE Calculations'!$L$23:$L$73,COUNT('RE Calculations'!$L$23:$L$73))
Name PropValueForChart3: 'RE Calculations'!$C$80:INDEX('RE Calculations'!$C$80:$C$130,COUNT('RE Calculations'!$C$80:$C$130))
Name RentForChart5: 'RE Calculations'!$C$136:INDEX('RE Calculations'!$C$136:$C$186,COUNT('RE Calculations'!$C$136:$C$186))
Name YearForChart1: 'RE Calculations'!$K$23:INDEX('RE Calculations'!$K$23:$K$73,COUNT('RE Calculations'!$L$23:$L$73))
Name YearForChart3: 'RE Calculations'!$B$80:INDEX('RE Calculations'!$B$80:$B$130,COUNT('RE Calculations'!$C$80:$C$130))
Name YearForChart4: 'RE Calculations'!$G$79:INDEX('RE Calculations'!$G$79:$G$130,COUNT('RE Calculations'!$H$79:$H$130))
Name YearForChart5: 'RE Calculations'!$B$136:INDEX('RE Calculations'!$B$136:$B$186,COUNT('RE Calculations'!$C$136:$C$186))
Name YearForChart6: 'RE Calculations'!$I$136:INDEX('RE Calculations'!$I$136:$I$186,COUNT('RE Calculations'!$J$136:$J$186))
Name YieldCostForChart6: 'RE Calculations'!$K$136:INDEX('RE Calculations'!$K$136:$K$186,COUNT('RE Calculations'!$J$136:$J$186))
Name YieldValueForChart6: 'RE Calculations'!$L$136:INDEX('RE Calculations'!$L$136:$L$186,COUNT('RE Calculations'!$J$136:$J$186))

Sheet Intro
B2: Investment Tool
B3: If you have questions or need consultation feel free to reach out on whatsapp +971 52 8602947
B4: This is a tool that I crafted to streamline the assessment and analysis of real estate investments
B5: It evaluates key factors like rental revenue, property value appreciation, and expenses related to buying, maintaining, and selling, helping you gauge the viability and returns of a potential investment.
B6: The workbook comes equipped with essential features such as a detailed analysis overview, mortgage calculation tools, financial projection models, and a section for researching comparable properties.
B7: this versatile tool can also be easily tailored to assess Airbnb rental opportunities.
B9: Important Note: The cells are unlocked for flexibility, so please input or modify data only in the cells highlighted in LIGHT BROWN
B10: You’ll find links to the relevant spreadsheet in the table below for easy access:
B12: No. | C12: Sheet Name | D12: Description
B13: 1 | C13: Inputs | D13: Enter the primary inputs and assumptions on this sheet, and they will automatically populate throughout the entire workbook. It also features a concise summary table, providing a clear, at-a-glance view of how adjustments to the assumptions impact the overall deal.
B14: 2 | C14: Analysis Summary | D14: Easy-to-print dashboards that showcase essential metrics and insightful charts, helping you clearly visualize the investment opportunity. Switch effortlessly between a Principal & Interest Loan and an Interest Only Loan with a simple toggle.
B15: 3 | C15: Mortgage Calculators (By Month) | D15: Features a detailed Amortization Schedule for both Principal & Interest and Interest Only Loans, calculated on a monthly basis. Additionally, it offers a mortgage comparison tool to easily evaluate two different financing scenarios side by side.
B16: 4 | C16: Mortgage Calculators (By Year) | D16: Features a detailed Amortization Schedule for both Principal & Interest and Interest Only Loans, calculated on a Yearly basis. Additionally, it offers a mortgage comparison tool to easily evaluate two different financing scenarios side by side.
B17: 5 | C17: Forecast (By Month) | D17: Monthly forecast of the investment’s performance, factoring in rental revenue, property value appreciation, and expenses related to buying, maintaining, and selling throughout the mortgage term. It incorporates cash flows, as well as gross and net profits for a complete financial overview.
B18: 6 | C18: Forecast (By Year) | D18: Yearly forecast of the investment’s performance, factoring in rental revenue, property value appreciation, and expenses related to buying, maintaining, and selling throughout the mortgage term. It incorporates cash flows, as well as gross and net profits for a complete financial overview.
B19: 7 | C19: Comparables | D19: User-friendly tool designed to evaluate comparable properties, both currently listed and recently sold, within the surrounding area. It also provides rental price comparisons for a well-rounded analysis.
B20: 8 | C20: Notes | D20: For any notes
B23: If you have any questions or feedback, please do not hesitate to message me on whatsapp +971 52 860 2947
B24: I also provide help with analysing any of your investment and provide consultation on wether a property is a worthwile investment, feel free to reach out anytime!

Sheet Inputs
B1: *** NOTE: INSERT/EDIT DATA IN LIGHT BROWN CELLS ONLY ***
B3: KEY INFORMATION | J3: QUICK SUMMARY
C4: Value | D4: Input Type | E4: Active? | G4: Notes/Comments | J4: Key Information
B5: Address | C5: The Lofts | G5: Input address for Analysis Summary tab | J5: Total Purchase Price | K5: =C6 -> 1499950
B6: Total Purchase Price | C6: 1499950 | J6: Down Payment (%) | K6: =IF($E7="YES",$C7,$C8/$C$6) -> 1
B7: Down Payment | C7: 1 | D7: % of Total Price | E7: YES | J7: Down Payment ($) | K7: =IF($E7="YES",$C7*$C$6,$C8) -> 1499950
C8: 80000 | D8: $ Value | E8: =IF($E$7="YES","NO","YES") -> NO | J8: Principal Amount | K8: =K5-K7 -> 0
B9: Yr 1 Market Value / After Repair Value (ARV) | C9: 1635000 | G9: Used to calculate total appreciation and profit | J9: Yr 1 Market Value / After Repair Value (ARV) | K9: =C9 -> 1635000
B10: Holding Period (Years) | C10: 5 | G10: Set to maximum loan duration if no intention to sell | J10: Holding Period | K10: =$C$10 -> 5
B11: Appreciation (Annual) | C11: 0.05 | J11: Appreciation (Annual) | K11: =C11 -> 0.05
B12: Rental Income | C12: 103000 | D12: per annum | J12: Monthly Appreciation | K12: =POWER((1+K11),1/12)-1 -> 0.0040741238
B13: Other Income | C13: 0 | D13: per week | J13: Estimated Selling Price | K13: =$K$9*(1+$K$11)^$K$10 -> 2086720.4
B14: Rental Growth (Annual) | C14: 0.05 | J14: Rental Income | K14: =TEXT($C$12,"AED#,##0.00")&" "&$D$12 -> AED103,000.00 per annum
J15: Other Income | K15: =TEXT($C$13,"AED#,##0.00")&" "&$D$13 -> AED0.00 per week
J16: Equivalent Monthly Income | K16: =($C$12*_xlfn.XLOOKUP($D$12,'RE Calculations'!$B$12:$B$16,'RE Calculations'!$C$12:$C$16,"Error - check formula",0)+$C$13*_xlfn.XLOOKUP($D$13,'RE Calculations'!$B$12:$B$16,'RE Calculations'!$C$12:$C$16,"Error - check formula",0))/12 -> 8583.3333
B17: MORTGAGE INFORMATION | J17: Rental Growth (Annual) | K17: =C14 -> 0.05
B18: Principal & Interest Loan (P&I) | J18: Purchasing Costs Required (Incl. Down Payment) | K18: =F56 -> 1601027
B19: Annual Interest Rate | C19: 0.045 | G19: Nominal Interest Rate | J19: Selling Costs | K19: =F95 -> 46234.407
B20: Loan Duration (Years) | C20: 30 | G20: Input the loan duration
B21: Fees | C21: 100 | D21: per annum | G21: Additional fees including for offset/redraw accounts | J21: Simple Cash Flow Calculator | K21: per month
J22: Total Income (Rent + Other) | K22: =K16*12/_xlfn.XLOOKUP($K$21,'RE Calculations'!$B$12:$B$16,'RE Calculations'!$C$12:$C$16,"Error - Check Unit Input",0) -> 8583.3333
B23: Interest Only Loan (IO) | J23: Ongoing Fees/Costs | K23: =F79/_xlfn.XLOOKUP($K$21,'RE Calculations'!$B$12:$B$16,'RE Calculations'!$C$12:$C$16,"Error - Check Unit Input",0) -> 2432.3333
B24: Annual Interest Rate | C24: 0.0475 | G24: Nominal Interest Rate | J24: Loan Payment (P&I Loan) | K24: =K39*12/_xlfn.XLOOKUP($K$21,'RE Calculations'!$B$12:$B$16,'RE Calculations'!$C$12:$C$16,"Error - Check Unit Input",0) -> 100
B25: Interest Only Duration (Years) | C25: 5 | G25: Loan switches to a typical Principal and Interest Loan after this duration | J25: Total Cash Flow (P&I Loan) | K25: =K22-K23-K24 -> 6051
B26: Standard Interest Rate (after IO period) | C26: 0.045 | G26: Nominal Interest Rate | J26: Cash-on-Cash Return (P&I Loan) | K26: =(K25*_xlfn.XLOOKUP($K$21,'RE Calculations'!$B$12:$B$16,'RE Calculations'!$C$12:$C$16,"Error - Check Unit Input",0))/K18 -> 0.045353389
B27: Total Loan Duration (Years) | C27: 30 | G27: Maximum 50 years | J27: Loan Payment (IO Loan) | K27: =K49*12/_xlfn.XLOOKUP($K$21,'RE Calculations'!$B$12:$B$16,'RE Calculations'!$C$12:$C$16,"Error - Check Unit Input",0) -> 120
B28: Fees | C28: 120 | D28: per annum | G28: Additional fees including for offset/redraw accounts | J28: ="Loan Payment After "&K44&" Years (IO Loan)" -> Loan Payment After 5 Years (IO Loan) | K28: =K50*12/_xlfn.XLOOKUP($K$21,'RE Calculations'!$B$12:$B$16,'RE Calculations'!$C$12:$C$16,"Error - Check Unit Input",0) -> 120
J29: Total Cash Flow (IO Loan) | K29: =K22-K23-K27 -> 6031
J30: ="Total Cash Flow After "&K44&" Years (IO Loan)" -> Total Cash Flow After 5 Years (IO Loan) | K30: =K22-K23-K28 -> 6031
B31: PURCHASING COSTS | J31: Cash-on-Cash Return (IO Loan) | K31: =(K29*_xlfn.XLOOKUP($K$21,'RE Calculations'!$B$12:$B$16,'RE Calculations'!$C$12:$C$16,"Error - Check Unit Input",0))/K18 -> 0.045203485
B32: Item | C32: % of Purchase Price | D32: One Time Cost | E32: Tax Deductible? | F32: Lump Sum Equivalent | G32: Notes/Comments
B33: Legal fees | C33: 0 | D33: 0 | E33: FALSE | F33: =IFERROR(IF(OR(C33=0,C33="",ISERROR(C33)),D33,C33*$C$6),"Error - Check Input") -> 0 | G33: Alternatively, get a Defect & Handover inspection for new builds | J33: Mortgage Information
B34: Conveyancer/Solicitor Fees | C34: 0 | D34: 4500 | E34: FALSE | F34: =IFERROR(IF(OR(C34=0,C34="",ISERROR(C34)),D34,C34*$C$6),"Error - Check Input") -> 4500 | G34: Make sure to confirm prices, extra charges and scope of services with conveyancer | J34: Principal & Interest Loan (P&I)
B35: Strata Report | C35: 0 | D35: 0 | E35: FALSE | F35: =IFERROR(IF(OR(C35=0,C35="",ISERROR(C35)),D35,C35*$C$6),"Error - Check Input") -> 0 | G35: Look for info on fees, special levies, find balance, future building works/maintenance plans | J35: Annual Interest Rate | K35: =C19 -> 0.045
B36: Mortgage registration fee 0.25% | C36: 0 | D36: 0 | E36: FALSE | F36: =IFERROR(IF(OR(C36=0,C36="",ISERROR(C36)),D36,C36*$C$6),"Error - Check Input") -> 0 | G36: Includes Loan Application + Establishment Fees, Documentation + Prep Fees | J36: Equivalent Monthly Interest Rate | K36: =K35/12 -> 0.00375
B37: Mortgage Insurance | C37: 0 | D37: 0 | E37: FALSE | F37: =IFERROR(IF(OR(C37=0,C37="",ISERROR(C37)),D37,C37*$C$6),"Error - Check Input") -> 0 | G37: Varies depending on LVR and total loan amount | J37: Loan Duration (Years) | K37: =C20 -> 30
B38: Valuation/Appraisal Fees | C38: 0 | D38: 0 | E38: FALSE | F38: =IFERROR(IF(OR(C38=0,C38="",ISERROR(C38)),D38,C38*$C$6),"Error - Check Input") -> 0 | G38: Input valuation fee if you paid for one | J38: Fees | K38: =TEXT($C$21,"AED#,##0.00")&" "&$D$21 -> AED100.00 per annum
B39: 4% Dubai Land department | C39: 0.04 | D39: 700 | E39: FALSE | F39: =IFERROR(IF(OR(C39=0,C39="",ISERROR(C39)),D39,C39*$C$6),"Error - Check Input") -> 59998 | G39: Registration of Discharge, Registration and Transfers | J39: Monthly Loan Payment | K39: =-PMT(K36,K37*12,K8)+$C$21*_xlfn.XLOOKUP($D$21,'RE Calculations'!$B$12:$B$16,'RE Calculations'!$C$12:$C$16,"ERROR - Check Input") -> 100
B40: NOC | C40: 0 | D40: 2000 | E40: FALSE | F40: =IFERROR(IF(OR(C40=0,C40="",ISERROR(C40)),D40,C40*$C$6),"Error - Check Input") -> 2000 | G40: NOC Paid to the developer
B41: Utilities and Services (Connection Fee) | C41: 0 | D41: 0 | E41: FALSE | F41: =IFERROR(IF(OR(C41=0,C41="",ISERROR(C41)),D41,C41*$C$6),"Error - Check Input") -> 0 | G41: Depends on whether property requires new connection | J41: Interest Only Loan (IO)
B42: DLD Admin fee | C42: 0 | D42: 580 | E42: FALSE | F42: =IFERROR(IF(OR(C42=0,C42="",ISERROR(C42)),D42,C42*$C$6),"Error - Check Input") -> 580 | G42: The DLD Admin fee | J42: Annual Interest Rate | K42: =C24 -> 0.0475
B43: Travel Expenses | C43: 0 | D43: 0 | E43: FALSE | F43: =IFERROR(IF(OR(C43=0,C43="",ISERROR(C43)),D43,C43*$C$6),"Error - Check Input") -> 0 | G43: Flights, fuel, etc | J43: Equivalent Monthly Interest Rate | K43: =K42/12 -> 0.0039583333
B44: Renovation/Maintenance | C44: 0 | D44: 0 | E44: FALSE | F44: =IFERROR(IF(OR(C44=0,C44="",ISERROR(C44)),D44,C44*$C$6),"Error - Check Input") -> 0 | G44: If property needs renovation work/maintenance | J44: Interest Only Duration (Years) | K44: =C25 -> 5
B45: Furnishing/Upgrades | C45: 0 | D45: 0 | E45: FALSE | F45: =IFERROR(IF(OR(C45=0,C45="",ISERROR(C45)),D45,C45*$C$6),"Error - Check Input") -> 0 | G45: If you need to furnish it i.e for holiday homes | J45: Standard Interest Rate (after interest only period) | K45: =C26 -> 0.045
B46: Letting Fee/Advertising Fee | C46: 0 | D46: 0 | E46: FALSE | F46: =IFERROR(IF(OR(C46=0,C46="",ISERROR(C46)),D46,C46*$C$6),"Error - Check Input") -> 0 | G46: Fee to rent it out | J46: Equivalent Monthly Interest Rate | K46: =K45/12 -> 0.00375
B47: Buyer's Agent | C47: 0.02 | D47: 0 | E47: FALSE | F47: =IFERROR(IF(OR(C47=0,C47="",ISERROR(C47)),D47,C47*$C$6),"Error - Check Input") -> 29999 | G47: Your agency commission fee usually 2% | J47: Total Loan Duration (Years) | K47: =C27 -> 30
B48: Trustee Office fee | C48: 0 | D48: 4000 | E48: FALSE | F48: =IFERROR(IF(OR(C48=0,C48="",ISERROR(C48)),D48,C48*$C$6),"Error - Check Input") -> 4000 | G48: Trustee office fee | J48: Fees | K48: =TEXT($C$28,"AED#,##0.00")&" "&$D$28 -> AED120.00 per annum
B49: Other Purchasing Costs 1 | C49: 0 | D49: 0 | E49: FALSE | F49: =IFERROR(IF(OR(C49=0,C49="",ISERROR(C49)),D49,C49*$C$6),"Error - Check Input") -> 0 | G49: Optional | J49: ="Monthly Loan Payment (First "&K44&" Years)" -> Monthly Loan Payment (First 5 Years) | K49: =K42*K8/12+$C$28*_xlfn.XLOOKUP($D$28,'RE Calculations'!$B$12:$B$16,'RE Calculations'!$C$12:$C$16,"ERROR - Check Input") -> 120
B50: Other Purchasing Costs 2 | C50: 0 | D50: 0 | E50: FALSE | F50: =IFERROR(IF(OR(C50=0,C50="",ISERROR(C50)),D50,C50*$C$6),"Error - Check Input") -> 0 | G50: Optional | J50: After Interest Only Period | K50: =-PMT(K46,(K47-K44)*12,K8)+$C$28*_xlfn.XLOOKUP($D$28,'RE Calculations'!$B$12:$B$16,'RE Calculations'!$C$12:$C$16,"ERROR - Check Input") -> 120
B51: Other Purchasing Costs 3 | C51: 0 | D51: 0 | E51: FALSE | F51: =IFERROR(IF(OR(C51=0,C51="",ISERROR(C51)),D51,C51*$C$6),"Error - Check Input") -> 0 | G51: Optional
B52: Other Purchasing Costs 4 | C52: 0 | D52: 0 | E52: FALSE | F52: =IFERROR(IF(OR(C52=0,C52="",ISERROR(C52)),D52,C52*$C$6),"Error - Check Input") -> 0 | G52: Optional | J52: Forecast Assumptions
B53: Other Purchasing Costs 5 | C53: 0 | D53: 0 | E53: FALSE | F53: =IFERROR(IF(OR(C53=0,C53="",ISERROR(C53)),D53,C53*$C$6),"Error - Check Input") -> 0 | G53: Optional | J53: Inflation (Annual) | K53: =C100 -> 0
J54: - | K54: =C101 -> 0
B55: Total Purchasing Costs (Excl. Down Payment) | F55: =SUM(F33:F54) -> 101077 | J55: Value Eligible for Depreciation (%) | K55: =IF(E102="YES",IF($E103="YES",$C$103,$C$104/$K$5),0) -> 0
B56: Total Purchasing Costs (Incl. Down Payment) | F56: =F55+K7 -> 1601027 | J56: Value Eligible for Depreciation ($) | K56: =IF(E102="YES",IF($E104="YES",$C$104,$C$103*$K$5),0) -> 0
J57: Depreciated over how many years? | K57: =IF(E102="YES",C105,0) -> 0
B59: ONGOING FEES/COSTS | C59: *Assumed all Ongoing Fees/Costs are tax deductible and are distributed throughout the year
B60: Item | C60: % of Total Income | D60: Amount | E60: Unit | F60: Annual Equivalent | G60: Notes/Comments
B61: Miscellanous | C61: 0 | D61: 0 | E61: per annum | F61: =IFERROR(IF(OR(C61=0,C61="",ISERROR(C61)),D61*_xlfn.XLOOKUP(E61,'RE Calculations'!$B$12:$B$16,'RE Calculations'!$C$12:$C$16,"Error - Check Unit Input",0),C61*'RE Calculations'!$C$8),"Error - Check Input") -> 0
B62: Other Misc 2 | C62: 0 | D62: 0 | E62: per annum | F62: =IFERROR(IF(OR(C62=0,C62="",ISERROR(C62)),D62*_xlfn.XLOOKUP(E62,'RE Calculations'!$B$12:$B$16,'RE Calculations'!$C$12:$C$16,"Error - Check Unit Input",0),C62*'RE Calculations'!$C$8),"Error - Check Input") -> 0
B63: Service Charges | C63: 0 | D63: 10158 | E63: per annum | F63: =IFERROR(IF(OR(C63=0,C63="",ISERROR(C63)),D63*_xlfn.XLOOKUP(E63,'RE Calculations'!$B$12:$B$16,'RE Calculations'!$C$12:$C$16,"Error - Check Unit Input",0),C63*'RE Calculations'!$C$8),"Error - Check Input") -> 10158
B64: Utilities and Services | C64: 0 | D64: 600 | E64: per month | F64: =IFERROR(IF(OR(C64=0,C64="",ISERROR(C64)),D64*_xlfn.XLOOKUP(E64,'RE Calculations'!$B$12:$B$16,'RE Calculations'!$C$12:$C$16,"Error - Check Unit Input",0),C64*'RE Calculations'!$C$8),"Error - Check Input") -> 7200 | G64: Depends if tenant is paying/ sometimes chiller is on the landlord/holiday homes
B65: Strata/Body Corporate Fees | C65: 0 | D65: 0 | E65: per annum | F65: =IFERROR(IF(OR(C65=0,C65="",ISERROR(C65)),D65*_xlfn.XLOOKUP(E65,'RE Calculations'!$B$12:$B$16,'RE Calculations'!$C$12:$C$16,"Error - Check Unit Input",0),C65*'RE Calculations'!$C$8),"Error - Check Input") -> 0 | G65: See strata report/ask conveyancer to check
B66: Home/Building Insurance | C66: 0 | D66: 0 | E66: per annum | F66: =IFERROR(IF(OR(C66=0,C66="",ISERROR(C66)),D66*_xlfn.XLOOKUP(E66,'RE Calculations'!$B$12:$B$16,'RE Calculations'!$C$12:$C$16,"Error - Check Unit Input",0),C66*'RE Calculations'!$C$8),"Error - Check Input") -> 0 | G66: Any home insurance fees
B67: Contents Insurance | C67: 0 | D67: 500 | E67: per annum | F67: =IFERROR(IF(OR(C67=0,C67="",ISERROR(C67)),D67*_xlfn.XLOOKUP(E67,'RE Calculations'!$B$12:$B$16,'RE Calculations'!$C$12:$C$16,"Error - Check Unit Input",0),C67*'RE Calculations'!$C$8),"Error - Check Input") -> 500 | G67: insured furniture if holiday homes or other home insurance
B68: Income Protection Insurance | C68: 0 | D68: 0 | E68: per annum | F68: =IFERROR(IF(OR(C68=0,C68="",ISERROR(C68)),D68*_xlfn.XLOOKUP(E68,'RE Calculations'!$B$12:$B$16,'RE Calculations'!$C$12:$C$16,"Error - Check Unit Input",0),C68*'RE Calculations'!$C$8),"Error - Check Input") -> 0 | G68: Optional
B69: Provision for Vacancy | C69: 0.02 | D69: 0 | E69: per annum | F69: =IFERROR(IF(OR(C69=0,C69="",ISERROR(C69)),D69*_xlfn.XLOOKUP(E69,'RE Calculations'!$B$12:$B$16,'RE Calculations'!$C$12:$C$16,"Error - Check Unit Input",0),C69*'RE Calculations'!$C$8),"Error - Check Input") -> 2060 | G69: no property is always 100% rented, have a provision for vacancy
B70: Provision for Maintainance & Capex | C70: 0.01 | D70: 0 | E70: per month | F70: =IFERROR(IF(OR(C70=0,C70="",ISERROR(C70)),D70*_xlfn.XLOOKUP(E70,'RE Calculations'!$B$12:$B$16,'RE Calculations'!$C$12:$C$16,"Error - Check Unit Input",0),C70*'RE Calculations'!$C$8),"Error - Check Input") -> 1030 | G70: Any provision for ongoing maintenance
B71: Management Fees | C71: 0.08 | D71: 0 | E71: per month | F71: =IFERROR(IF(OR(C71=0,C71="",ISERROR(C71)),D71*_xlfn.XLOOKUP(E71,'RE Calculations'!$B$12:$B$16,'RE Calculations'!$C$12:$C$16,"Error - Check Unit Input",0),C71*'RE Calculations'!$C$8),"Error - Check Input") -> 8240 | G71: If you give your property for property management or holiday home company
B72: Other Maintenance misc | C72: 0 | D72: 0 | E72: per annum | F72: =IFERROR(IF(OR(C72=0,C72="",ISERROR(C72)),D72*_xlfn.XLOOKUP(E72,'RE Calculations'!$B$12:$B$16,'RE Calculations'!$C$12:$C$16,"Error - Check Unit Input",0),C72*'RE Calculations'!$C$8),"Error - Check Input") -> 0 | G72: Optional
B73: Other Ongoing Costs 1 | C73: 0 | D73: 0 | E73: per month | F73: =IFERROR(IF(OR(C73=0,C73="",ISERROR(C73)),D73*_xlfn.XLOOKUP(E73,'RE Calculations'!$B$12:$B$16,'RE Calculations'!$C$12:$C$16,"Error - Check Unit Input",0),C73*'RE Calculations'!$C$8),"Error - Check Input") -> 0 | G73: Optional
B74: Other Ongoing Costs 2 | C74: 0 | D74: 0 | E74: per month | F74: =IFERROR(IF(OR(C74=0,C74="",ISERROR(C74)),D74*_xlfn.XLOOKUP(E74,'RE Calculations'!$B$12:$B$16,'RE Calculations'!$C$12:$C$16,"Error - Check Unit Input",0),C74*'RE Calculations'!$C$8),"Error - Check Input") -> 0 | G74: Optional
B75: Other Ongoing Costs 3 | C75: 0 | D75: 0 | E75: per month | F75: =IFERROR(IF(OR(C75=0,C75="",ISERROR(C75)),D75*_xlfn.XLOOKUP(E75,'RE Calculations'!$B$12:$B$16,'RE Calculations'!$C$12:$C$16,"Error - Check Unit Input",0),C75*'RE Calculations'!$C$8),"Error - Check Input") -> 0 | G75: Optional
... B77: Other Ongoing Costs 5 | C77: 0 | D77: 0 | E77: per month | F77: =IFERROR(IF(OR(C77=0,C77="",ISERROR(C77)),D77*_xlfn.XLOOKUP(E77,'RE Calculations'!$B$12:$B$16,'RE Calculations'!$C$12:$C$16,"Error - Check Unit Input",0),C77*'RE Calculations'!$C$8),"Error - Check Input") -> 0 | G77: Optional
B79: Total Ongoing Fees/Costs | D79: =F79/_xlfn.XLOOKUP(E79,'RE Calculations'!$B$12:$B$16,'RE Calculations'!$C$12:$C$16,"Error - check formula",0) -> 2432.3333 | E79: per month | F79: =SUM(F61:F78) -> 29188
B82: SELLING FEES/COSTS
B83: Item | C83: % of Sale Price | D83: One Time Cost | E83: Tax Deductible? | F83: Lump Sum Equivalent | G83: Notes/Comments
B84: Advertising & Marketing Costs | C84: 0 | D84: 0 | E84: FALSE | F84: =IFERROR(IF(OR(C84=0,C84="",ISERROR(C84)),D84,C84*$K$13),"Error - Check Input") -> 0 | G84: Any related fees
B85: Real Estate Agency Commission | C85: 0.02 | D85: 0 | E85: FALSE | F85: =IFERROR(IF(OR(C85=0,C85="",ISERROR(C85)),D85,C85*$K$13),"Error - Check Input") -> 41734.407 | G85: Usually agreed with the broker
B86: Legal Fees | C86: 0 | D86: 4500 | E86: FALSE | F86: =IFERROR(IF(OR(C86=0,C86="",ISERROR(C86)),D86,C86*$K$13),"Error - Check Input") -> 4500
B87: Contingency | C87: 0 | D87: 0 | E87: FALSE | F87: =IFERROR(IF(OR(C87=0,C87="",ISERROR(C87)),D87,C87*$K$13),"Error - Check Input") -> 0 | G87: Optional
B88: Renovation/Maintainance (to sell) | C88: 0 | D88: 0 | E88: FALSE | F88: =IFERROR(IF(OR(C88=0,C88="",ISERROR(C88)),D88,C88*$K$13),"Error - Check Input") -> 0 | G88: Optional
B89: Other Closing Costs 1 | C89: 0 | D89: 0 | E89: FALSE | F89: =IFERROR(IF(OR(C89=0,C89="",ISERROR(C89)),D89,C89*$K$13),"Error - Check Input") -> 0 | G89: Optional
B90: Other Closing Costs 2 | C90: 0 | D90: 0 | E90: FALSE | F90: =IFERROR(IF(OR(C90=0,C90="",ISERROR(C90)),D90,C90*$K$13),"Error - Check Input") -> 0 | G90: Optional
B91: Other Closing Costs 3 | C91: 0 | D91: 0 | E91: FALSE | F91: =IFERROR(IF(OR(C91=0,C91="",ISERROR(C91)),D91,C91*$K$13),"Error - Check Input") -> 0 | G91: Optional
B92: Other Closing Costs 4 | C92: 0 | D92: 0 | E92: FALSE | F92: =IFERROR(IF(OR(C92=0,C92="",ISERROR(C92)),D92,C92*$K$13),"Error - Check Input") -> 0 | G92: Optional
B93: Other Closing Costs 5 | C93: 0 | D93: 0 | E93: FALSE | F93: =IFERROR(IF(OR(C93=0,C93="",ISERROR(C93)),D93,C93*$K$13),"Error - Check Input") -> 0 | G93: Optional
B95: Total Selling Fees/Costs | F95: =SUM(F84:F94) -> 46234.407
B98: FORECAST ASSUMPTIONS
C99: Value | D99: Input Type | E99: Active?
B100: Inflation (Annual) | C100: 0
B101: - | C101: 0
B102: Consider Depreciation? | E102: NO | G102: Set to "NO" to ignore depreciation
B103: Value Eligible for Depreciation | C103: 0.25 | D103: % of Total Price | E103: YES | G103: E.g. 50-60% for new builds, 25% for established properties (depending on age); Generally higher for apartments
C104: 120000 | D104: $ Value | E104: =IF($E$103="YES","NO","YES") -> NO | G104: Value eligible for depreciation claims (i.e. non-land component only, excluding amount already depreciated)
B105: Depreciated over how many years? | C105: 30 | G105: Number of years left for depreciation claims; Lumped all depreciable items into one for simplicity

Sheet Analysis Summary
B2: Principal & Interest Loan (P&I) | C2: <-- Toggle between Principal & Interest Loan and Interest Only Loan
B4: =Inputs!$C$5 -> The Lofts | Z4: =Inputs!$C$5 -> The Lofts | BK4: =Inputs!$C$5 -> The Lofts
B6: KEY INFORMATION | E6: =$B$2 -> Principal & Interest Loan (P&I) | Z6: ="With a holding period of "&$C$12&" years:" -> With a holding period of 5 years: | AM6: =$B$2 -> Principal & Interest Loan (P&I) | BK6: Year 1 | CE6: ="Year "&Inputs!$K$10&" (Holding Period)" -> Year 5 (Holding Period)
B7: Total Price | C7: =Inputs!$K5 -> 1499950 | Z7: Purchasing Costs | AF7: Estimated Property Value
B8: Down Payment (%) | C8: =Inputs!$K6 -> 1 | BK8: Total Rental Income | BX8: =IF('Analysis Summary'!$B$2=Inputs!$B$18,_xlfn.XLOOKUP(1,'Forecast (By Year)'!$F$3:$F$55,'Forecast (By Year)'!$I$3:$I$55),_xlfn.XLOOKUP(1,'Forecast (By Year)'!$AD$3:$AD$55,'Forecast (By Year)'!$AG$3:$AG$55)) -> 103000 | CE8: Total Rental Income | CR8: =IF('Analysis Summary'!$B$2=Inputs!$B$18,_xlfn.XLOOKUP(Inputs!$K$10,'Forecast (By Year)'!$F$3:$F$55,'Forecast (By Year)'!$I$3:$I$55),_xlfn.XLOOKUP(Inputs!$K$10,'Forecast (By Year)'!$AD$3:$AD$55,'Forecast (By Year)'!$AG$3:$AG$55)) -> 125197.14
B9: Down Payment ($) | C9: =Inputs!$K7 -> 1499950 | BK9: Total Ongoing Fees/Costs | BX9: =IF('Analysis Summary'!$B$2=Inputs!$B$18,_xlfn.XLOOKUP(1,'Forecast (By Year)'!$F$3:$F$55,'Forecast (By Year)'!$L$3:$L$55),_xlfn.XLOOKUP(1,'Forecast (By Year)'!$AD$3:$AD$55,'Forecast (By Year)'!$AJ$3:$AJ$55)) -> 29188 | CE9: Total Ongoing Fees/Costs | CR9: =IF('Analysis Summary'!$B$2=Inputs!$B$18,_xlfn.XLOOKUP(Inputs!$K$10,'Forecast (By Year)'!$F$3:$F$55,'Forecast (By Year)'!$L$3:$L$55),_xlfn.XLOOKUP(Inputs!$K$10,'Forecast (By Year)'!$AD$3:$AD$55,'Forecast (By Year)'!$AJ$3:$AJ$55)) -> 31629.686
B10: Principal Amount | C10: =Inputs!$K8 -> 0 | Z10: ='RE Calculations'!H194 -> 1601027 | AF10: ='RE Calculations'!H195 -> 2086720.4 | BK10: ="Loan Repayment - "&$B$2 -> Loan Repayment - Principal & Interest Loan (P&I) | BX10: =IF('Analysis Summary'!$B$2=Inputs!$B$18,_xlfn.XLOOKUP(1,'Forecast (By Year)'!$F$3:$F$55,'Forecast (By Year)'!$M$3:$M$55),_xlfn.XLOOKUP(1,'Forecast (By Year)'!$AD$3:$AD$55,'Forecast (By Year)'!$AK$3:$AK$55)) -> 0 | CE10: ="Loan Repayment - "&$B$2 -> Loan Repayment - Principal & Interest Loan (P&I) | CR10: =IF('Analysis Summary'!$B$2=Inputs!$B$18,_xlfn.XLOOKUP(Inputs!$K$10,'Forecast (By Year)'!$F$3:$F$55,'Forecast (By Year)'!$M$3:$M$55),_xlfn.XLOOKUP(Inputs!$K$10,'Forecast (By Year)'!$AD$3:$AD$55,'Forecast (By Year)'!$AK$3:$AK$55)) -> 0
B11: Yr 1 Market Value / After Repair Value (ARV) | C11: =Inputs!$K9 -> 1635000 | BK11: Before Tax Cash Flow | BX11: =BX8-BX9-BX10 -> 73812 | CE11: Before Tax Cash Flow | CR11: =CR8-CR9-CR10 -> 93567.458
B12: Holding Period | C12: =Inputs!$K10 -> 5
B13: Appreciation (Annual) | C13: =Inputs!$K11 -> 0.05 | Z13: Cumulative Cash Flow | AF13: Estimated Equity Value | BK13: Total Ongoing Fees/Costs | BX13: =BX9 -> 29188 | CE13: Total Ongoing Fees/Costs | CR13: =CR9 -> 31629.686
B14: Monthly Appreciation | C14: =Inputs!$K12 -> 0.0040741238 | BK14: Interest + Fees | BX14: =IF('Analysis Summary'!$B$2=Inputs!$B$18,_xlfn.XLOOKUP(1,'Forecast (By Year)'!$F$3:$F$55,'Forecast (By Year)'!$O$3:$O$55),_xlfn.XLOOKUP(1,'Forecast (By Year)'!$AD$3:$AD$55,'Forecast (By Year)'!$AM$3:$AM$55)) -> 100 | CE14: Interest + Fees | CR14: =IF('Analysis Summary'!$B$2=Inputs!$B$18,_xlfn.XLOOKUP(Inputs!$K$10,'Forecast (By Year)'!$F$3:$F$55,'Forecast (By Year)'!$O$3:$O$55),_xlfn.XLOOKUP(Inputs!$K$10,'Forecast (By Year)'!$AD$3:$AD$55,'Forecast (By Year)'!$AM$3:$AM$55)) -> 100
B15: Estimated Selling Price | C15: =Inputs!$K13 -> 2086720.4 | BK15: Depreciation | BX15: =IF('Analysis Summary'!$B$2=Inputs!$B$18,_xlfn.XLOOKUP(1,'Forecast (By Year)'!$F$3:$F$55,'Forecast (By Year)'!$P$3:$P$55),_xlfn.XLOOKUP(1,'Forecast (By Year)'!$AD$3:$AD$55,'Forecast (By Year)'!$AN$3:$AN$55)) -> 0 | CE15: Depreciation | CR15: =IF('Analysis Summary'!$B$2=Inputs!$B$18,_xlfn.XLOOKUP(Inputs!$K$10,'Forecast (By Year)'!$F$3:$F$55,'Forecast (By Year)'!$P$3:$P$55),_xlfn.XLOOKUP(Inputs!$K$10,'Forecast (By Year)'!$AD$3:$AD$55,'Forecast (By Year)'!$AN$3:$AN$55)) -> 0
B16: Rental Income | C16: =Inputs!$K14 -> AED103,000.00 per annum | Z16: ='RE Calculations'!H196 -> 417244.62 | AF16: ='RE Calculations'!H197 -> 2086720.4 | BK16: Total Deductions | BX16: =SUM(BX13:CB15) -> 29288 | CE16: Total Deductions | CR16: =SUM(CR13:CV15) -> 31729.686
B17: Other Income | C17: =Inputs!$K15 -> AED0.00 per week
B18: Equivalent Monthly Income | C18: =Inputs!$K16 -> 8583.3333 | BK18: ="Tax Payment / Credit (at "&Inputs!$K$54*100&"% tax rate)" -> Tax Payment / Credit (at 0% tax rate) | BX18: =IF('Analysis Summary'!$B$2=Inputs!$B$18,_xlfn.XLOOKUP(1,'Forecast (By Year)'!$F$3:$F$55,'Forecast (By Year)'!$S$3:$S$55),_xlfn.XLOOKUP(1,'Forecast (By Year)'!$AD$3:$AD$55,'Forecast (By Year)'!$AQ$3:$AQ$55)) -> 0 | CE18: ="Tax Payment / Credit (at "&Inputs!$K$54*100&"% tax rate)" -> Tax Payment / Credit (at 0% tax rate) | CR18: =IF('Analysis Summary'!$B$2=Inputs!$B$18,_xlfn.XLOOKUP(Inputs!$K$10,'Forecast (By Year)'!$F$3:$F$55,'Forecast (By Year)'!$S$3:$S$55),_xlfn.XLOOKUP(Inputs!$K$10,'Forecast (By Year)'!$AD$3:$AD$55,'Forecast (By Year)'!$AQ$3:$AQ$55)) -> 0
B19: Rental Growth (Annual) | C19: =Inputs!$K17 -> 0.05 | Z19: Gross Profit After Sale (excl. Cash Flow) | AF19: Net Profit After Sale (incl. Cash Flow) | BK19: After Tax Cash Flow | BX19: =BX11-BX18 -> 73812 | CE19: After Tax Cash Flow | CR19: =CR11-CR18 -> 93567.458
B20: Purchasing Costs Required (Incl. Down Payment) | C20: =Inputs!$K18 -> 1601027
B21: Selling Costs | C21: =Inputs!$K19 -> 46234.407 | BS21: Before Tax | CM21: Before Tax
Z22: ='RE Calculations'!H198 -> 439458.95 | AF22: ='RE Calculations'!H199 -> 856703.56 | BK22: Cash-on-Cash Return | BQ22: Yield on Cost | BW22: Yield on Value | CE22: Cash-on-Cash Return | CK22: Yield on Cost | CQ22: Yield on Value
B23: MORTGAGE INFORMATION
B24: Principal & Interest Loan (P&I) | BK24: ='RE Calculations'!H210 -> 0.046102908 | BQ24: ='RE Calculations'!H211 -> 0.04920964 | BW24: ='RE Calculations'!H212 -> 0.045144954 | CE24: ='RE Calculations'!H218 -> 0.058442149 | CK24: ='RE Calculations'!H219 -> 0.062380385 | CQ24: ='RE Calculations'!H220 -> 0.057227803
B25: Annual Interest Rate | C25: =Inputs!K35 -> 0.045 | Z25: Gross Annualized Return-on-Investment | AF25: Net Annualized Return-on-Investment
B26: Equivalent Monthly Interest Rate | C26: =Inputs!K36 -> 0.00375 | BS26: After Tax | CM26: After Tax
B27: Loan Duration | C27: =Inputs!K37 -> 30 | BK27: Cash-on-Cash Return | BQ27: Yield on Cost | BW27: Yield on Value | CE27: Cash-on-Cash Return | CK27: Yield on Cost | CQ27: Yield on Value
B28: Fees | C28: =Inputs!K38 -> AED100.00 per annum | Z28: ='RE Calculations'!H200 -> 0.054897131 | AF28: ='RE Calculations'!H201 -> 0.10701925
B29: Monthly Loan Payment | C29: =Inputs!K39 -> 100 | BK29: ='RE Calculations'!H214 -> 0.046102908 | BQ29: ='RE Calculations'!H215 -> 0.04920964 | BW29: ='RE Calculations'!H216 -> 0.045144954 | CE29: ='RE Calculations'!H222 -> 0.058442149 | CK29: ='RE Calculations'!H223 -> 0.062380385 | CQ29: ='RE Calculations'!H224 -> 0.057227803
B31: Interest Only Loan (IO) | Z31: Gross Annualized Return-on-Equity | AF31: Net Annualized Return-on-Equity
B32: Annual Interest Rate | C32: =Inputs!K42 -> 0.0475 | BK32: =$B$2 -> Principal & Interest Loan (P&I)
B33: Equivalent Monthly Interest Rate | C33: =Inputs!K43 -> 0.0039583333
B34: Interest Only Duration | C34: =Inputs!K44 -> 5 | Z34: ='RE Calculations'!H202 -> 0.042119582 | AF34: ='RE Calculations'!H203 -> 0.08211005
B35: Standard Interest Rate (after interest only period) | C35: =Inputs!K45 -> 0.045
B36: Equivalent Monthly Interest Rate | C36: =Inputs!K46 -> 0.00375
B37: Total Loan Duration | C37: =Inputs!K47 -> 30 | Z37: Capitalization Rate | AF37: Debt Service Coverage Ratio
B38: Fees | C38: =Inputs!K48 -> AED120.00 per annum
B39: Monthly Loan Payment (First 5 Years) | C39: =Inputs!K49 -> 120
B40: After Interest Only Period | C40: =Inputs!K50 -> 120 | Z40: ='RE Calculations'!H204 -> 0.044839481 | AF40: ='RE Calculations'!H205 -> 1251.9714
B42: FORECAST ASSUMPTIONS | E42: ="With a holding period of "&$C$12&" years:" -> With a holding period of 5 years:
B43: Inflation (Annual) | C43: =Inputs!K53 -> 0 | E43: Annual Payment | H43: Loan Balance | M43: Cumulative Principal | S43: Cumulative Interest + Fees | Z43: Loan To Value Ratio | AF43: Loan To Cost Ratio
B44: Tax Bracket | C44: =Inputs!K54 -> 0
B45: Value Eligible for Depreciation (%) | C45: =Inputs!K55 -> 0
B46: Value Eligible for Depreciation ($) | C46: =Inputs!K56 -> 0 | E46: ='RE Calculations'!H190 -> 100 | H46: ='RE Calculations'!H191 -> 0 | M46: ='RE Calculations'!H192 -> 0 | S46: ='RE Calculations'!H193 -> 500 | Z46: ='RE Calculations'!H206 -> 0 | AF46: ='RE Calculations'!H207 -> 0
B47: Depreciated over how many years? | C47: =Inputs!K57 -> 0
Z51: Metric | AF51: Formula | BK51: Metric | BQ51: Formula
Z52: Gross Profit After Sale | AF52: Property Value less Purchasing Costs | BK52: Before Tax
Z53: Net Profit After Sale | AF53: Gross Profit less Cumulative Cash Flow | BK53: Cash-on-Cash Return | BQ53: Annual Before Tax Cash Flow/Purchasing Costs
Z54: Gross Annualized ROI | AF54: (Gross Profit/Purchasing Costs Required)/Holding Period | BK54: Yield on Cost | BQ54: Annual Before Tax Cash Flow/Total Purchase Price
Z55: Net Annualized ROI | AF55: (Net Profit/Purchasing Costs Required)/Holding Period | BK55: Yield on Value | BQ55: Annual Before Tax Cash Flow/Yr 1 Market Value or ARV
Z56: Gross Annualized ROE | AF56: (Gross Profit/Est. Equity Value)/Holding Period | BK56: After Tax
Z57: Net Annualized ROE | AF57: (Net Profit/Est. Equity Value)/Holding Period | BK57: Cash-on-Cash Return | BQ57: Annual After Tax Cash Flow/Purchasing Costs
Z58: Capitalization Rate | AF58: Annual Operating Income/Total Purchase Price | BK58: Yield on Cost | BQ58: Annual After Tax Cash Flow/Total Purchase Price
Z59: Debt Service Coverage Ratio | AF59: After Tax Cash Flow/Debt Service | BK59: Yield on Value | BQ59: Annual After Tax Cash Flow/Yr 1 Market Value or ARV
Z60: Loan To Value Ratio | AF60: Loan Balance/Est. Property Value
Z61: Loan To Cost Ratio | AF61: Loan Balance/Purchase Price

Sheet RE Calculations
B1: *** NOTE: THIS SHEET CONTAINS SOME KEY CALCULATIONS BEHIND THE WORKBOOK. PLEASE DO NOT EDIT OR SOME FORMULAS/CHARTS WILL BE BROKEN. ***
B3: TOTAL INCOME
B4: per week | C4: =(Inputs!$C$12*_xlfn.XLOOKUP(Inputs!$D$12,'RE Calculations'!$B$12:$B$16,'RE Calculations'!$C$12:$C$16,"Error - Check Unit Input",0)+Inputs!$C$13*_xlfn.XLOOKUP(Inputs!$D$13,'RE Calculations'!$B$12:$B$16,'RE Calculations'!$C$12:$C$16,"Error - Check Unit Input",0))/_xlfn.XLOOKUP(B4,'RE Calculations'!$B$12:$B$16,'RE Calculations'!$C$12:$C$16,"Error - Check Unit Input",0) -> 1980.7692
B5: per fortnight | C5: =(Inputs!$C$12*_xlfn.XLOOKUP(Inputs!$D$12,'RE Calculations'!$B$12:$B$16,'RE Calculations'!$C$12:$C$16,"Error - Check Unit Input",0)+Inputs!$C$13*_xlfn.XLOOKUP(Inputs!$D$13,'RE Calculations'!$B$12:$B$16,'RE Calculations'!$C$12:$C$16,"Error - Check Unit Input",0))/_xlfn.XLOOKUP(B5,'RE Calculations'!$B$12:$B$16,'RE Calculations'!$C$12:$C$16,"Error - Check Unit Input",0) -> 3961.5385
B6: per month | C6: =(Inputs!$C$12*_xlfn.XLOOKUP(Inputs!$D$12,'RE Calculations'!$B$12:$B$16,'RE Calculations'!$C$12:$C$16,"Error - Check Unit Input",0)+Inputs!$C$13*_xlfn.XLOOKUP(Inputs!$D$13,'RE Calculations'!$B$12:$B$16,'RE Calculations'!$C$12:$C$16,"Error - Check Unit Input",0))/_xlfn.XLOOKUP(B6,'RE Calculations'!$B$12:$B$16,'RE Calculations'!$C$12:$C$16,"Error - Check Unit Input",0) -> 8583.3333
B7: per quarter | C7: =(Inputs!$C$12*_xlfn.XLOOKUP(Inputs!$D$12,'RE Calculations'!$B$12:$B$16,'RE Calculations'!$C$12:$C$16,"Error - Check Unit Input",0)+Inputs!$C$13*_xlfn.XLOOKUP(Inputs!$D$13,'RE Calculations'!$B$12:$B$16,'RE Calculations'!$C$12:$C$16,"Error - Check Unit Input",0))/_xlfn.XLOOKUP(B7,'RE Calculations'!$B$12:$B$16,'RE Calculations'!$C$12:$C$16,"Error - Check Unit Input",0) -> 25750
B8: per annum | C8: =(Inputs!$C$12*_xlfn.XLOOKUP(Inputs!$D$12,'RE Calculations'!$B$12:$B$16,'RE Calculations'!$C$12:$C$16,"Error - Check Unit Input",0)+Inputs!$C$13*_xlfn.XLOOKUP(Inputs!$D$13,'RE Calculations'!$B$12:$B$16,'RE Calculations'!$C$12:$C$16,"Error - Check Unit Input",0))/_xlfn.XLOOKUP(B8,'RE Calculations'!$B$12:$B$16,'RE Calculations'!$C$12:$C$16,"Error - Check Unit Input",0) -> 103000
B10: PERIOD CONVERTER
B11: Units (Period) | C11: Annual Equivalent
B12: per week | C12: 52
B13: per fortnight | C13: 26
B14: per month | C14: 12
B15: per quarter | C15: 4
B16: per annum | C16: 1
B18: CHARTS FOR ANALYSIS SUMMARY TAB
B19: Loan Amortization Chart | K19: Annual Payments
B20: ='Analysis Summary'!$E$6 -> Principal & Interest Loan (P&I) | I20: =_xlfn.MAXIFS(D22:E73,D22:E73,">0") -> 3000 | K20: ='Analysis Summary'!$E$6 -> Principal & Interest Loan (P&I) | O20: =_xlfn.XLOOKUP(Inputs!$K$10,'RE Calculations'!$K$22:$K$73,'RE Calculations'!$N$22:$N$73) -> 100
B21: Year | C21: Cumulative Payment | D21: Cumulative Principal | E21: Cumulative Interest + Fees | F21: Balance | G21: Principal Label | H21: Interest + Fees Label | I21: Holding Period | K21: Year | L21: Principal | M21: Interest + Fees | N21: Sum | O21: Holding Period
B22: 0 | C22: =IF($B$20=Inputs!$B$18,IF($B22<='Mortgage Calculators (By Year)'!$C$9,SUM('Mortgage Calculators (By Year)'!C$22:C22),NA()),IF($B22<='Mortgage Calculators (By Year)'!$J$12,SUM('Mortgage Calculators (By Year)'!J$22:J22),NA())) -> 0 | D22: =IF($B$20=Inputs!$B$18,IF($B22<='Mortgage Calculators (By Year)'!$C$9,SUM('Mortgage Calculators (By Year)'!D$22:D22),NA()),IF($B22<='Mortgage Calculators (By Year)'!$J$12,SUM('Mortgage Calculators (By Year)'!K$22:K22),NA())) -> 0 | E22: =IF($B$20=Inputs!$B$18,IF($B22<='Mortgage Calculators (By Year)'!$C$9,SUM('Mortgage Calculators (By Year)'!E$22:E22),NA()),IF($B22<='Mortgage Calculators (By Year)'!$J$12,SUM('Mortgage Calculators (By Year)'!L$22:L22),NA())) -> 0 | F22: =IF($B$20=Inputs!$B$18,IF($B22<='Mortgage Calculators (By Year)'!$C$9,'Mortgage Calculators (By Year)'!F22,NA()),IF($B22<='Mortgage Calculators (By Year)'!$J$12,'Mortgage Calculators (By Year)'!M22,NA())) -> 0 | I22: =IF(B22=ROUND(Inputs!$K$10,0),$I$20,NA()) -> #N/A | K22: 0 | L22: =IF($K$20=Inputs!$B$18,IF($K22<='Mortgage Calculators (By Year)'!$C$9,'Mortgage Calculators (By Year)'!D22,NA()),IF($K22<='Mortgage Calculators (By Year)'!$J$12,'Mortgage Calculators (By Year)'!K22,NA())) -> 0 | M22: =IF($K$20=Inputs!$B$18,IF($K22<='Mortgage Calculators (By Year)'!$C$9,'Mortgage Calculators (By Year)'!E22,NA()),IF($K22<='Mortgage Calculators (By Year)'!$J$12,'Mortgage Calculators (By Year)'!L22,NA())) -> 0 | N22: =L22+M22 -> 0 | O22: =IF(K22=ROUND(Inputs!$K$10,0),$O$20,NA()) -> #N/A
B23: 1 | C23: =IF($B$20=Inputs!$B$18,IF($B23<='Mortgage Calculators (By Year)'!$C$9,SUM('Mortgage Calculators (By Year)'!C$22:C23),NA()),IF($B23<='Mortgage Calculators (By Year)'!$J$12,SUM('Mortgage Calculators (By Year)'!J$22:J23),NA())) -> 0 | D23: =IF($B$20=Inputs!$B$18,IF($B23<='Mortgage Calculators (By Year)'!$C$9,SUM('Mortgage Calculators (By Year)'!D$22:D23),NA()),IF($B23<='Mortgage Calculators (By Year)'!$J$12,SUM('Mortgage Calculators (By Year)'!K$22:K23),NA())) -> 0 | E23: =IF($B$20=Inputs!$B$18,IF($B23<='Mortgage Calculators (By Year)'!$C$9,SUM('Mortgage Calculators (By Year)'!E$22:E23),NA()),IF($B23<='Mortgage Calculators (By Year)'!$J$12,SUM('Mortgage Calculators (By Year)'!L$22:L23),NA())) -> 100 | F23: =IF($B$20=Inputs!$B$18,IF($B23<='Mortgage Calculators (By Year)'!$C$9,'Mortgage Calculators (By Year)'!F23,NA()),IF($B23<='Mortgage Calculators (By Year)'!$J$12,'Mortgage Calculators (By Year)'!M23,NA())) -> 0 | G23: =IF($B$20=Inputs!$B$18,IF($B23='Mortgage Calculators (By Year)'!$C$9,D23,""),IF($B23='Mortgage Calculators (By Year)'!$J$12,D23,"")) | H23: =IF($B$20=Inputs!$B$18,IF($B23='Mortgage Calculators (By Year)'!$C$9,E23,""),IF($B23='Mortgage Calculators (By Year)'!$J$12,E23,"")) | I23: =IF(B23=ROUND(Inputs!$K$10,0),$I$20,NA()) -> #N/A | K23: 1 | L23: =IF($K$20=Inputs!$B$18,IF($K23<='Mortgage Calculators (By Year)'!$C$9,'Mortgage Calculators (By Year)'!D23,NA()),IF($K23<='Mortgage Calculators (By Year)'!$J$12,'Mortgage Calculators (By Year)'!K23,NA())) -> 0 | M23: =IF($K$20=Inputs!$B$18,IF($K23<='Mortgage Calculators (By Year)'!$C$9,'Mortgage Calculators (By Year)'!E23,NA()),IF($K23<='Mortgage Calculators (By Year)'!$J$12,'Mortgage Calculators (By Year)'!L23,NA())) -> 100 | N23: =L23+M23 -> 100 | O23: =IF(K23=ROUND(Inputs!$K$10,0),$O$20,NA()) -> #N/A
B24: 2 | C24: =IF($B$20=Inputs!$B$18,IF($B24<='Mortgage Calculators (By Year)'!$C$9,SUM('Mortgage Calculators (By Year)'!C$22:C24),NA()),IF($B24<='Mortgage Calculators (By Year)'!$J$12,SUM('Mortgage Calculators (By Year)'!J$22:J24),NA())) -> 0 | D24: =IF($B$20=Inputs!$B$18,IF($B24<='Mortgage Calculators (By Year)'!$C$9,SUM('Mortgage Calculators (By Year)'!D$22:D24),NA()),IF($B24<='Mortgage Calculators (By Year)'!$J$12,SUM('Mortgage Calculators (By Year)'!K$22:K24),NA())) -> 0 | E24: =IF($B$20=Inputs!$B$18,IF($B24<='Mortgage Calculators (By Year)'!$C$9,SUM('Mortgage Calculators (By Year)'!E$22:E24),NA()),IF($B24<='Mortgage Calculators (By Year)'!$J$12,SUM('Mortgage Calculators (By Year)'!L$22:L24),NA())) -> 200 | F24: =IF($B$20=Inputs!$B$18,IF($B24<='Mortgage Calculators (By Year)'!$C$9,'Mortgage Calculators (By Year)'!F24,NA()),IF($B24<='Mortgage Calculators (By Year)'!$J$12,'Mortgage Calculators (By Year)'!M24,NA())) -> 0 | G24: =IF($B$20=Inputs!$B$18,IF($B24='Mortgage Calculators (By Year)'!$C$9,D24,""),IF($B24='Mortgage Calculators (By Year)'!$J$12,D24,"")) | H24: =IF($B$20=Inputs!$B$18,IF($B24='Mortgage Calculators (By Year)'!$C$9,E24,""),IF($B24='Mortgage Calculators (By Year)'!$J$12,E24,"")) | I24: =IF(B24=ROUND(Inputs!$K$10,0),$I$20,NA()) -> #N/A | K24: 2 | L24: =IF($K$20=Inputs!$B$18,IF($K24<='Mortgage Calculators (By Year)'!$C$9,'Mortgage Calculators (By Year)'!D24,NA()),IF($K24<='Mortgage Calculators (By Year)'!$J$12,'Mortgage Calculators (By Year)'!K24,NA())) -> 0 | M24: =IF($K$20=Inputs!$B$18,IF($K24<='Mortgage Calculators (By Year)'!$C$9,'Mortgage Calculators (By Year)'!E24,NA()),IF($K24<='Mortgage Calculators (By Year)'!$J$12,'Mortgage Calculators (By Year)'!L24,NA())) -> 100 | N24: =L24+M24 -> 100 | O24: =IF(K24=ROUND(Inputs!$K$10,0),$O$20,NA()) -> #N/A
B25: 3 | C25: =IF($B$20=Inputs!$B$18,IF($B25<='Mortgage Calculators (By Year)'!$C$9,SUM('Mortgage Calculators (By Year)'!C$22:C25),NA()),IF($B25<='Mortgage Calculators (By Year)'!$J$12,SUM('Mortgage Calculators (By Year)'!J$22:J25),NA())) -> 0 | D25: =IF($B$20=Inputs!$B$18,IF($B25<='Mortgage Calculators (By Year)'!$C$9,SUM('Mortgage Calculators (By Year)'!D$22:D25),NA()),IF($B25<='Mortgage Calculators (By Year)'!$J$12,SUM('Mortgage Calculators (By Year)'!K$22:K25),NA())) -> 0 | E25: =IF($B$20=Inputs!$B$18,IF($B25<='Mortgage Calculators (By Year)'!$C$9,SUM('Mortgage Calculators (By Year)'!E$22:E25),NA()),IF($B25<='Mortgage Calculators (By Year)'!$J$12,SUM('Mortgage Calculators (By Year)'!L$22:L25),NA())) -> 300 | F25: =IF($B$20=Inputs!$B$18,IF($B25<='Mortgage Calculators (By Year)'!$C$9,'Mortgage Calculators (By Year)'!F25,NA()),IF($B25<='Mortgage Calculators (By Year)'!$J$12,'Mortgage Calculators (By Year)'!M25,NA())) -> 0 | G25: =IF($B$20=Inputs!$B$18,IF($B25='Mortgage Calculators (By Year)'!$C$9,D25,""),IF($B25='Mortgage Calculators (By Year)'!$J$12,D25,"")) | H25: =IF($B$20=Inputs!$B$18,IF($B25='Mortgage Calculators (By Year)'!$C$9,E25,""),IF($B25='Mortgage Calculators (By Year)'!$J$12,E25,"")) | I25: =IF(B25=ROUND(Inputs!$K$10,0),$I$20,NA()) -> #N/A | K25: 3 | L25: =IF($K$20=Inputs!$B$18,IF($K25<='Mortgage Calculators (By Year)'!$C$9,'Mortgage Calculators (By Year)'!D25,NA()),IF($K25<='Mortgage Calculators (By Year)'!$J$12,'Mortgage Calculators (By Year)'!K25,NA())) -> 0 | M25: =IF($K$20=Inputs!$B$18,IF($K25<='Mortgage Calculators (By Year)'!$C$9,'Mortgage Calculators (By Year)'!E25,NA()),IF($K25<='Mortgage Calculators (By Year)'!$J$12,'Mortgage Calculators (By Year)'!L25,NA())) -> 100 | N25: =L25+M25 -> 100 | O25: =IF(K25=ROUND(Inputs!$K$10,0),$O$20,NA()) -> #N/A
B26: 4 | C26: =IF($B$20=Inputs!$B$18,IF($B26<='Mortgage Calculators (By Year)'!$C$9,SUM('Mortgage Calculators (By Year)'!C$22:C26),NA()),IF($B26<='Mortgage Calculators (By Year)'!$J$12,SUM('Mortgage Calculators (By Year)'!J$22:J26),NA())) -> 0 | D26: =IF($B$20=Inputs!$B$18,IF($B26<='Mortgage Calculators (By Year)'!$C$9,SUM('Mortgage Calculators (By Year)'!D$22:D26),NA()),IF($B26<='Mortgage Calculators (By Year)'!$J$12,SUM('Mortgage Calculators (By Year)'!K$22:K26),NA())) -> 0 | E26: =IF($B$20=Inputs!$B$18,IF($B26<='Mortgage Calculators (By Year)'!$C$9,SUM('Mortgage Calculators (By Year)'!E$22:E26),NA()),IF($B26<='Mortgage Calculators (By Year)'!$J$12,SUM('Mortgage Calculators (By Year)'!L$22:L26),NA())) -> 400 | F26: =IF($B$20=Inputs!$B$18,IF($B26<='Mortgage Calculators (By Year)'!$C$9,'Mortgage Calculators (By Year)'!F26,NA()),IF($B26<='Mortgage Calculators (By Year)'!$J$12,'Mortgage Calculators (By Year)'!M26,NA())) -> 0 | G26: =IF($B$20=Inputs!$B$18,IF($B26='Mortgage Calculators (By Year)'!$C$9,D26,""),IF($B26='Mortgage Calculators (By Year)'!$J$12,D26,"")) | H26: =IF($B$20=Inputs!$B$18,IF($B26='Mortgage Calculators (By Year)'!$C$9,E26,""),IF($B26='Mortgage Calculators (By Year)'!$J$12,E26,"")) | I26: =IF(B26=ROUND(Inputs!$K$10,0),$I$20,NA()) -> #N/A | K26: 4 | L26: =IF($K$20=Inputs!$B$18,IF($K26<='Mortgage Calculators (By Year)'!$C$9,'Mortgage Calculators (By Year)'!D26,NA()),IF($K26<='Mortgage Calculators (By Year)'!$J$12,'Mortgage Calculators (By Year)'!K26,NA())) -> 0 | M26: =IF($K$20=Inputs!$B$18,IF($K26<='Mortgage Calculators (By Year)'!$C$9,'Mortgage Calculators (By Year)'!E26,NA()),IF($K26<='Mortgage Calculators (By Year)'!$J$12,'Mortgage Calculators (By Year)'!L26,NA())) -> 100 | N26: =L26+M26 -> 100 | O26: =IF(K26=ROUND(Inputs!$K$10,0),$O$20,NA()) -> #N/A
B27: 5 | C27: =IF($B$20=Inputs!$B$18,IF($B27<='Mortgage Calculators (By Year)'!$C$9,SUM('Mortgage Calculators (By Year)'!C$22:C27),NA()),IF($B27<='Mortgage Calculators (By Year)'!$J$12,SUM('Mortgage Calculators (By Year)'!J$22:J27),NA())) -> 0 | D27: =IF($B$20=Inputs!$B$18,IF($B27<='Mortgage Calculators (By Year)'!$C$9,SUM('Mortgage Calculators (By Year)'!D$22:D27),NA()),IF($B27<='Mortgage Calculators (By Year)'!$J$12,SUM('Mortgage Calculators (By Year)'!K$22:K27),NA())) -> 0 | E27: =IF($B$20=Inputs!$B$18,IF($B27<='Mortgage Calculators (By Year)'!$C$9,SUM('Mortgage Calculators (By Year)'!E$22:E27),NA()),IF($B27<='Mortgage Calculators (By Year)'!$J$12,SUM('Mortgage Calculators (By Year)'!L$22:L27),NA())) -> 500 | F27: =IF($B$20=Inputs!$B$18,IF($B27<='Mortgage Calculators (By Year)'!$C$9,'Mortgage Calculators (By Year)'!F27,NA()),IF($B27<='Mortgage Calculators (By Year)'!$J$12,'Mortgage Calculators (By Year)'!M27,NA())) -> 0 | G27: =IF($B$20=Inputs!$B$18,IF($B27='Mortgage Calculators (By Year)'!$C$9,D27,""),IF($B27='Mortgage Calculators (By Year)'!$J$12,D27,"")) | H27: =IF($B$20=Inputs!$B$18,IF($B27='Mortgage Calculators (By Year)'!$C$9,E27,""),IF($B27='Mortgage Calculators (By Year)'!$J$12,E27,"")) | I27: =IF(B27=ROUND(Inputs!$K$10,0),$I$20,NA()) -> 3000 | K27: 5 | L27: =IF($K$20=Inputs!$B$18,IF($K27<='Mortgage Calculators (By Year)'!$C$9,'Mortgage Calculators (By Year)'!D27,NA()),IF($K27<='Mortgage Calculators (By Year)'!$J$12,'Mortgage Calculators (By Year)'!K27,NA())) -> 0 | M27: =IF($K$20=Inputs!$B$18,IF($K27<='Mortgage Calculators (By Year)'!$C$9,'Mortgage Calculators (By Year)'!E27,NA()),IF($K27<='Mortgage Calculators (By Year)'!$J$12,'Mortgage Calculators (By Year)'!L27,NA())) -> 100 | N27: =L27+M27 -> 100 | O27: =IF(K27=ROUND(Inputs!$K$10,0),$O$20,NA()) -> 100
B28: 6 | C28: =IF($B$20=Inputs!$B$18,IF($B28<='Mortgage Calculators (By Year)'!$C$9,SUM('Mortgage Calculators (By Year)'!C$22:C28),NA()),IF($B28<='Mortgage Calculators (By Year)'!$J$12,SUM('Mortgage Calculators (By Year)'!J$22:J28),NA())) -> 0 | D28: =IF($B$20=Inputs!$B$18,IF($B28<='Mortgage Calculators (By Year)'!$C$9,SUM('Mortgage Calculators (By Year)'!D$22:D28),NA()),IF($B28<='Mortgage Calculators (By Year)'!$J$12,SUM('Mortgage Calculators (By Year)'!K$22:K28),NA())) -> 0 | E28: =IF($B$20=Inputs!$B$18,IF($B28<='Mortgage Calculators (By Year)'!$C$9,SUM('Mortgage Calculators (By Year)'!E$22:E28),NA()),IF($B28<='Mortgage Calculators (By Year)'!$J$12,SUM('Mortgage Calculators (By Year)'!L$22:L28),NA())) -> 600 | F28: =IF($B$20=Inputs!$B$18,IF($B28<='Mortgage Calculators (By Year)'!$C$9,'Mortgage Calculators (By Year)'!F28,NA()),IF($B28<='Mortgage Calculators (By Year)'!$J$12,'Mortgage Calculators (By Year)'!M28,NA())) -> 0 | G28: =IF($B$20=Inputs!$B$18,IF($B28='Mortgage Calculators (By Year)'!$C$9,D28,""),IF($B28='Mortgage Calculators (By Year)'!$J$12,D28,"")) | H28: =IF($B$20=Inputs!$B$18,IF($B28='Mortgage Calculators (By Year)'!$C$9,E28,""),IF($B28='Mortgage Calculators (By Year)'!$J$12,E28,"")) | I28: =IF(B28=ROUND(Inputs!$K$10,0),$I$20,NA()) -> #N/A | K28: 6 | L28: =IF($K$20=Inputs!$B$18,IF($K28<='Mortgage Calculators (By Year)'!$C$9,'Mortgage Calculators (By Year)'!D28,NA()),IF($K28<='Mortgage Calculators (By Year)'!$J$12,'Mortgage Calculators (By Year)'!K28,NA())) -> 0 | M28: =IF($K$20=Inputs!$B$18,IF($K28<='Mortgage Calculators (By Year)'!$C$9,'Mortgage Calculators (By Year)'!E28,NA()),IF($K28<='Mortgage Calculators (By Year)'!$J$12,'Mortgage Calculators (By Year)'!L28,NA())) -> 100 | N28: =L28+M28 -> 100 | O28: =IF(K28=ROUND(Inputs!$K$10,0),$O$20,NA()) -> #N/A
B29: 7 | C29: =IF($B$20=Inputs!$B$18,IF($B29<='Mortgage Calculators (By Year)'!$C$9,SUM('Mortgage Calculators (By Year)'!C$22:C29),NA()),IF($B29<='Mortgage Calculators (By Year)'!$J$12,SUM('Mortgage Calculators (By Year)'!J$22:J29),NA())) -> 0 | D29: =IF($B$20=Inputs!$B$18,IF($B29<='Mortgage Calculators (By Year)'!$C$9,SUM('Mortgage Calculators (By Year)'!D$22:D29),NA()),IF($B29<='Mortgage Calculators (By Year)'!$J$12,SUM('Mortgage Calculators (By Year)'!K$22:K29),NA())) -> 0 | E29: =IF($B$20=Inputs!$B$18,IF($B29<='Mortgage Calculators (By Year)'!$C$9,SUM('Mortgage Calculators (By Year)'!E$22:E29),NA()),IF($B29<='Mortgage Calculators (By Year)'!$J$12,SUM('Mortgage Calculators (By Year)'!L$22:L29),NA())) -> 700 | F29: =IF($B$20=Inputs!$B$18,IF($B29<='Mortgage Calculators (By Year)'!$C$9,'Mortgage Calculators (By Year)'!F29,NA()),IF($B29<='Mortgage Calculators (By Year)'!$J$12,'Mortgage Calculators (By Year)'!M29,NA())) -> 0 | G29: =IF($B$20=Inputs!$B$18,IF($B29='Mortgage Calculators (By Year)'!$C$9,D29,""),IF($B29='Mortgage Calculators (By Year)'!$J$12,D29,"")) | H29: =IF($B$20=Inputs!$B$18,IF($B29='Mortgage Calculators (By Year)'!$C$9,E29,""),IF($B29='Mortgage Calculators (By Year)'!$J$12,E29,"")) | I29: =IF(B29=ROUND(Inputs!$K$10,0),$I$20,NA()) -> #N/A | K29: 7 | L29: =IF($K$20=Inputs!$B$18,IF($K29<='Mortgage Calculators (By Year)'!$C$9,'Mortgage Calculators (By Year)'!D29,NA()),IF($K29<='Mortgage Calculators (By Year)'!$J$12,'Mortgage Calculators (By Year)'!K29,NA())) -> 0 | M29: =IF($K$20=Inputs!$B$18,IF($K29<='Mortgage Calculators (By Year)'!$C$9,'Mortgage Calculators (By Year)'!E29,NA()),IF($K29<='Mortgage Calculators (By Year)'!$J$12,'Mortgage Calculators (By Year)'!L29,NA())) -> 100 | N29: =L29+M29 -> 100 | O29: =IF(K29=ROUND(Inputs!$K$10,0),$O$20,NA()) -> #N/A
B30: 8 | C30: =IF($B$20=Inputs!$B$18,IF($B30<='Mortgage Calculators (By Year)'!$C$9,SUM('Mortgage Calculators (By Year)'!C$22:C30),NA()),IF($B30<='Mortgage Calculators (By Year)'!$J$12,SUM('Mortgage Calculators (By Year)'!J$22:J30),NA())) -> 0 | D30: =IF($B$20=Inputs!$B$18,IF($B30<='Mortgage Calculators (By Year)'!$C$9,SUM('Mortgage Calculators (By Year)'!D$22:D30),NA()),IF($B30<='Mortgage Calculators (By Year)'!$J$12,SUM('Mortgage Calculators (By Year)'!K$22:K30),NA())) -> 0 | E30: =IF($B$20=Inputs!$B$18,IF($B30<='Mortgage Calculators (By Year)'!$C$9,SUM('Mortgage Calculators (By Year)'!E$22:E30),NA()),IF($B30<='Mortgage Calculators (By Year)'!$J$12,SUM('Mortgage Calculators (By Year)'!L$22:L30),NA())) -> 800 | F30: =IF($B$20=Inputs!$B$18,IF($B30<='Mortgage Calculators (By Year)'!$C$9,'Mortgage Calculators (By Year)'!F30,NA()),IF($B30<='Mortgage Calculators (By Year)'!$J$12,'Mortgage Calculators (By Year)'!M30,NA())) -> 0 | G30: =IF($B$20=Inputs!$B$18,IF($B30='Mortgage Calculators (By Year)'!$C$9,D30,""),IF($B30='Mortgage Calculators (By Year)'!$J$12,D30,"")) | H30: =IF($B$20=Inputs!$B$18,IF($B30='Mortgage Calculators (By Year)'!$C$9,E30,""),IF($B30='Mortgage Calculators (By Year)'!$J$12,E30,"")) | I30: =IF(B30=ROUND(Inputs!$K$10,0),$I$20,NA()) -> #N/A | K30: 8 | L30: =IF($K$20=Inputs!$B$18,IF($K30<='Mortgage Calculators (By Year)'!$C$9,'Mortgage Calculators (By Year)'!D30,NA()),IF($K30<='Mortgage Calculators (By Year)'!$J$12,'Mortgage Calculators (By Year)'!K30,NA())) -> 0 | M30: =IF($K$20=Inputs!$B$18,IF($K30<='Mortgage Calculators (By Year)'!$C$9,'Mortgage Calculators (By Year)'!E30,NA()),IF($K30<='Mortgage Calculators (By Year)'!$J$12,'Mortgage Calculators (By Year)'!L30,NA())) -> 100 | N30: =L30+M30 -> 100 | O30: =IF(K30=ROUND(Inputs!$K$10,0),$O$20,NA()) -> #N/A
B31: 9 | C31: =IF($B$20=Inputs!$B$18,IF($B31<='Mortgage Calculators (By Year)'!$C$9,SUM('Mortgage Calculators (By Year)'!C$22:C31),NA()),IF($B31<='Mortgage Calculators (By Year)'!$J$12,SUM('Mortgage Calculators (By Year)'!J$22:J31),NA())) -> 0 | D31: =IF($B$20=Inputs!$B$18,IF($B31<='Mortgage Calculators (By Year)'!$C$9,SUM('Mortgage Calculators (By Year)'!D$22:D31),NA()),IF($B31<='Mortgage Calculators (By Year)'!$J$12,SUM('Mortgage Calculators (By Year)'!K$22:K31),NA())) -> 0 | E31: =IF($B$20=Inputs!$B$18,IF($B31<='Mortgage Calculators (By Year)'!$C$9,SUM('Mortgage Calculators (By Year)'!E$22:E31),NA()),IF($B31<='Mortgage Calculators (By Year)'!$J$12,SUM('Mortgage Calculators (By Year)'!L$22:L31),NA())) -> 900 | F31: =IF($B$20=Inputs!$B$18,IF($B31<='Mortgage Calculators (By Year)'!$C$9,'Mortgage Calculators (By Year)'!F31,NA()),IF($B31<='Mortgage Calculators (By Year)'!$J$12,'Mortgage Calculators (By Year)'!M31,NA())) -> 0 | G31: =IF($B$20=Inputs!$B$18,IF($B31='Mortgage Calculators (By Year)'!$C$9,D31,""),IF($B31='Mortgage Calculators (By Year)'!$J$12,D31,"")) | H31: =IF($B$20=Inputs!$B$18,IF($B31='Mortgage Calculators (By Year)'!$C$9,E31,""),IF($B31='Mortgage Calculators (By Year)'!$J$12,E31,"")) | I31: =IF(B31=ROUND(Inputs!$K$10,0),$I$20,NA()) -> #N/A | K31: 9 | L31: =IF($K$20=Inputs!$B$18,IF($K31<='Mortgage Calculators (By Year)'!$C$9,'Mortgage Calculators (By Year)'!D31,NA()),IF($K31<='Mortgage Calculators (By Year)'!$J$12,'Mortgage Calculators (By Year)'!K31,NA())) -> 0 | M31: =IF($K$20=Inputs!$B$18,IF($K31<='Mortgage Calculators (By Year)'!$C$9,'Mortgage Calculators (By Year)'!E31,NA()),IF($K31<='Mortgage Calculators (By Year)'!$J$12,'Mortgage Calculators (By Year)'!L31,NA())) -> 100 | N31: =L31+M31 -> 100 | O31: =IF(K31=ROUND(Inputs!$K$10,0),$O$20,NA()) -> #N/A
B32: 10 | C32: =IF($B$20=Inputs!$B$18,IF($B32<='Mortgage Calculators (By Year)'!$C$9,SUM('Mortgage Calculators (By Year)'!C$22:C32),NA()),IF($B32<='Mortgage Calculators (By Year)'!$J$12,SUM('Mortgage Calculators (By Year)'!J$22:J32),NA())) -> 0 | D32: =IF($B$20=Inputs!$B$18,IF($B32<='Mortgage Calculators (By Year)'!$C$9,SUM('Mortgage Calculators (By Year)'!D$22:D32),NA()),IF($B32<='Mortgage Calculators (By Year)'!$J$12,SUM('Mortgage Calculators (By Year)'!K$22:K32),NA())) -> 0 | E32: =IF($B$20=Inputs!$B$18,IF($B32<='Mortgage Calculators (By Year)'!$C$9,SUM('Mortgage Calculators (By Year)'!E$22:E32),NA()),IF($B32<='Mortgage Calculators (By Year)'!$J$12,SUM('Mortgage Calculators (By Year)'!L$22:L32),NA())) -> 1000 | F32: =IF($B$20=Inputs!$B$18,IF($B32<='Mortgage Calculators (By Year)'!$C$9,'Mortgage Calculators (By Year)'!F32,NA()),IF($B32<='Mortgage Calculators (By Year)'!$J$12,'Mortgage Calculators (By Year)'!M32,NA())) -> 0 | G32: =IF($B$20=Inputs!$B$18,IF($B32='Mortgage Calculators (By Year)'!$C$9,D32,""),IF($B32='Mortgage Calculators (By Year)'!$J$12,D32,"")) | H32: =IF($B$20=Inputs!$B$18,IF($B32='Mortgage Calculators (By Year)'!$C$9,E32,""),IF($B32='Mortgage Calculators (By Year)'!$J$12,E32,"")) | I32: =IF(B32=ROUND(Inputs!$K$10,0),$I$20,NA()) -> #N/A | K32: 10 | L32: =IF($K$20=Inputs!$B$18,IF($K32<='Mortgage Calculators (By Year)'!$C$9,'Mortgage Calculators (By Year)'!D32,NA()),IF($K32<='Mortgage Calculators (By Year)'!$J$12,'Mortgage Calculators (By Year)'!K32,NA())) -> 0 | M32: =IF($K$20=Inputs!$B$18,IF($K32<='Mortgage Calculators (By Year)'!$C$9,'Mortgage Calculators (By Year)'!E32,NA()),IF($K32<='Mortgage Calculators (By Year)'!$J$12,'Mortgage Calculators (By Year)'!L32,NA())) -> 100 | N32: =L32+M32 -> 100 | O32: =IF(K32=ROUND(Inputs!$K$10,0),$O$20,NA()) -> #N/A
B33: 11 | C33: =IF($B$20=Inputs!$B$18,IF($B33<='Mortgage Calculators (By Year)'!$C$9,SUM('Mortgage Calculators (By Year)'!C$22:C33),NA()),IF($B33<='Mortgage Calculators (By Year)'!$J$12,SUM('Mortgage Calculators (By Year)'!J$22:J33),NA())) -> 0 | D33: =IF($B$20=Inputs!$B$18,IF($B33<='Mortgage Calculators (By Year)'!$C$9,SUM('Mortgage Calculators (By Year)'!D$22:D33),NA()),IF($B33<='Mortgage Calculators (By Year)'!$J$12,SUM('Mortgage Calculators (By Year)'!K$22:K33),NA())) -> 0 | E33: =IF($B$20=Inputs!$B$18,IF($B33<='Mortgage Calculators (By Year)'!$C$9,SUM('Mortgage Calculators (By Year)'!E$22:E33),NA()),IF($B33<='Mortgage Calculators (By Year)'!$J$12,SUM('Mortgage Calculators (By Year)'!L$22:L33),NA())) -> 1100 | F33: =IF($B$20=Inputs!$B$18,IF($B33<='Mortgage Calculators (By Year)'!$C$9,'Mortgage Calculators (By Year)'!F33,NA()),IF($B33<='Mortgage Calculators (By Year)'!$J$12,'Mortgage Calculators (By Year)'!M33,NA())) -> 0 | G33: =IF($B$20=Inputs!$B$18,IF($B33='Mortgage Calculators (By Year)'!$C$9,D33,""),IF($B33='Mortgage Calculators (By Year)'!$J$12,D33,"")) | H33: =IF($B$20=Inputs!$B$18,IF($B33='Mortgage Calculators (By Year)'!$C$9,E33,""),IF($B33='Mortgage Calculators (By Year)'!$J$12,E33,"")) | I33: =IF(B33=ROUND(Inputs!$K$10,0),$I$20,NA()) -> #N/A | K33: 11 | L33: =IF($K$20=Inputs!$B$18,IF($K33<='Mortgage Calculators (By Year)'!$C$9,'Mortgage Calculators (By Year)'!D33,NA()),IF($K33<='Mortgage Calculators (By Year)'!$J$12,'Mortgage Calculators (By Year)'!K33,NA())) -> 0 | M33: =IF($K$20=Inputs!$B$18,IF($K33<='Mortgage Calculators (By Year)'!$C$9,'Mortgage Calculators (By Year)'!E33,NA()),IF($K33<='Mortgage Calculators (By Year)'!$J$12,'Mortgage Calculators (By Year)'!L33,NA())) -> 100 | N33: =L33+M33 -> 100 | O33: =IF(K33=ROUND(Inputs!$K$10,0),$O$20,NA()) -> #N/A
B34: 12 | C34: =IF($B$20=Inputs!$B$18,IF($B34<='Mortgage Calculators (By Year)'!$C$9,SUM('Mortgage Calculators (By Year)'!C$22:C34),NA()),IF($B34<='Mortgage Calculators (By Year)'!$J$12,SUM('Mortgage Calculators (By Year)'!J$22:J34),NA())) -> 0 | D34: =IF($B$20=Inputs!$B$18,IF($B34<='Mortgage Calculators (By Year)'!$C$9,SUM('Mortgage Calculators (By Year)'!D$22:D34),NA()),IF($B34<='Mortgage Calculators (By Year)'!$J$12,SUM('Mortgage Calculators (By Year)'!K$22:K34),NA())) -> 0 | E34: =IF($B$20=Inputs!$B$18,IF($B34<='Mortgage Calculators (By Year)'!$C$9,SUM('Mortgage Calculators (By Year)'!E$22:E34),NA()),IF($B34<='Mortgage Calculators (By Year)'!$J$12,SUM('Mortgage Calculators (By Year)'!L$22:L34),NA())) -> 1200 | F34: =IF($B$20=Inputs!$B$18,IF($B34<='Mortgage Calculators (By Year)'!$C$9,'Mortgage Calculators (By Year)'!F34,NA()),IF($B34<='Mortgage Calculators (By Year)'!$J$12,'Mortgage Calculators (By Year)'!M34,NA())) -> 0 | G34: =IF($B$20=Inputs!$B$18,IF($B34='Mortgage Calculators (By Year)'!$C$9,D34,""),IF($B34='Mortgage Calculators (By Year)'!$J$12,D34,"")) | H34: =IF($B$20=Inputs!$B$18,IF($B34='Mortgage Calculators (By Year)'!$C$9,E34,""),IF($B34='Mortgage Calculators (By Year)'!$J$12,E34,"")) | I34: =IF(B34=ROUND(Inputs!$K$10,0),$I$20,NA()) -> #N/A | K34: 12 | L34: =IF($K$20=Inputs!$B$18,IF($K34<='Mortgage Calculators (By Year)'!$C$9,'Mortgage Calculators (By Year)'!D34,NA()),IF($K34<='Mortgage Calculators (By Year)'!$J$12,'Mortgage Calculators (By Year)'!K34,NA())) -> 0 | M34: =IF($K$20=Inputs!$B$18,IF($K34<='Mortgage Calculators (By Year)'!$C$9,'Mortgage Calculators (By Year)'!E34,NA()),IF($K34<='Mortgage Calculators (By Year)'!$J$12,'Mortgage Calculators (By Year)'!L34,NA())) -> 100 | N34: =L34+M34 -> 100 | O34: =IF(K34=ROUND(Inputs!$K$10,0),$O$20,NA()) -> #N/A
... B73: 51 | C73: =IF($B$20=Inputs!$B$18,IF($B73<='Mortgage Calculators (By Year)'!$C$9,SUM('Mortgage Calculators (By Year)'!C$22:C73),NA()),IF($B73<='Mortgage Calculators (By Year)'!$J$12,SUM('Mortgage Calculators (By Year)'!J$22:J73),NA())) -> #N/A | D73: =IF($B$20=Inputs!$B$18,IF($B73<='Mortgage Calculators (By Year)'!$C$9,SUM('Mortgage Calculators (By Year)'!D$22:D73),NA()),IF($B73<='Mortgage Calculators (By Year)'!$J$12,SUM('Mortgage Calculators (By Year)'!K$22:K73),NA())) -> #N/A | E73: =IF($B$20=Inputs!$B$18,IF($B73<='Mortgage Calculators (By Year)'!$C$9,SUM('Mortgage Calculators (By Year)'!E$22:E73),NA()),IF($B73<='Mortgage Calculators (By Year)'!$J$12,SUM('Mortgage Calculators (By Year)'!L$22:L73),NA())) -> #N/A | F73: =IF($B$20=Inputs!$B$18,IF($B73<='Mortgage Calculators (By Year)'!$C$9,'Mortgage Calculators (By Year)'!F73,NA()),IF($B73<='Mortgage Calculators (By Year)'!$J$12,'Mortgage Calculators (By Year)'!M73,NA())) -> #N/A | G73: =IF($B$20=Inputs!$B$18,IF($B73='Mortgage Calculators (By Year)'!$C$9,D73,""),IF($B73='Mortgage Calculators (By Year)'!$J$12,D73,"")) | H73: =IF($B$20=Inputs!$B$18,IF($B73='Mortgage Calculators (By Year)'!$C$9,E73,""),IF($B73='Mortgage Calculators (By Year)'!$J$12,E73,"")) | I73: =IF(B73=ROUND(Inputs!$K$10,0),$I$20,NA()) -> #N/A | K73: 51 | L73: =IF($K$20=Inputs!$B$18,IF($K73<='Mortgage Calculators (By Year)'!$C$9,'Mortgage Calculators (By Year)'!D73,NA()),IF($K73<='Mortgage Calculators (By Year)'!$J$12,'Mortgage Calculators (By Year)'!K73,NA())) -> #N/A | M73: =IF($K$20=Inputs!$B$18,IF($K73<='Mortgage Calculators (By Year)'!$C$9,'Mortgage Calculators (By Year)'!E73,NA()),IF($K73<='Mortgage Calculators (By Year)'!$J$12,'Mortgage Calculators (By Year)'!L73,NA())) -> #N/A | N73: =L73+M73 -> #N/A | O73: =IF(K73=ROUND(Inputs!$K$10,0),$O$20,NA()) -> #N/A
B75: CHARTS FOR ANALYSIS SUMMARY TAB (PG 2)
B76: Property and Equity Growth | G76: Annual Payments
B77: ='Analysis Summary'!$E$6 -> Principal & Interest Loan (P&I) | E77: =_xlfn.XLOOKUP(Inputs!$K$10,'RE Calculations'!$B$79:$B$130,'RE Calculations'!$C$79:$C$130) -> 2086720.4 | G77: ='Analysis Summary'!$E$6 -> Principal & Interest Loan (P&I) | L77: =_xlfn.MAXIFS(H79:I130,H79:I130,">0") -> 10874230
B78: Year | C78: Property Value | D78: Equity Value | E78: Holding Period | G78: Year | H78: Gross Profit | I78: Net Profit | J78: Gross Annualized ROI | K78: Net Annualized ROI | L78: Holding Period
B79: 0 | C79: =IF($B$77=Inputs!$B$18,IF($B79<='Mortgage Calculators (By Year)'!$C$9,'Forecast (By Year)'!G4,NA()),IF($B79<='Mortgage Calculators (By Year)'!$J$12,'Forecast (By Year)'!AE4,NA())) -> 1635000 | D79: =IF($B$77=Inputs!$B$18,IF($B79<='Mortgage Calculators (By Year)'!$C$9,'Forecast (By Year)'!H4,NA()),IF($B79<='Mortgage Calculators (By Year)'!$J$12,'Forecast (By Year)'!AF4,NA())) -> 1635000 | E79: =IF(B79=ROUND(Inputs!$K$10,0),$E$77,NA()) -> #N/A | G79: 0 | H79: =IF($K$20=Inputs!$B$18,IF($G79<='Mortgage Calculators (By Year)'!$C$9,'Forecast (By Year)'!V4,NA()),IF($G79<='Mortgage Calculators (By Year)'!$J$12,'Forecast (By Year)'!AT4,NA())) -> -3227 | I79: =IF($K$20=Inputs!$B$18,IF($G79<='Mortgage Calculators (By Year)'!$C$9,'Forecast (By Year)'!Y4,NA()),IF($G79<='Mortgage Calculators (By Year)'!$J$12,'Forecast (By Year)'!AW4,NA())) -> -3227 | J79: =IF($K$20=Inputs!$B$18,IF($G79<='Mortgage Calculators (By Year)'!$C$9,'Forecast (By Year)'!X4,NA()),IF($G79<='Mortgage Calculators (By Year)'!$J$12,'Forecast (By Year)'!AV4,NA())) -> - | K79: =IF($K$20=Inputs!$B$18,IF($G79<='Mortgage Calculators (By Year)'!$C$9,'Forecast (By Year)'!AA4,NA()),IF($G79<='Mortgage Calculators (By Year)'!$J$12,'Forecast (By Year)'!AY4,NA())) -> - | L79: =IF(G79=ROUND(Inputs!$K$10,0),$L$77,NA()) -> #N/A
B80: 1 | C80: =IF($B$77=Inputs!$B$18,IF($B80<='Mortgage Calculators (By Year)'!$C$9,'Forecast (By Year)'!G5,NA()),IF($B80<='Mortgage Calculators (By Year)'!$J$12,'Forecast (By Year)'!AE5,NA())) -> 1716750 | D80: =IF($B$77=Inputs!$B$18,IF($B80<='Mortgage Calculators (By Year)'!$C$9,'Forecast (By Year)'!H5,NA()),IF($B80<='Mortgage Calculators (By Year)'!$J$12,'Forecast (By Year)'!AF5,NA())) -> 1716750 | E80: =IF(B80=ROUND(Inputs!$K$10,0),$E$77,NA()) -> #N/A | G80: 1 | H80: =IF($K$20=Inputs!$B$18,IF($G80<='Mortgage Calculators (By Year)'!$C$9,'Forecast (By Year)'!V5,NA()),IF($G80<='Mortgage Calculators (By Year)'!$J$12,'Forecast (By Year)'!AT5,NA())) -> 76888 | I80: =IF($K$20=Inputs!$B$18,IF($G80<='Mortgage Calculators (By Year)'!$C$9,'Forecast (By Year)'!Y5,NA()),IF($G80<='Mortgage Calculators (By Year)'!$J$12,'Forecast (By Year)'!AW5,NA())) -> 150700 | J80: =IF($K$20=Inputs!$B$18,IF($G80<='Mortgage Calculators (By Year)'!$C$9,'Forecast (By Year)'!X5,NA()),IF($G80<='Mortgage Calculators (By Year)'!$J$12,'Forecast (By Year)'!AV5,NA())) -> 0.048024174 | K80: =IF($K$20=Inputs!$B$18,IF($G80<='Mortgage Calculators (By Year)'!$C$9,'Forecast (By Year)'!AA5,NA()),IF($G80<='Mortgage Calculators (By Year)'!$J$12,'Forecast (By Year)'!AY5,NA())) -> 0.094127082 | L80: =IF(G80=ROUND(Inputs!$K$10,0),$L$77,NA()) -> #N/A
B81: 2 | C81: =IF($B$77=Inputs!$B$18,IF($B81<='Mortgage Calculators (By Year)'!$C$9,'Forecast (By Year)'!G6,NA()),IF($B81<='Mortgage Calculators (By Year)'!$J$12,'Forecast (By Year)'!AE6,NA())) -> 1802587.5 | D81: =IF($B$77=Inputs!$B$18,IF($B81<='Mortgage Calculators (By Year)'!$C$9,'Forecast (By Year)'!H6,NA()),IF($B81<='Mortgage Calculators (By Year)'!$J$12,'Forecast (By Year)'!AF6,NA())) -> 1802587.5 | E81: =IF(B81=ROUND(Inputs!$K$10,0),$E$77,NA()) -> #N/A | G81: 2 | H81: =IF($K$20=Inputs!$B$18,IF($G81<='Mortgage Calculators (By Year)'!$C$9,'Forecast (By Year)'!V6,NA()),IF($G81<='Mortgage Calculators (By Year)'!$J$12,'Forecast (By Year)'!AT6,NA())) -> 161008.75 | I81: =IF($K$20=Inputs!$B$18,IF($G81<='Mortgage Calculators (By Year)'!$C$9,'Forecast (By Year)'!Y6,NA()),IF($G81<='Mortgage Calculators (By Year)'!$J$12,'Forecast (By Year)'!AW6,NA())) -> 313216.25 | J81: =IF($K$20=Inputs!$B$18,IF($G81<='Mortgage Calculators (By Year)'!$C$9,'Forecast (By Year)'!X6,NA()),IF($G81<='Mortgage Calculators (By Year)'!$J$12,'Forecast (By Year)'!AV6,NA())) -> 0.050282959 | K81: =IF($K$20=Inputs!$B$18,IF($G81<='Mortgage Calculators (By Year)'!$C$9,'Forecast (By Year)'!AA6,NA()),IF($G81<='Mortgage Calculators (By Year)'!$J$12,'Forecast (By Year)'!AY6,NA())) -> 0.097817292 | L81: =IF(G81=ROUND(Inputs!$K$10,0),$L$77,NA()) -> #N/A
B82: 3 | C82: =IF($B$77=Inputs!$B$18,IF($B82<='Mortgage Calculators (By Year)'!$C$9,'Forecast (By Year)'!G7,NA()),IF($B82<='Mortgage Calculators (By Year)'!$J$12,'Forecast (By Year)'!AE7,NA())) -> 1892716.9 | D82: =IF($B$77=Inputs!$B$18,IF($B82<='Mortgage Calculators (By Year)'!$C$9,'Forecast (By Year)'!H7,NA()),IF($B82<='Mortgage Calculators (By Year)'!$J$12,'Forecast (By Year)'!AF7,NA())) -> 1892716.9 | E82: =IF(B82=ROUND(Inputs!$K$10,0),$E$77,NA()) -> #N/A | G82: 3 | H82: =IF($K$20=Inputs!$B$18,IF($G82<='Mortgage Calculators (By Year)'!$C$9,'Forecast (By Year)'!V7,NA()),IF($G82<='Mortgage Calculators (By Year)'!$J$12,'Forecast (By Year)'!AT7,NA())) -> 249335.54 | I82: =IF($K$20=Inputs!$B$18,IF($G82<='Mortgage Calculators (By Year)'!$C$9,'Forecast (By Year)'!Y7,NA()),IF($G82<='Mortgage Calculators (By Year)'!$J$12,'Forecast (By Year)'!AW7,NA())) -> 484751.21 | J82: =IF($K$20=Inputs!$B$18,IF($G82<='Mortgage Calculators (By Year)'!$C$9,'Forecast (By Year)'!X7,NA()),IF($G82<='Mortgage Calculators (By Year)'!$J$12,'Forecast (By Year)'!AV7,NA())) -> 0.051911583 | K82: =IF($K$20=Inputs!$B$18,IF($G82<='Mortgage Calculators (By Year)'!$C$9,'Forecast (By Year)'!AA7,NA()),IF($G82<='Mortgage Calculators (By Year)'!$J$12,'Forecast (By Year)'!AY7,NA())) -> 0.10092505 | L82: =IF(G82=ROUND(Inputs!$K$10,0),$L$77,NA()) -> #N/A
B83: 4 | C83: =IF($B$77=Inputs!$B$18,IF($B83<='Mortgage Calculators (By Year)'!$C$9,'Forecast (By Year)'!G8,NA()),IF($B83<='Mortgage Calculators (By Year)'!$J$12,'Forecast (By Year)'!AE8,NA())) -> 1987352.7 | D83: =IF($B$77=Inputs!$B$18,IF($B83<='Mortgage Calculators (By Year)'!$C$9,'Forecast (By Year)'!H8,NA()),IF($B83<='Mortgage Calculators (By Year)'!$J$12,'Forecast (By Year)'!AF8,NA())) -> 1987352.7 | E83: =IF(B83=ROUND(Inputs!$K$10,0),$E$77,NA()) -> #N/A | G83: 4 | H83: =IF($K$20=Inputs!$B$18,IF($G83<='Mortgage Calculators (By Year)'!$C$9,'Forecast (By Year)'!V8,NA()),IF($G83<='Mortgage Calculators (By Year)'!$J$12,'Forecast (By Year)'!AT8,NA())) -> 342078.66 | I83: =IF($K$20=Inputs!$B$18,IF($G83<='Mortgage Calculators (By Year)'!$C$9,'Forecast (By Year)'!Y8,NA()),IF($G83<='Mortgage Calculators (By Year)'!$J$12,'Forecast (By Year)'!AW8,NA())) -> 665755.82 | J83: =IF($K$20=Inputs!$B$18,IF($G83<='Mortgage Calculators (By Year)'!$C$9,'Forecast (By Year)'!X8,NA()),IF($G83<='Mortgage Calculators (By Year)'!$J$12,'Forecast (By Year)'!AV8,NA())) -> 0.053415505 | K83: =IF($K$20=Inputs!$B$18,IF($G83<='Mortgage Calculators (By Year)'!$C$9,'Forecast (By Year)'!AA8,NA()),IF($G83<='Mortgage Calculators (By Year)'!$J$12,'Forecast (By Year)'!AY8,NA())) -> 0.10395762 | L83: =IF(G83=ROUND(Inputs!$K$10,0),$L$77,NA()) -> #N/A
B84: 5 | C84: =IF($B$77=Inputs!$B$18,IF($B84<='Mortgage Calculators (By Year)'!$C$9,'Forecast (By Year)'!G9,NA()),IF($B84<='Mortgage Calculators (By Year)'!$J$12,'Forecast (By Year)'!AE9,NA())) -> 2086720.4 | D84: =IF($B$77=Inputs!$B$18,IF($B84<='Mortgage Calculators (By Year)'!$C$9,'Forecast (By Year)'!H9,NA()),IF($B84<='Mortgage Calculators (By Year)'!$J$12,'Forecast (By Year)'!AF9,NA())) -> 2086720.4 | E84: =IF(B84=ROUND(Inputs!$K$10,0),$E$77,NA()) -> 2086720.4 | G84: 5 | H84: =IF($K$20=Inputs!$B$18,IF($G84<='Mortgage Calculators (By Year)'!$C$9,'Forecast (By Year)'!V9,NA()),IF($G84<='Mortgage Calculators (By Year)'!$J$12,'Forecast (By Year)'!AT9,NA())) -> 439458.95 | I84: =IF($K$20=Inputs!$B$18,IF($G84<='Mortgage Calculators (By Year)'!$C$9,'Forecast (By Year)'!Y9,NA()),IF($G84<='Mortgage Calculators (By Year)'!$J$12,'Forecast (By Year)'!AW9,NA())) -> 856703.56 | J84: =IF($K$20=Inputs!$B$18,IF($G84<='Mortgage Calculators (By Year)'!$C$9,'Forecast (By Year)'!X9,NA()),IF($G84<='Mortgage Calculators (By Year)'!$J$12,'Forecast (By Year)'!AV9,NA())) -> 0.054897131 | K84: =IF($K$20=Inputs!$B$18,IF($G84<='Mortgage Calculators (By Year)'!$C$9,'Forecast (By Year)'!AA9,NA()),IF($G84<='Mortgage Calculators (By Year)'!$J$12,'Forecast (By Year)'!AY9,NA())) -> 0.10701925 | L84: =IF(G84=ROUND(Inputs!$K$10,0),$L$77,NA()) -> 10874230
B85: 6 | C85: =IF($B$77=Inputs!$B$18,IF($B85<='Mortgage Calculators (By Year)'!$C$9,'Forecast (By Year)'!G10,NA()),IF($B85<='Mortgage Calculators (By Year)'!$J$12,'Forecast (By Year)'!AE10,NA())) -> 2191056.4 | D85: =IF($B$77=Inputs!$B$18,IF($B85<='Mortgage Calculators (By Year)'!$C$9,'Forecast (By Year)'!H10,NA()),IF($B85<='Mortgage Calculators (By Year)'!$J$12,'Forecast (By Year)'!AF10,NA())) -> 2191056.4 | E85: =IF(B85=ROUND(Inputs!$K$10,0),$E$77,NA()) -> #N/A | G85: 6 | H85: =IF($K$20=Inputs!$B$18,IF($G85<='Mortgage Calculators (By Year)'!$C$9,'Forecast (By Year)'!V10,NA()),IF($G85<='Mortgage Calculators (By Year)'!$J$12,'Forecast (By Year)'!AT10,NA())) -> 541708.24 | I85: =IF($K$20=Inputs!$B$18,IF($G85<='Mortgage Calculators (By Year)'!$C$9,'Forecast (By Year)'!Y10,NA()),IF($G85<='Mortgage Calculators (By Year)'!$J$12,'Forecast (By Year)'!AW10,NA())) -> 1058091.6 | J85: =IF($K$20=Inputs!$B$18,IF($G85<='Mortgage Calculators (By Year)'!$C$9,'Forecast (By Year)'!X10,NA()),IF($G85<='Mortgage Calculators (By Year)'!$J$12,'Forecast (By Year)'!AV10,NA())) -> 0.056391746 | K85: =IF($K$20=Inputs!$B$18,IF($G85<='Mortgage Calculators (By Year)'!$C$9,'Forecast (By Year)'!AA10,NA()),IF($G85<='Mortgage Calculators (By Year)'!$J$12,'Forecast (By Year)'!AY10,NA())) -> 0.11014717 | L85: =IF(G85=ROUND(Inputs!$K$10,0),$L$77,NA()) -> #N/A
B86: 7 | C86: =IF($B$77=Inputs!$B$18,IF($B86<='Mortgage Calculators (By Year)'!$C$9,'Forecast (By Year)'!G11,NA()),IF($B86<='Mortgage Calculators (By Year)'!$J$12,'Forecast (By Year)'!AE11,NA())) -> 2300609.2 | D86: =IF($B$77=Inputs!$B$18,IF($B86<='Mortgage Calculators (By Year)'!$C$9,'Forecast (By Year)'!H11,NA()),IF($B86<='Mortgage Calculators (By Year)'!$J$12,'Forecast (By Year)'!AF11,NA())) -> 2300609.2 | E86: =IF(B86=ROUND(Inputs!$K$10,0),$E$77,NA()) -> #N/A | G86: 7 | H86: =IF($K$20=Inputs!$B$18,IF($G86<='Mortgage Calculators (By Year)'!$C$9,'Forecast (By Year)'!V11,NA()),IF($G86<='Mortgage Calculators (By Year)'!$J$12,'Forecast (By Year)'!AT11,NA())) -> 649070.01 | I86: =IF($K$20=Inputs!$B$18,IF($G86<='Mortgage Calculators (By Year)'!$C$9,'Forecast (By Year)'!Y11,NA()),IF($G86<='Mortgage Calculators (By Year)'!$J$12,'Forecast (By Year)'!AW11,NA())) -> 1270441.9 | J86: =IF($K$20=Inputs!$B$18,IF($G86<='Mortgage Calculators (By Year)'!$C$9,'Forecast (By Year)'!X11,NA()),IF($G86<='Mortgage Calculators (By Year)'!$J$12,'Forecast (By Year)'!AV11,NA())) -> 0.057915505 | K86: =IF($K$20=Inputs!$B$18,IF($G86<='Mortgage Calculators (By Year)'!$C$9,'Forecast (By Year)'!AA11,NA()),IF($G86<='Mortgage Calculators (By Year)'!$J$12,'Forecast (By Year)'!AY11,NA())) -> 0.11335955 | L86: =IF(G86=ROUND(Inputs!$K$10,0),$L$77,NA()) -> #N/A
B87: 8 | C87: =IF($B$77=Inputs!$B$18,IF($B87<='Mortgage Calculators (By Year)'!$C$9,'Forecast (By Year)'!G12,NA()),IF($B87<='Mortgage Calculators (By Year)'!$J$12,'Forecast (By Year)'!AE12,NA())) -> 2415639.7 | D87: =IF($B$77=Inputs!$B$18,IF($B87<='Mortgage Calculators (By Year)'!$C$9,'Forecast (By Year)'!H12,NA()),IF($B87<='Mortgage Calculators (By Year)'!$J$12,'Forecast (By Year)'!AF12,NA())) -> 2415639.7 | E87: =IF(B87=ROUND(Inputs!$K$10,0),$E$77,NA()) -> #N/A | G87: 8 | H87: =IF($K$20=Inputs!$B$18,IF($G87<='Mortgage Calculators (By Year)'!$C$9,'Forecast (By Year)'!V12,NA()),IF($G87<='Mortgage Calculators (By Year)'!$J$12,'Forecast (By Year)'!AT12,NA())) -> 761799.86 | I87: =IF($K$20=Inputs!$B$18,IF($G87<='Mortgage Calculators (By Year)'!$C$9,'Forecast (By Year)'!Y12,NA()),IF($G87<='Mortgage Calculators (By Year)'!$J$12,'Forecast (By Year)'!AW12,NA())) -> 1494302.7 | J87: =IF($K$20=Inputs!$B$18,IF($G87<='Mortgage Calculators (By Year)'!$C$9,'Forecast (By Year)'!X12,NA()),IF($G87<='Mortgage Calculators (By Year)'!$J$12,'Forecast (By Year)'!AV12,NA())) -> 0.059477437 | K87: =IF($K$20=Inputs!$B$18,IF($G87<='Mortgage Calculators (By Year)'!$C$9,'Forecast (By Year)'!AA12,NA()),IF($G87<='Mortgage Calculators (By Year)'!$J$12,'Forecast (By Year)'!AY12,NA())) -> 0.11666751 | L87: =IF(G87=ROUND(Inputs!$K$10,0),$L$77,NA()) -> #N/A
B88: 9 | C88: =IF($B$77=Inputs!$B$18,IF($B88<='Mortgage Calculators (By Year)'!$C$9,'Forecast (By Year)'!G13,NA()),IF($B88<='Mortgage Calculators (By Year)'!$J$12,'Forecast (By Year)'!AE13,NA())) -> 2536421.6 | D88: =IF($B$77=Inputs!$B$18,IF($B88<='Mortgage Calculators (By Year)'!$C$9,'Forecast (By Year)'!H13,NA()),IF($B88<='Mortgage Calculators (By Year)'!$J$12,'Forecast (By Year)'!AF13,NA())) -> 2536421.6 | E88: =IF(B88=ROUND(Inputs!$K$10,0),$E$77,NA()) -> #N/A | G88: 9 | H88: =IF($K$20=Inputs!$B$18,IF($G88<='Mortgage Calculators (By Year)'!$C$9,'Forecast (By Year)'!V13,NA()),IF($G88<='Mortgage Calculators (By Year)'!$J$12,'Forecast (By Year)'!AT13,NA())) -> 880166.2 | I88: =IF($K$20=Inputs!$B$18,IF($G88<='Mortgage Calculators (By Year)'!$C$9,'Forecast (By Year)'!Y13,NA()),IF($G88<='Mortgage Calculators (By Year)'!$J$12,'Forecast (By Year)'!AW13,NA())) -> 1730249.4 | J88: =IF($K$20=Inputs!$B$18,IF($G88<='Mortgage Calculators (By Year)'!$C$9,'Forecast (By Year)'!X13,NA()),IF($G88<='Mortgage Calculators (By Year)'!$J$12,'Forecast (By Year)'!AV13,NA())) -> 0.061083445 | K88: =IF($K$20=Inputs!$B$18,IF($G88<='Mortgage Calculators (By Year)'!$C$9,'Forecast (By Year)'!AA13,NA()),IF($G88<='Mortgage Calculators (By Year)'!$J$12,'Forecast (By Year)'!AY13,NA())) -> 0.12007913 | L88: =IF(G88=ROUND(Inputs!$K$10,0),$L$77,NA()) -> #N/A
B89: 10 | C89: =IF($B$77=Inputs!$B$18,IF($B89<='Mortgage Calculators (By Year)'!$C$9,'Forecast (By Year)'!G14,NA()),IF($B89<='Mortgage Calculators (By Year)'!$J$12,'Forecast (By Year)'!AE14,NA())) -> 2663242.7 | D89: =IF($B$77=Inputs!$B$18,IF($B89<='Mortgage Calculators (By Year)'!$C$9,'Forecast (By Year)'!H14,NA()),IF($B89<='Mortgage Calculators (By Year)'!$J$12,'Forecast (By Year)'!AF14,NA())) -> 2663242.7 | E89: =IF(B89=ROUND(Inputs!$K$10,0),$E$77,NA()) -> #N/A | G89: 10 | H89: =IF($K$20=Inputs!$B$18,IF($G89<='Mortgage Calculators (By Year)'!$C$9,'Forecast (By Year)'!V14,NA()),IF($G89<='Mortgage Calculators (By Year)'!$J$12,'Forecast (By Year)'!AT14,NA())) -> 1004450.9 | I89: =IF($K$20=Inputs!$B$18,IF($G89<='Mortgage Calculators (By Year)'!$C$9,'Forecast (By Year)'!Y14,NA()),IF($G89<='Mortgage Calculators (By Year)'!$J$12,'Forecast (By Year)'!AW14,NA())) -> 1978886.3 | J89: =IF($K$20=Inputs!$B$18,IF($G89<='Mortgage Calculators (By Year)'!$C$9,'Forecast (By Year)'!X14,NA()),IF($G89<='Mortgage Calculators (By Year)'!$J$12,'Forecast (By Year)'!AV14,NA())) -> 0.062737909 | K89: =IF($K$20=Inputs!$B$18,IF($G89<='Mortgage Calculators (By Year)'!$C$9,'Forecast (By Year)'!AA14,NA()),IF($G89<='Mortgage Calculators (By Year)'!$J$12,'Forecast (By Year)'!AY14,NA())) -> 0.12360106 | L89: =IF(G89=ROUND(Inputs!$K$10,0),$L$77,NA()) -> #N/A
B90: 11 | C90: =IF($B$77=Inputs!$B$18,IF($B90<='Mortgage Calculators (By Year)'!$C$9,'Forecast (By Year)'!G15,NA()),IF($B90<='Mortgage Calculators (By Year)'!$J$12,'Forecast (By Year)'!AE15,NA())) -> 2796404.9 | D90: =IF($B$77=Inputs!$B$18,IF($B90<='Mortgage Calculators (By Year)'!$C$9,'Forecast (By Year)'!H15,NA()),IF($B90<='Mortgage Calculators (By Year)'!$J$12,'Forecast (By Year)'!AF15,NA())) -> 2796404.9 | E90: =IF(B90=ROUND(Inputs!$K$10,0),$E$77,NA()) -> #N/A | G90: 11 | H90: =IF($K$20=Inputs!$B$18,IF($G90<='Mortgage Calculators (By Year)'!$C$9,'Forecast (By Year)'!V15,NA()),IF($G90<='Mortgage Calculators (By Year)'!$J$12,'Forecast (By Year)'!AT15,NA())) -> 1134949.8 | I90: =IF($K$20=Inputs!$B$18,IF($G90<='Mortgage Calculators (By Year)'!$C$9,'Forecast (By Year)'!Y15,NA()),IF($G90<='Mortgage Calculators (By Year)'!$J$12,'Forecast (By Year)'!AW15,NA())) -> 2240847.9 | J90: =IF($K$20=Inputs!$B$18,IF($G90<='Mortgage Calculators (By Year)'!$C$9,'Forecast (By Year)'!X15,NA()),IF($G90<='Mortgage Calculators (By Year)'!$J$12,'Forecast (By Year)'!AV15,NA())) -> 0.064444416 | K90: =IF($K$20=Inputs!$B$18,IF($G90<='Mortgage Calculators (By Year)'!$C$9,'Forecast (By Year)'!AA15,NA()),IF($G90<='Mortgage Calculators (By Year)'!$J$12,'Forecast (By Year)'!AY15,NA())) -> 0.12723923 | L90: =IF(G90=ROUND(Inputs!$K$10,0),$L$77,NA()) -> #N/A
... B130: 51 | C130: =IF($B$77=Inputs!$B$18,IF($B130<='Mortgage Calculators (By Year)'!$C$9,'Forecast (By Year)'!G55,NA()),IF($B130<='Mortgage Calculators (By Year)'!$J$12,'Forecast (By Year)'!AE55,NA())) -> #N/A | D130: =IF($B$77=Inputs!$B$18,IF($B130<='Mortgage Calculators (By Year)'!$C$9,'Forecast (By Year)'!H55,NA()),IF($B130<='Mortgage Calculators (By Year)'!$J$12,'Forecast (By Year)'!AF55,NA())) -> #N/A | E130: =IF(B130=ROUND(Inputs!$K$10,0),$E$77,NA()) -> #N/A | G130: 51 | H130: =IF($K$20=Inputs!$B$18,IF($G130<='Mortgage Calculators (By Year)'!$C$9,'Forecast (By Year)'!V55,NA()),IF($G130<='Mortgage Calculators (By Year)'!$J$12,'Forecast (By Year)'!AT55,NA())) -> #N/A | I130: =IF($K$20=Inputs!$B$18,IF($G130<='Mortgage Calculators (By Year)'!$C$9,'Forecast (By Year)'!Y55,NA()),IF($G130<='Mortgage Calculators (By Year)'!$J$12,'Forecast (By Year)'!AW55,NA())) -> #N/A | J130: =IF($K$20=Inputs!$B$18,IF($G130<='Mortgage Calculators (By Year)'!$C$9,'Forecast (By Year)'!X55,NA()),IF($G130<='Mortgage Calculators (By Year)'!$J$12,'Forecast (By Year)'!AV55,NA())) -> #N/A | K130: =IF($K$20=Inputs!$B$18,IF($G130<='Mortgage Calculators (By Year)'!$C$9,'Forecast (By Year)'!AA55,NA()),IF($G130<='Mortgage Calculators (By Year)'!$J$12,'Forecast (By Year)'!AY55,NA())) -> #N/A | L130: =IF(G130=ROUND(Inputs!$K$10,0),$L$77,NA()) -> #N/A
B132: CHARTS FOR ANALYSIS SUMMARY TAB (PG 3)
B133: Cash Flow | I133: Investment Performance (Before Tax)
B134: ='Analysis Summary'!$E$6 -> Principal & Interest Loan (P&I) | D134: =_xlfn.MAXIFS(C136:D186,C136:D186,">0") -> 423961.97 | G134: =_xlfn.XLOOKUP(Inputs!$K$10,'RE Calculations'!$B$136:$B$186,'RE Calculations'!$C$136:$C$186) -> 125197.14 | I134: ='Analysis Summary'!$E$6 -> Principal & Interest Loan (P&I) | M134: 1
B135: Year | C135: Total Rental Income | D135: Total Expenses | E135: Total Ongoing Fees/Costs | F135: Loan Repayment | G135: Holding Period | I135: Year | J135: Cash-on-Cash Return | K135: Yield on Cost | L135: Yield on Value | M135: Holding Period
B136: 1 | C136: =IF($B$77=Inputs!$B$18,IF($B136<='Mortgage Calculators (By Year)'!$C$9,'Forecast (By Year)'!I5,NA()),IF($B136<='Mortgage Calculators (By Year)'!$J$12,'Forecast (By Year)'!AG5,NA())) -> 103000 | D136: =SUM(E136:F136) -> 29188 | E136: =IF($B$77=Inputs!$B$18,IF($B136<='Mortgage Calculators (By Year)'!$C$9,'Forecast (By Year)'!L5,NA()),IF($B136<='Mortgage Calculators (By Year)'!$J$12,'Forecast (By Year)'!AJ5,NA())) -> 29188 | F136: =IF($B$77=Inputs!$B$18,IF($B136<='Mortgage Calculators (By Year)'!$C$9,'Forecast (By Year)'!M5,NA()),IF($B136<='Mortgage Calculators (By Year)'!$J$12,'Forecast (By Year)'!AK5,NA())) -> 0 | G136: =IF(B136=ROUND(Inputs!$K$10,0),_xlfn.MAXIFS(C136:D136,C136:D136,">0"),NA()) -> #N/A | I136: 1 | J136: =IF($B$77=Inputs!$B$18,_xlfn.XLOOKUP(I136,'Forecast (By Year)'!$F$3:$F$55,'Forecast (By Year)'!$R$3:$R$55)/Inputs!$K$18,_xlfn.XLOOKUP(I136,'Forecast (By Year)'!$AD$3:$AD$55,'Forecast (By Year)'!$AP$3:$AP$55)/Inputs!$K$18) -> 0.046102908 | K136: =IF($B$77=Inputs!$B$18,_xlfn.XLOOKUP(I136,'Forecast (By Year)'!$F$3:$F$55,'Forecast (By Year)'!$R$3:$R$55)/Inputs!$K$5,_xlfn.XLOOKUP(I136,'Forecast (By Year)'!$AD$3:$AD$55,'Forecast (By Year)'!$AP$3:$AP$55)/Inputs!$K$5) -> 0.04920964 | L136: =IF($B$77=Inputs!$B$18,_xlfn.XLOOKUP(I136,'Forecast (By Year)'!$F$3:$F$55,'Forecast (By Year)'!$R$3:$R$55)/Inputs!$K$9,_xlfn.XLOOKUP(I136,'Forecast (By Year)'!$AD$3:$AD$55,'Forecast (By Year)'!$AP$3:$AP$55)/Inputs!$K$9) -> 0.045144954 | M136: =IF(I136=ROUND(Inputs!$K$10,0),$M$134,NA()) -> #N/A
B137: 2 | C137: =IF($B$77=Inputs!$B$18,IF($B137<='Mortgage Calculators (By Year)'!$C$9,'Forecast (By Year)'!I6,NA()),IF($B137<='Mortgage Calculators (By Year)'!$J$12,'Forecast (By Year)'!AG6,NA())) -> 108150 | D137: =SUM(E137:F137) -> 29754.5 | E137: =IF($B$77=Inputs!$B$18,IF($B137<='Mortgage Calculators (By Year)'!$C$9,'Forecast (By Year)'!L6,NA()),IF($B137<='Mortgage Calculators (By Year)'!$J$12,'Forecast (By Year)'!AJ6,NA())) -> 29754.5 | F137: =IF($B$77=Inputs!$B$18,IF($B137<='Mortgage Calculators (By Year)'!$C$9,'Forecast (By Year)'!M6,NA()),IF($B137<='Mortgage Calculators (By Year)'!$J$12,'Forecast (By Year)'!AK6,NA())) -> 0 | G137: =IF(B137=ROUND(Inputs!$K$10,0),_xlfn.MAXIFS(C137:D137,C137:D137,">0"),NA()) -> #N/A | I137: 2 | J137: =IF($B$77=Inputs!$B$18,_xlfn.XLOOKUP(I137,'Forecast (By Year)'!$F$3:$F$55,'Forecast (By Year)'!$R$3:$R$55)/Inputs!$K$18,_xlfn.XLOOKUP(I137,'Forecast (By Year)'!$AD$3:$AD$55,'Forecast (By Year)'!$AP$3:$AP$55)/Inputs!$K$18) -> 0.048965758 | K137: =IF($B$77=Inputs!$B$18,_xlfn.XLOOKUP(I137,'Forecast (By Year)'!$F$3:$F$55,'Forecast (By Year)'!$R$3:$R$55)/Inputs!$K$5,_xlfn.XLOOKUP(I137,'Forecast (By Year)'!$AD$3:$AD$55,'Forecast (By Year)'!$AP$3:$AP$55)/Inputs!$K$5) -> 0.052265409 | L137: =IF($B$77=Inputs!$B$18,_xlfn.XLOOKUP(I137,'Forecast (By Year)'!$F$3:$F$55,'Forecast (By Year)'!$R$3:$R$55)/Inputs!$K$9,_xlfn.XLOOKUP(I137,'Forecast (By Year)'!$AD$3:$AD$55,'Forecast (By Year)'!$AP$3:$AP$55)/Inputs!$K$9) -> 0.047948318 | M137: =IF(I137=ROUND(Inputs!$K$10,0),$M$134,NA()) -> #N/A
B138: 3 | C138: =IF($B$77=Inputs!$B$18,IF($B138<='Mortgage Calculators (By Year)'!$C$9,'Forecast (By Year)'!I7,NA()),IF($B138<='Mortgage Calculators (By Year)'!$J$12,'Forecast (By Year)'!AG7,NA())) -> 113557.5 | D138: =SUM(E138:F138) -> 30349.325 | E138: =IF($B$77=Inputs!$B$18,IF($B138<='Mortgage Calculators (By Year)'!$C$9,'Forecast (By Year)'!L7,NA()),IF($B138<='Mortgage Calculators (By Year)'!$J$12,'Forecast (By Year)'!AJ7,NA())) -> 30349.325 | F138: =IF($B$77=Inputs!$B$18,IF($B138<='Mortgage Calculators (By Year)'!$C$9,'Forecast (By Year)'!M7,NA()),IF($B138<='Mortgage Calculators (By Year)'!$J$12,'Forecast (By Year)'!AK7,NA())) -> 0 | G138: =IF(B138=ROUND(Inputs!$K$10,0),_xlfn.MAXIFS(C138:D138,C138:D138,">0"),NA()) -> #N/A | I138: 3 | J138: =IF($B$77=Inputs!$B$18,_xlfn.XLOOKUP(I138,'Forecast (By Year)'!$F$3:$F$55,'Forecast (By Year)'!$R$3:$R$55)/Inputs!$K$18,_xlfn.XLOOKUP(I138,'Forecast (By Year)'!$AD$3:$AD$55,'Forecast (By Year)'!$AP$3:$AP$55)/Inputs!$K$18) -> 0.05197175 | K138: =IF($B$77=Inputs!$B$18,_xlfn.XLOOKUP(I138,'Forecast (By Year)'!$F$3:$F$55,'Forecast (By Year)'!$R$3:$R$55)/Inputs!$K$5,_xlfn.XLOOKUP(I138,'Forecast (By Year)'!$AD$3:$AD$55,'Forecast (By Year)'!$AP$3:$AP$55)/Inputs!$K$5) -> 0.055473966 | L138: =IF($B$77=Inputs!$B$18,_xlfn.XLOOKUP(I138,'Forecast (By Year)'!$F$3:$F$55,'Forecast (By Year)'!$R$3:$R$55)/Inputs!$K$9,_xlfn.XLOOKUP(I138,'Forecast (By Year)'!$AD$3:$AD$55,'Forecast (By Year)'!$AP$3:$AP$55)/Inputs!$K$9) -> 0.05089185 | M138: =IF(I138=ROUND(Inputs!$K$10,0),$M$134,NA()) -> #N/A
B139: 4 | C139: =IF($B$77=Inputs!$B$18,IF($B139<='Mortgage Calculators (By Year)'!$C$9,'Forecast (By Year)'!I8,NA()),IF($B139<='Mortgage Calculators (By Year)'!$J$12,'Forecast (By Year)'!AG8,NA())) -> 119235.38 | D139: =SUM(E139:F139) -> 30973.891 | E139: =IF($B$77=Inputs!$B$18,IF($B139<='Mortgage Calculators (By Year)'!$C$9,'Forecast (By Year)'!L8,NA()),IF($B139<='Mortgage Calculators (By Year)'!$J$12,'Forecast (By Year)'!AJ8,NA())) -> 30973.891 | F139: =IF($B$77=Inputs!$B$18,IF($B139<='Mortgage Calculators (By Year)'!$C$9,'Forecast (By Year)'!M8,NA()),IF($B139<='Mortgage Calculators (By Year)'!$J$12,'Forecast (By Year)'!AK8,NA())) -> 0 | G139: =IF(B139=ROUND(Inputs!$K$10,0),_xlfn.MAXIFS(C139:D139,C139:D139,">0"),NA()) -> #N/A | I139: 4 | J139: =IF($B$77=Inputs!$B$18,_xlfn.XLOOKUP(I139,'Forecast (By Year)'!$F$3:$F$55,'Forecast (By Year)'!$R$3:$R$55)/Inputs!$K$18,_xlfn.XLOOKUP(I139,'Forecast (By Year)'!$AD$3:$AD$55,'Forecast (By Year)'!$AP$3:$AP$55)/Inputs!$K$18) -> 0.055128042 | K139: =IF($B$77=Inputs!$B$18,_xlfn.XLOOKUP(I139,'Forecast (By Year)'!$F$3:$F$55,'Forecast (By Year)'!$R$3:$R$55)/Inputs!$K$5,_xlfn.XLOOKUP(I139,'Forecast (By Year)'!$AD$3:$AD$55,'Forecast (By Year)'!$AP$3:$AP$55)/Inputs!$K$5) -> 0.058842951 | L139: =IF($B$77=Inputs!$B$18,_xlfn.XLOOKUP(I139,'Forecast (By Year)'!$F$3:$F$55,'Forecast (By Year)'!$R$3:$R$55)/Inputs!$K$9,_xlfn.XLOOKUP(I139,'Forecast (By Year)'!$AD$3:$AD$55,'Forecast (By Year)'!$AP$3:$AP$55)/Inputs!$K$9) -> 0.053982559 | M139: =IF(I139=ROUND(Inputs!$K$10,0),$M$134,NA()) -> #N/A
B140: 5 | C140: =IF($B$77=Inputs!$B$18,IF($B140<='Mortgage Calculators (By Year)'!$C$9,'Forecast (By Year)'!I9,NA()),IF($B140<='Mortgage Calculators (By Year)'!$J$12,'Forecast (By Year)'!AG9,NA())) -> 125197.14 | D140: =SUM(E140:F140) -> 31629.686 | E140: =IF($B$77=Inputs!$B$18,IF($B140<='Mortgage Calculators (By Year)'!$C$9,'Forecast (By Year)'!L9,NA()),IF($B140<='Mortgage Calculators (By Year)'!$J$12,'Forecast (By Year)'!AJ9,NA())) -> 31629.686 | F140: =IF($B$77=Inputs!$B$18,IF($B140<='Mortgage Calculators (By Year)'!$C$9,'Forecast (By Year)'!M9,NA()),IF($B140<='Mortgage Calculators (By Year)'!$J$12,'Forecast (By Year)'!AK9,NA())) -> 0 | G140: =IF(B140=ROUND(Inputs!$K$10,0),_xlfn.MAXIFS(C140:D140,C140:D140,">0"),NA()) -> 125197.14 | I140: 5 | J140: =IF($B$77=Inputs!$B$18,_xlfn.XLOOKUP(I140,'Forecast (By Year)'!$F$3:$F$55,'Forecast (By Year)'!$R$3:$R$55)/Inputs!$K$18,_xlfn.XLOOKUP(I140,'Forecast (By Year)'!$AD$3:$AD$55,'Forecast (By Year)'!$AP$3:$AP$55)/Inputs!$K$18) -> 0.058442149 | K140: =IF($B$77=Inputs!$B$18,_xlfn.XLOOKUP(I140,'Forecast (By Year)'!$F$3:$F$55,'Forecast (By Year)'!$R$3:$R$55)/Inputs!$K$5,_xlfn.XLOOKUP(I140,'Forecast (By Year)'!$AD$3:$AD$55,'Forecast (By Year)'!$AP$3:$AP$55)/Inputs!$K$5) -> 0.062380385 | L140: =IF($B$77=Inputs!$B$18,_xlfn.XLOOKUP(I140,'Forecast (By Year)'!$F$3:$F$55,'Forecast (By Year)'!$R$3:$R$55)/Inputs!$K$9,_xlfn.XLOOKUP(I140,'Forecast (By Year)'!$AD$3:$AD$55,'Forecast (By Year)'!$AP$3:$AP$55)/Inputs!$K$9) -> 0.057227803 | M140: =IF(I140=ROUND(Inputs!$K$10,0),$M$134,NA()) -> 1
B141: 6 | C141: =IF($B$77=Inputs!$B$18,IF($B141<='Mortgage Calculators (By Year)'!$C$9,'Forecast (By Year)'!I10,NA()),IF($B141<='Mortgage Calculators (By Year)'!$J$12,'Forecast (By Year)'!AG10,NA())) -> 131457 | D141: =SUM(E141:F141) -> 32318.27 | E141: =IF($B$77=Inputs!$B$18,IF($B141<='Mortgage Calculators (By Year)'!$C$9,'Forecast (By Year)'!L10,NA()),IF($B141<='Mortgage Calculators (By Year)'!$J$12,'Forecast (By Year)'!AJ10,NA())) -> 32318.27 | F141: =IF($B$77=Inputs!$B$18,IF($B141<='Mortgage Calculators (By Year)'!$C$9,'Forecast (By Year)'!M10,NA()),IF($B141<='Mortgage Calculators (By Year)'!$J$12,'Forecast (By Year)'!AK10,NA())) -> 0 | G141: =IF(B141=ROUND(Inputs!$K$10,0),_xlfn.MAXIFS(C141:D141,C141:D141,">0"),NA()) -> #N/A | I141: 6 | J141: =IF($B$77=Inputs!$B$18,_xlfn.XLOOKUP(I141,'Forecast (By Year)'!$F$3:$F$55,'Forecast (By Year)'!$R$3:$R$55)/Inputs!$K$18,_xlfn.XLOOKUP(I141,'Forecast (By Year)'!$AD$3:$AD$55,'Forecast (By Year)'!$AP$3:$AP$55)/Inputs!$K$18) -> 0.061921961 | K141: =IF($B$77=Inputs!$B$18,_xlfn.XLOOKUP(I141,'Forecast (By Year)'!$F$3:$F$55,'Forecast (By Year)'!$R$3:$R$55)/Inputs!$K$5,_xlfn.XLOOKUP(I141,'Forecast (By Year)'!$AD$3:$AD$55,'Forecast (By Year)'!$AP$3:$AP$55)/Inputs!$K$5) -> 0.06609469 | L141: =IF($B$77=Inputs!$B$18,_xlfn.XLOOKUP(I141,'Forecast (By Year)'!$F$3:$F$55,'Forecast (By Year)'!$R$3:$R$55)/Inputs!$K$9,_xlfn.XLOOKUP(I141,'Forecast (By Year)'!$AD$3:$AD$55,'Forecast (By Year)'!$AP$3:$AP$55)/Inputs!$K$9) -> 0.060635309 | M141: =IF(I141=ROUND(Inputs!$K$10,0),$M$134,NA()) -> #N/A
B142: 7 | C142: =IF($B$77=Inputs!$B$18,IF($B142<='Mortgage Calculators (By Year)'!$C$9,'Forecast (By Year)'!I11,NA()),IF($B142<='Mortgage Calculators (By Year)'!$J$12,'Forecast (By Year)'!AG11,NA())) -> 138029.85 | D142: =SUM(E142:F142) -> 33041.284 | E142: =IF($B$77=Inputs!$B$18,IF($B142<='Mortgage Calculators (By Year)'!$C$9,'Forecast (By Year)'!L11,NA()),IF($B142<='Mortgage Calculators (By Year)'!$J$12,'Forecast (By Year)'!AJ11,NA())) -> 33041.284 | F142: =IF($B$77=Inputs!$B$18,IF($B142<='Mortgage Calculators (By Year)'!$C$9,'Forecast (By Year)'!M11,NA()),IF($B142<='Mortgage Calculators (By Year)'!$J$12,'Forecast (By Year)'!AK11,NA())) -> 0 | G142: =IF(B142=ROUND(Inputs!$K$10,0),_xlfn.MAXIFS(C142:D142,C142:D142,">0"),NA()) -> #N/A | I142: 7 | J142: =IF($B$77=Inputs!$B$18,_xlfn.XLOOKUP(I142,'Forecast (By Year)'!$F$3:$F$55,'Forecast (By Year)'!$R$3:$R$55)/Inputs!$K$18,_xlfn.XLOOKUP(I142,'Forecast (By Year)'!$AD$3:$AD$55,'Forecast (By Year)'!$AP$3:$AP$55)/Inputs!$K$18) -> 0.065575763 | K142: =IF($B$77=Inputs!$B$18,_xlfn.XLOOKUP(I142,'Forecast (By Year)'!$F$3:$F$55,'Forecast (By Year)'!$R$3:$R$55)/Inputs!$K$5,_xlfn.XLOOKUP(I142,'Forecast (By Year)'!$AD$3:$AD$55,'Forecast (By Year)'!$AP$3:$AP$55)/Inputs!$K$5) -> 0.069994711 | L142: =IF($B$77=Inputs!$B$18,_xlfn.XLOOKUP(I142,'Forecast (By Year)'!$F$3:$F$55,'Forecast (By Year)'!$R$3:$R$55)/Inputs!$K$9,_xlfn.XLOOKUP(I142,'Forecast (By Year)'!$AD$3:$AD$55,'Forecast (By Year)'!$AP$3:$AP$55)/Inputs!$K$9) -> 0.064213191 | M142: =IF(I142=ROUND(Inputs!$K$10,0),$M$134,NA()) -> #N/A
B143: 8 | C143: =IF($B$77=Inputs!$B$18,IF($B143<='Mortgage Calculators (By Year)'!$C$9,'Forecast (By Year)'!I12,NA()),IF($B143<='Mortgage Calculators (By Year)'!$J$12,'Forecast (By Year)'!AG12,NA())) -> 144931.34 | D143: =SUM(E143:F143) -> 33800.448 | E143: =IF($B$77=Inputs!$B$18,IF($B143<='Mortgage Calculators (By Year)'!$C$9,'Forecast (By Year)'!L12,NA()),IF($B143<='Mortgage Calculators (By Year)'!$J$12,'Forecast (By Year)'!AJ12,NA())) -> 33800.448 | F143: =IF($B$77=Inputs!$B$18,IF($B143<='Mortgage Calculators (By Year)'!$C$9,'Forecast (By Year)'!M12,NA()),IF($B143<='Mortgage Calculators (By Year)'!$J$12,'Forecast (By Year)'!AK12,NA())) -> 0 | G143: =IF(B143=ROUND(Inputs!$K$10,0),_xlfn.MAXIFS(C143:D143,C143:D143,">0"),NA()) -> #N/A | I143: 8 | J143: =IF($B$77=Inputs!$B$18,_xlfn.XLOOKUP(I143,'Forecast (By Year)'!$F$3:$F$55,'Forecast (By Year)'!$R$3:$R$55)/Inputs!$K$18,_xlfn.XLOOKUP(I143,'Forecast (By Year)'!$AD$3:$AD$55,'Forecast (By Year)'!$AP$3:$AP$55)/Inputs!$K$18) -> 0.069412256 | K143: =IF($B$77=Inputs!$B$18,_xlfn.XLOOKUP(I143,'Forecast (By Year)'!$F$3:$F$55,'Forecast (By Year)'!$R$3:$R$55)/Inputs!$K$5,_xlfn.XLOOKUP(I143,'Forecast (By Year)'!$AD$3:$AD$55,'Forecast (By Year)'!$AP$3:$AP$55)/Inputs!$K$5) -> 0.074089733 | L143: =IF($B$77=Inputs!$B$18,_xlfn.XLOOKUP(I143,'Forecast (By Year)'!$F$3:$F$55,'Forecast (By Year)'!$R$3:$R$55)/Inputs!$K$9,_xlfn.XLOOKUP(I143,'Forecast (By Year)'!$AD$3:$AD$55,'Forecast (By Year)'!$AP$3:$AP$55)/Inputs!$K$9) -> 0.067969967 | M143: =IF(I143=ROUND(Inputs!$K$10,0),$M$134,NA()) -> #N/A
B144: 9 | C144: =IF($B$77=Inputs!$B$18,IF($B144<='Mortgage Calculators (By Year)'!$C$9,'Forecast (By Year)'!I13,NA()),IF($B144<='Mortgage Calculators (By Year)'!$J$12,'Forecast (By Year)'!AG13,NA())) -> 152177.91 | D144: =SUM(E144:F144) -> 34597.57 | E144: =IF($B$77=Inputs!$B$18,IF($B144<='Mortgage Calculators (By Year)'!$C$9,'Forecast (By Year)'!L13,NA()),IF($B144<='Mortgage Calculators (By Year)'!$J$12,'Forecast (By Year)'!AJ13,NA())) -> 34597.57 | F144: =IF($B$77=Inputs!$B$18,IF($B144<='Mortgage Calculators (By Year)'!$C$9,'Forecast (By Year)'!M13,NA()),IF($B144<='Mortgage Calculators (By Year)'!$J$12,'Forecast (By Year)'!AK13,NA())) -> 0 | G144: =IF(B144=ROUND(Inputs!$K$10,0),_xlfn.MAXIFS(C144:D144,C144:D144,">0"),NA()) -> #N/A | I144: 9 | J144: =IF($B$77=Inputs!$B$18,_xlfn.XLOOKUP(I144,'Forecast (By Year)'!$F$3:$F$55,'Forecast (By Year)'!$R$3:$R$55)/Inputs!$K$18,_xlfn.XLOOKUP(I144,'Forecast (By Year)'!$AD$3:$AD$55,'Forecast (By Year)'!$AP$3:$AP$55)/Inputs!$K$18) -> 0.073440573 | K144: =IF($B$77=Inputs!$B$18,_xlfn.XLOOKUP(I144,'Forecast (By Year)'!$F$3:$F$55,'Forecast (By Year)'!$R$3:$R$55)/Inputs!$K$5,_xlfn.XLOOKUP(I144,'Forecast (By Year)'!$AD$3:$AD$55,'Forecast (By Year)'!$AP$3:$AP$55)/Inputs!$K$5) -> 0.078389507 | L144: =IF($B$77=Inputs!$B$18,_xlfn.XLOOKUP(I144,'Forecast (By Year)'!$F$3:$F$55,'Forecast (By Year)'!$R$3:$R$55)/Inputs!$K$9,_xlfn.XLOOKUP(I144,'Forecast (By Year)'!$AD$3:$AD$55,'Forecast (By Year)'!$AP$3:$AP$55)/Inputs!$K$9) -> 0.071914581 | M144: =IF(I144=ROUND(Inputs!$K$10,0),$M$134,NA()) -> #N/A
B145: 10 | C145: =IF($B$77=Inputs!$B$18,IF($B145<='Mortgage Calculators (By Year)'!$C$9,'Forecast (By Year)'!I14,NA()),IF($B145<='Mortgage Calculators (By Year)'!$J$12,'Forecast (By Year)'!AG14,NA())) -> 159786.81 | D145: =SUM(E145:F145) -> 35434.549 | E145: =IF($B$77=Inputs!$B$18,IF($B145<='Mortgage Calculators (By Year)'!$C$9,'Forecast (By Year)'!L14,NA()),IF($B145<='Mortgage Calculators (By Year)'!$J$12,'Forecast (By Year)'!AJ14,NA())) -> 35434.549 | F145: =IF($B$77=Inputs!$B$18,IF($B145<='Mortgage Calculators (By Year)'!$C$9,'Forecast (By Year)'!M14,NA()),IF($B145<='Mortgage Calculators (By Year)'!$J$12,'Forecast (By Year)'!AK14,NA())) -> 0 | G145: =IF(B145=ROUND(Inputs!$K$10,0),_xlfn.MAXIFS(C145:D145,C145:D145,">0"),NA()) -> #N/A | I145: 10 | J145: =IF($B$77=Inputs!$B$18,_xlfn.XLOOKUP(I145,'Forecast (By Year)'!$F$3:$F$55,'Forecast (By Year)'!$R$3:$R$55)/Inputs!$K$18,_xlfn.XLOOKUP(I145,'Forecast (By Year)'!$AD$3:$AD$55,'Forecast (By Year)'!$AP$3:$AP$55)/Inputs!$K$18) -> 0.077670306 | K145: =IF($B$77=Inputs!$B$18,_xlfn.XLOOKUP(I145,'Forecast (By Year)'!$F$3:$F$55,'Forecast (By Year)'!$R$3:$R$55)/Inputs!$K$5,_xlfn.XLOOKUP(I145,'Forecast (By Year)'!$AD$3:$AD$55,'Forecast (By Year)'!$AP$3:$AP$55)/Inputs!$K$5) -> 0.082904269 | L145: =IF($B$77=Inputs!$B$18,_xlfn.XLOOKUP(I145,'Forecast (By Year)'!$F$3:$F$55,'Forecast (By Year)'!$R$3:$R$55)/Inputs!$K$9,_xlfn.XLOOKUP(I145,'Forecast (By Year)'!$AD$3:$AD$55,'Forecast (By Year)'!$AP$3:$AP$55)/Inputs!$K$9) -> 0.076056427 | M145: =IF(I145=ROUND(Inputs!$K$10,0),$M$134,NA()) -> #N/A
B146: 11 | C146: =IF($B$77=Inputs!$B$18,IF($B146<='Mortgage Calculators (By Year)'!$C$9,'Forecast (By Year)'!I15,NA()),IF($B146<='Mortgage Calculators (By Year)'!$J$12,'Forecast (By Year)'!AG15,NA())) -> 167776.15 | D146: =SUM(E146:F146) -> 36313.376 | E146: =IF($B$77=Inputs!$B$18,IF($B146<='Mortgage Calculators (By Year)'!$C$9,'Forecast (By Year)'!L15,NA()),IF($B146<='Mortgage Calculators (By Year)'!$J$12,'Forecast (By Year)'!AJ15,NA())) -> 36313.376 | F146: =IF($B$77=Inputs!$B$18,IF($B146<='Mortgage Calculators (By Year)'!$C$9,'Forecast (By Year)'!M15,NA()),IF($B146<='Mortgage Calculators (By Year)'!$J$12,'Forecast (By Year)'!AK15,NA())) -> 0 | G146: =IF(B146=ROUND(Inputs!$K$10,0),_xlfn.MAXIFS(C146:D146,C146:D146,">0"),NA()) -> #N/A | I146: 11 | J146: =IF($B$77=Inputs!$B$18,_xlfn.XLOOKUP(I146,'Forecast (By Year)'!$F$3:$F$55,'Forecast (By Year)'!$R$3:$R$55)/Inputs!$K$18,_xlfn.XLOOKUP(I146,'Forecast (By Year)'!$AD$3:$AD$55,'Forecast (By Year)'!$AP$3:$AP$55)/Inputs!$K$18) -> 0.082111526 | K146: =IF($B$77=Inputs!$B$18,_xlfn.XLOOKUP(I146,'Forecast (By Year)'!$F$3:$F$55,'Forecast (By Year)'!$R$3:$R$55)/Inputs!$K$5,_xlfn.XLOOKUP(I146,'Forecast (By Year)'!$AD$3:$AD$55,'Forecast (By Year)'!$AP$3:$AP$55)/Inputs!$K$5) -> 0.087644768 | L146: =IF($B$77=Inputs!$B$18,_xlfn.XLOOKUP(I146,'Forecast (By Year)'!$F$3:$F$55,'Forecast (By Year)'!$R$3:$R$55)/Inputs!$K$9,_xlfn.XLOOKUP(I146,'Forecast (By Year)'!$AD$3:$AD$55,'Forecast (By Year)'!$AP$3:$AP$55)/Inputs!$K$9) -> 0.080405364 | M146: =IF(I146=ROUND(Inputs!$K$10,0),$M$134,NA()) -> #N/A
B147: 12 | C147: =IF($B$77=Inputs!$B$18,IF($B147<='Mortgage Calculators (By Year)'!$C$9,'Forecast (By Year)'!I16,NA()),IF($B147<='Mortgage Calculators (By Year)'!$J$12,'Forecast (By Year)'!AG16,NA())) -> 176164.95 | D147: =SUM(E147:F147) -> 37236.145 | E147: =IF($B$77=Inputs!$B$18,IF($B147<='Mortgage Calculators (By Year)'!$C$9,'Forecast (By Year)'!L16,NA()),IF($B147<='Mortgage Calculators (By Year)'!$J$12,'Forecast (By Year)'!AJ16,NA())) -> 37236.145 | F147: =IF($B$77=Inputs!$B$18,IF($B147<='Mortgage Calculators (By Year)'!$C$9,'Forecast (By Year)'!M16,NA()),IF($B147<='Mortgage Calculators (By Year)'!$J$12,'Forecast (By Year)'!AK16,NA())) -> 0 | G147: =IF(B147=ROUND(Inputs!$K$10,0),_xlfn.MAXIFS(C147:D147,C147:D147,">0"),NA()) -> #N/A | I147: 12 | J147: =IF($B$77=Inputs!$B$18,_xlfn.XLOOKUP(I147,'Forecast (By Year)'!$F$3:$F$55,'Forecast (By Year)'!$R$3:$R$55)/Inputs!$K$18,_xlfn.XLOOKUP(I147,'Forecast (By Year)'!$AD$3:$AD$55,'Forecast (By Year)'!$AP$3:$AP$55)/Inputs!$K$18) -> 0.086774807 | K147: =IF($B$77=Inputs!$B$18,_xlfn.XLOOKUP(I147,'Forecast (By Year)'!$F$3:$F$55,'Forecast (By Year)'!$R$3:$R$55)/Inputs!$K$5,_xlfn.XLOOKUP(I147,'Forecast (By Year)'!$AD$3:$AD$55,'Forecast (By Year)'!$AP$3:$AP$55)/Inputs!$K$5) -> 0.092622293 | L147: =IF($B$77=Inputs!$B$18,_xlfn.XLOOKUP(I147,'Forecast (By Year)'!$F$3:$F$55,'Forecast (By Year)'!$R$3:$R$55)/Inputs!$K$9,_xlfn.XLOOKUP(I147,'Forecast (By Year)'!$AD$3:$AD$55,'Forecast (By Year)'!$AP$3:$AP$55)/Inputs!$K$9) -> 0.084971749 | M147: =IF(I147=ROUND(Inputs!$K$10,0),$M$134,NA()) -> #N/A
... B186: 51 | C186: =IF($B$77=Inputs!$B$18,IF($B186<='Mortgage Calculators (By Year)'!$C$9,'Forecast (By Year)'!I55,NA()),IF($B186<='Mortgage Calculators (By Year)'!$J$12,'Forecast (By Year)'!AG55,NA())) -> #N/A | D186: =SUM(E186:F186) -> #N/A | E186: =IF($B$77=Inputs!$B$18,IF($B186<='Mortgage Calculators (By Year)'!$C$9,'Forecast (By Year)'!L55,NA()),IF($B186<='Mortgage Calculators (By Year)'!$J$12,'Forecast (By Year)'!AJ55,NA())) -> #N/A | F186: =IF($B$77=Inputs!$B$18,IF($B186<='Mortgage Calculators (By Year)'!$C$9,'Forecast (By Year)'!M55,NA()),IF($B186<='Mortgage Calculators (By Year)'!$J$12,'Forecast (By Year)'!AK55,NA())) -> #N/A | G186: =IF(B186=ROUND(Inputs!$K$10,0),_xlfn.MAXIFS(C186:D186,C186:D186,">0"),NA()) -> #N/A | I186: 51 | J186: =IF($B$77=Inputs!$B$18,_xlfn.XLOOKUP(I186,'Forecast (By Year)'!$F$3:$F$55,'Forecast (By Year)'!$R$3:$R$55)/Inputs!$K$18,_xlfn.XLOOKUP(I186,'Forecast (By Year)'!$AD$3:$AD$55,'Forecast (By Year)'!$AP$3:$AP$55)/Inputs!$K$18) -> #N/A | K186: =IF($B$77=Inputs!$B$18,_xlfn.XLOOKUP(I186,'Forecast (By Year)'!$F$3:$F$55,'Forecast (By Year)'!$R$3:$R$55)/Inputs!$K$5,_xlfn.XLOOKUP(I186,'Forecast (By Year)'!$AD$3:$AD$55,'Forecast (By Year)'!$AP$3:$AP$55)/Inputs!$K$5) -> #N/A | L186: =IF($B$77=Inputs!$B$18,_xlfn.XLOOKUP(I186,'Forecast (By Year)'!$F$3:$F$55,'Forecast (By Year)'!$R$3:$R$55)/Inputs!$K$9,_xlfn.XLOOKUP(I186,'Forecast (By Year)'!$AD$3:$AD$55,'Forecast (By Year)'!$AP$3:$AP$55)/Inputs!$K$9) -> #N/A | M186: =IF(I186=ROUND(Inputs!$K$10,0),$M$134,NA()) -> #N/A
B188: SELLING COSTS | F188: DASHBOARD NUMBERS FOR ANALYSIS SUMMARY TAB
B189: Used for Forecast (By Month) tab - Gross Profit if Sold | F189: ="For a holding period of "&Inputs!$K$10&" years" -> For a holding period of 5 years
B190: Month | C190: Selling Costs | F190: Annual Payment | H190: =_xlfn.XLOOKUP(Inputs!$K$10,'RE Calculations'!$K$22:$K$73,'RE Calculations'!$N$22:$N$73) -> 100
B191: 0 | C191: =IFERROR(IF(OR(Inputs!$C$84=0,Inputs!$C$84="",ISERROR(Inputs!$C$84)),Inputs!$D$84,Inputs!$C$84*Inputs!$K$9),"Error - Check Input") +IFERROR(IF(OR(Inputs!$C$85=0,Inputs!$C$85="",ISERROR(Inputs!$C$85)),Inputs!$D$85,Inputs!$C$85*Inputs!$K$9),"Error - Check Input") +IFERROR(IF(OR(Inputs!$C$86=0,Inputs!$C$86="",ISERROR(Inputs!$C$86)),Inputs!$D$86,Inputs!$C$86*Inputs!$K$9),"Error - Check Input") +IFERROR(IF(OR(Inputs!$C$87=0,Inputs!$C$87="",ISERROR(Inputs!$C$87)),Inputs!$D$87,Inputs!$C$87*Inputs!$K$9),"Error - Check Input") +IFERROR(IF(OR(Inputs!$C$88=0,Inputs!$C$88="",ISERROR(Inputs!$C$88)),Inputs!$D$88,Inputs!$C$88*Inputs!$K$9),"Error - Check Input") +IFERROR(IF(OR(Inputs!$C$89=0,Inputs!$C$89="",ISERROR(Inputs!$C$89)),Inputs!$D$89,Inputs!$C$89*Inputs!$K$9),"Error - Check Input") +IFERROR(IF(OR(Inputs!$C$90=0,Inputs!$C$90="",ISERROR(Inputs!$C$90)),Inputs!$D$90,Inputs!$C$90*Inputs!$K$9),"Error - Check Input") +IFERROR(IF(OR(Inputs!$C$93=0,Inputs!$C$93="",ISERROR(Inputs!$C$93)),Inputs!$D$93,Inputs!$C$93*Inputs!$K$9),"Error - Check Input") -> 37200 | F191: Loan Balance | H191: =_xlfn.XLOOKUP(Inputs!$K$10,'RE Calculations'!$B$22:$B$73,'RE Calculations'!$F$22:$F$73) -> 0
B192: 1 | C192: =IFERROR(IF(OR(Inputs!$C$84=0,Inputs!$C$84="",ISERROR(Inputs!$C$84)),Inputs!$D$84,Inputs!$C$84*Inputs!$K$9*(1+Inputs!$K$12)^B192),"Error - Check Input") +IFERROR(IF(OR(Inputs!$C$85=0,Inputs!$C$85="",ISERROR(Inputs!$C$85)),Inputs!$D$85,Inputs!$C$85*Inputs!$K$9*(1+Inputs!$K$12)^B192),"Error - Check Input") +IFERROR(IF(OR(Inputs!$C$86=0,Inputs!$C$86="",ISERROR(Inputs!$C$86)),Inputs!$D$86,Inputs!$C$86*Inputs!$K$9*(1+Inputs!$K$12)^B192),"Error - Check Input") +IFERROR(IF(OR(Inputs!$C$87=0,Inputs!$C$87="",ISERROR(Inputs!$C$87)),Inputs!$D$87,Inputs!$C$87*Inputs!$K$9*(1+Inputs!$K$12)^B192),"Error - Check Input") +IFERROR(IF(OR(Inputs!$C$88=0,Inputs!$C$88="",ISERROR(Inputs!$C$88)),Inputs!$D$88,Inputs!$C$88*Inputs!$K$9*(1+Inputs!$K$12)^B192),"Error - Check Input") +IFERROR(IF(OR(Inputs!$C$89=0,Inputs!$C$89="",ISERROR(Inputs!$C$89)),Inputs!$D$89,Inputs!$C$89*Inputs!$K$9*(1+Inputs!$K$12)^B192),"Error - Check Input") +IFERROR(IF(OR(Inputs!$C$90=0,Inputs!$C$90="",ISERROR(Inputs!$C$90)),Inputs!$D$90,Inputs!$C$90*Inputs!$K$9*(1+Inputs!$K$12)^B192),"Error - Check Input") +IFERROR(IF(OR(Inputs!$C$93=0,Inputs!$C$93="",ISERROR(Inputs!$C$93)),Inputs!$D$93,Inputs!$C$93*Inputs!$K$9*(1+Inputs!$K$12)^B192),"Error - Check Input") -> 37333.224 | F192: Cumulative Principal | H192: =_xlfn.XLOOKUP(Inputs!$K$10,'RE Calculations'!$B$22:$B$73,'RE Calculations'!$D$22:$D$73) -> 0
B193: 2 | C193: =IFERROR(IF(OR(Inputs!$C$84=0,Inputs!$C$84="",ISERROR(Inputs!$C$84)),Inputs!$D$84,Inputs!$C$84*Inputs!$K$9*(1+Inputs!$K$12)^B193),"Error - Check Input") +IFERROR(IF(OR(Inputs!$C$85=0,Inputs!$C$85="",ISERROR(Inputs!$C$85)),Inputs!$D$85,Inputs!$C$85*Inputs!$K$9*(1+Inputs!$K$12)^B193),"Error - Check Input") +IFERROR(IF(OR(Inputs!$C$86=0,Inputs!$C$86="",ISERROR(Inputs!$C$86)),Inputs!$D$86,Inputs!$C$86*Inputs!$K$9*(1+Inputs!$K$12)^B193),"Error - Check Input") +IFERROR(IF(OR(Inputs!$C$87=0,Inputs!$C$87="",ISERROR(Inputs!$C$87)),Inputs!$D$87,Inputs!$C$87*Inputs!$K$9*(1+Inputs!$K$12)^B193),"Error - Check Input") +IFERROR(IF(OR(Inputs!$C$88=0,Inputs!$C$88="",ISERROR(Inputs!$C$88)),Inputs!$D$88,Inputs!$C$88*Inputs!$K$9*(1+Inputs!$K$12)^B193),"Error - Check Input") +IFERROR(IF(OR(Inputs!$C$89=0,Inputs!$C$89="",ISERROR(Inputs!$C$89)),Inputs!$D$89,Inputs!$C$89*Inputs!$K$9*(1+Inputs!$K$12)^B193),"Error - Check Input") +IFERROR(IF(OR(Inputs!$C$90=0,Inputs!$C$90="",ISERROR(Inputs!$C$90)),Inputs!$D$90,Inputs!$C$90*Inputs!$K$9*(1+Inputs!$K$12)^B193),"Error - Check Input") +IFERROR(IF(OR(Inputs!$C$93=0,Inputs!$C$93="",ISERROR(Inputs!$C$93)),Inputs!$D$93,Inputs!$C$93*Inputs!$K$9*(1+Inputs!$K$12)^B193),"Error - Check Input") -> 37466.99 | F193: Cumulative Interest + Fees | H193: =_xlfn.XLOOKUP(Inputs!$K$10,'RE Calculations'!$B$22:$B$73,'RE Calculations'!$E$22:$E$73) -> 500
B194: 3 | C194: =IFERROR(IF(OR(Inputs!$C$84=0,Inputs!$C$84="",ISERROR(Inputs!$C$84)),Inputs!$D$84,Inputs!$C$84*Inputs!$K$9*(1+Inputs!$K$12)^B194),"Error - Check Input") +IFERROR(IF(OR(Inputs!$C$85=0,Inputs!$C$85="",ISERROR(Inputs!$C$85)),Inputs!$D$85,Inputs!$C$85*Inputs!$K$9*(1+Inputs!$K$12)^B194),"Error - Check Input") +IFERROR(IF(OR(Inputs!$C$86=0,Inputs!$C$86="",ISERROR(Inputs!$C$86)),Inputs!$D$86,Inputs!$C$86*Inputs!$K$9*(1+Inputs!$K$12)^B194),"Error - Check Input") +IFERROR(IF(OR(Inputs!$C$87=0,Inputs!$C$87="",ISERROR(Inputs!$C$87)),Inputs!$D$87,Inputs!$C$87*Inputs!$K$9*(1+Inputs!$K$12)^B194),"Error - Check Input") +IFERROR(IF(OR(Inputs!$C$88=0,Inputs!$C$88="",ISERROR(Inputs!$C$88)),Inputs!$D$88,Inputs!$C$88*Inputs!$K$9*(1+Inputs!$K$12)^B194),"Error - Check Input") +IFERROR(IF(OR(Inputs!$C$89=0,Inputs!$C$89="",ISERROR(Inputs!$C$89)),Inputs!$D$89,Inputs!$C$89*Inputs!$K$9*(1+Inputs!$K$12)^B194),"Error - Check Input") +IFERROR(IF(OR(Inputs!$C$90=0,Inputs!$C$90="",ISERROR(Inputs!$C$90)),Inputs!$D$90,Inputs!$C$90*Inputs!$K$9*(1+Inputs!$K$12)^B194),"Error - Check Input") +IFERROR(IF(OR(Inputs!$C$93=0,Inputs!$C$93="",ISERROR(Inputs!$C$93)),Inputs!$D$93,Inputs!$C$93*Inputs!$K$9*(1+Inputs!$K$12)^B194),"Error - Check Input") -> 37601.302 | F194: Purchasing Costs | H194: =Inputs!K18 -> 1601027
B195: 4 | C195: =IFERROR(IF(OR(Inputs!$C$84=0,Inputs!$C$84="",ISERROR(Inputs!$C$84)),Inputs!$D$84,Inputs!$C$84*Inputs!$K$9*(1+Inputs!$K$12)^B195),"Error - Check Input") +IFERROR(IF(OR(Inputs!$C$85=0,Inputs!$C$85="",ISERROR(Inputs!$C$85)),Inputs!$D$85,Inputs!$C$85*Inputs!$K$9*(1+Inputs!$K$12)^B195),"Error - Check Input") +IFERROR(IF(OR(Inputs!$C$86=0,Inputs!$C$86="",ISERROR(Inputs!$C$86)),Inputs!$D$86,Inputs!$C$86*Inputs!$K$9*(1+Inputs!$K$12)^B195),"Error - Check Input") +IFERROR(IF(OR(Inputs!$C$87=0,Inputs!$C$87="",ISERROR(Inputs!$C$87)),Inputs!$D$87,Inputs!$C$87*Inputs!$K$9*(1+Inputs!$K$12)^B195),"Error - Check Input") +IFERROR(IF(OR(Inputs!$C$88=0,Inputs!$C$88="",ISERROR(Inputs!$C$88)),Inputs!$D$88,Inputs!$C$88*Inputs!$K$9*(1+Inputs!$K$12)^B195),"Error - Check Input") +IFERROR(IF(OR(Inputs!$C$89=0,Inputs!$C$89="",ISERROR(Inputs!$C$89)),Inputs!$D$89,Inputs!$C$89*Inputs!$K$9*(1+Inputs!$K$12)^B195),"Error - Check Input") +IFERROR(IF(OR(Inputs!$C$90=0,Inputs!$C$90="",ISERROR(Inputs!$C$90)),Inputs!$D$90,Inputs!$C$90*Inputs!$K$9*(1+Inputs!$K$12)^B195),"Error - Check Input") +IFERROR(IF(OR(Inputs!$C$93=0,Inputs!$C$93="",ISERROR(Inputs!$C$93)),Inputs!$D$93,Inputs!$C$93*Inputs!$K$9*(1+Inputs!$K$12)^B195),"Error - Check Input") -> 37736.161 | F195: Est. Property Value | H195: =_xlfn.XLOOKUP(Inputs!$K$10,'RE Calculations'!$B$79:$B$130,'RE Calculations'!$C$79:$C$130) -> 2086720.4
B196: 5 | C196: =IFERROR(IF(OR(Inputs!$C$84=0,Inputs!$C$84="",ISERROR(Inputs!$C$84)),Inputs!$D$84,Inputs!$C$84*Inputs!$K$9*(1+Inputs!$K$12)^B196),"Error - Check Input") +IFERROR(IF(OR(Inputs!$C$85=0,Inputs!$C$85="",ISERROR(Inputs!$C$85)),Inputs!$D$85,Inputs!$C$85*Inputs!$K$9*(1+Inputs!$K$12)^B196),"Error - Check Input") +IFERROR(IF(OR(Inputs!$C$86=0,Inputs!$C$86="",ISERROR(Inputs!$C$86)),Inputs!$D$86,Inputs!$C$86*Inputs!$K$9*(1+Inputs!$K$12)^B196),"Error - Check Input") +IFERROR(IF(OR(Inputs!$C$87=0,Inputs!$C$87="",ISERROR(Inputs!$C$87)),Inputs!$D$87,Inputs!$C$87*Inputs!$K$9*(1+Inputs!$K$12)^B196),"Error - Check Input") +IFERROR(IF(OR(Inputs!$C$88=0,Inputs!$C$88="",ISERROR(Inputs!$C$88)),Inputs!$D$88,Inputs!$C$88*Inputs!$K$9*(1+Inputs!$K$12)^B196),"Error - Check Input") +IFERROR(IF(OR(Inputs!$C$89=0,Inputs!$C$89="",ISERROR(Inputs!$C$89)),Inputs!$D$89,Inputs!$C$89*Inputs!$K$9*(1+Inputs!$K$12)^B196),"Error - Check Input") +IFERROR(IF(OR(Inputs!$C$90=0,Inputs!$C$90="",ISERROR(Inputs!$C$90)),Inputs!$D$90,Inputs!$C$90*Inputs!$K$9*(1+Inputs!$K$12)^B196),"Error - Check Input") +IFERROR(IF(OR(Inputs!$C$93=0,Inputs!$C$93="",ISERROR(Inputs!$C$93)),Inputs!$D$93,Inputs!$C$93*Inputs!$K$9*(1+Inputs!$K$12)^B196),"Error - Check Input") -> 37871.569 | F196: Cumulative Cash Flow | H196: =IF($B$77=Inputs!$B$18,_xlfn.XLOOKUP(Inputs!$K$10,'Forecast (By Year)'!$F$4:$F$55,'Forecast (By Year)'!$U$4:$U$55),_xlfn.XLOOKUP(Inputs!$K$10,'Forecast (By Year)'!$AD$4:$AD$55,'Forecast (By Year)'!$AR$4:$AR$55)) -> 417244.62
B197: 6 | C197: =IFERROR(IF(OR(Inputs!$C$84=0,Inputs!$C$84="",ISERROR(Inputs!$C$84)),Inputs!$D$84,Inputs!$C$84*Inputs!$K$9*(1+Inputs!$K$12)^B197),"Error - Check Input") +IFERROR(IF(OR(Inputs!$C$85=0,Inputs!$C$85="",ISERROR(Inputs!$C$85)),Inputs!$D$85,Inputs!$C$85*Inputs!$K$9*(1+Inputs!$K$12)^B197),"Error - Check Input") +IFERROR(IF(OR(Inputs!$C$86=0,Inputs!$C$86="",ISERROR(Inputs!$C$86)),Inputs!$D$86,Inputs!$C$86*Inputs!$K$9*(1+Inputs!$K$12)^B197),"Error - Check Input") +IFERROR(IF(OR(Inputs!$C$87=0,Inputs!$C$87="",ISERROR(Inputs!$C$87)),Inputs!$D$87,Inputs!$C$87*Inputs!$K$9*(1+Inputs!$K$12)^B197),"Error - Check Input") +IFERROR(IF(OR(Inputs!$C$88=0,Inputs!$C$88="",ISERROR(Inputs!$C$88)),Inputs!$D$88,Inputs!$C$88*Inputs!$K$9*(1+Inputs!$K$12)^B197),"Error - Check Input") +IFERROR(IF(OR(Inputs!$C$89=0,Inputs!$C$89="",ISERROR(Inputs!$C$89)),Inputs!$D$89,Inputs!$C$89*Inputs!$K$9*(1+Inputs!$K$12)^B197),"Error - Check Input") +IFERROR(IF(OR(Inputs!$C$90=0,Inputs!$C$90="",ISERROR(Inputs!$C$90)),Inputs!$D$90,Inputs!$C$90*Inputs!$K$9*(1+Inputs!$K$12)^B197),"Error - Check Input") +IFERROR(IF(OR(Inputs!$C$93=0,Inputs!$C$93="",ISERROR(Inputs!$C$93)),Inputs!$D$93,Inputs!$C$93*Inputs!$K$9*(1+Inputs!$K$12)^B197),"Error - Check Input") -> 38007.529 | F197: Est. Equity Value | H197: =_xlfn.XLOOKUP(Inputs!$K$10,'RE Calculations'!$B$79:$B$130,'RE Calculations'!$D$79:$D$130) -> 2086720.4
B198: 7 | C198: =IFERROR(IF(OR(Inputs!$C$84=0,Inputs!$C$84="",ISERROR(Inputs!$C$84)),Inputs!$D$84,Inputs!$C$84*Inputs!$K$9*(1+Inputs!$K$12)^B198),"Error - Check Input") +IFERROR(IF(OR(Inputs!$C$85=0,Inputs!$C$85="",ISERROR(Inputs!$C$85)),Inputs!$D$85,Inputs!$C$85*Inputs!$K$9*(1+Inputs!$K$12)^B198),"Error - Check Input") +IFERROR(IF(OR(Inputs!$C$86=0,Inputs!$C$86="",ISERROR(Inputs!$C$86)),Inputs!$D$86,Inputs!$C$86*Inputs!$K$9*(1+Inputs!$K$12)^B198),"Error - Check Input") +IFERROR(IF(OR(Inputs!$C$87=0,Inputs!$C$87="",ISERROR(Inputs!$C$87)),Inputs!$D$87,Inputs!$C$87*Inputs!$K$9*(1+Inputs!$K$12)^B198),"Error - Check Input") +IFERROR(IF(OR(Inputs!$C$88=0,Inputs!$C$88="",ISERROR(Inputs!$C$88)),Inputs!$D$88,Inputs!$C$88*Inputs!$K$9*(1+Inputs!$K$12)^B198),"Error - Check Input") +IFERROR(IF(OR(Inputs!$C$89=0,Inputs!$C$89="",ISERROR(Inputs!$C$89)),Inputs!$D$89,Inputs!$C$89*Inputs!$K$9*(1+Inputs!$K$12)^B198),"Error - Check Input") +IFERROR(IF(OR(Inputs!$C$90=0,Inputs!$C$90="",ISERROR(Inputs!$C$90)),Inputs!$D$90,Inputs!$C$90*Inputs!$K$9*(1+Inputs!$K$12)^B198),"Error - Check Input") +IFERROR(IF(OR(Inputs!$C$93=0,Inputs!$C$93="",ISERROR(Inputs!$C$93)),Inputs!$D$93,Inputs!$C$93*Inputs!$K$9*(1+Inputs!$K$12)^B198),"Error - Check Input") -> 38144.043 | F198: Gross Profit After Sale | H198: =IF($B$77=Inputs!$B$18,_xlfn.XLOOKUP(Inputs!$K$10,'Forecast (By Year)'!$F$4:$F$55,'Forecast (By Year)'!$V$4:$V$55),_xlfn.XLOOKUP(Inputs!$K$10,'Forecast (By Year)'!$AD$4:$AD$55,'Forecast (By Year)'!$AT$4:$AT$55)) -> 439458.95 | I198: Property Value less Purchasing Costs
B199: 8 | C199: =IFERROR(IF(OR(Inputs!$C$84=0,Inputs!$C$84="",ISERROR(Inputs!$C$84)),Inputs!$D$84,Inputs!$C$84*Inputs!$K$9*(1+Inputs!$K$12)^B199),"Error - Check Input") +IFERROR(IF(OR(Inputs!$C$85=0,Inputs!$C$85="",ISERROR(Inputs!$C$85)),Inputs!$D$85,Inputs!$C$85*Inputs!$K$9*(1+Inputs!$K$12)^B199),"Error - Check Input") +IFERROR(IF(OR(Inputs!$C$86=0,Inputs!$C$86="",ISERROR(Inputs!$C$86)),Inputs!$D$86,Inputs!$C$86*Inputs!$K$9*(1+Inputs!$K$12)^B199),"Error - Check Input") +IFERROR(IF(OR(Inputs!$C$87=0,Inputs!$C$87="",ISERROR(Inputs!$C$87)),Inputs!$D$87,Inputs!$C$87*Inputs!$K$9*(1+Inputs!$K$12)^B199),"Error - Check Input") +IFERROR(IF(OR(Inputs!$C$88=0,Inputs!$C$88="",ISERROR(Inputs!$C$88)),Inputs!$D$88,Inputs!$C$88*Inputs!$K$9*(1+Inputs!$K$12)^B199),"Error - Check Input") +IFERROR(IF(OR(Inputs!$C$89=0,Inputs!$C$89="",ISERROR(Inputs!$C$89)),Inputs!$D$89,Inputs!$C$89*Inputs!$K$9*(1+Inputs!$K$12)^B199),"Error - Check Input") +IFERROR(IF(OR(Inputs!$C$90=0,Inputs!$C$90="",ISERROR(Inputs!$C$90)),Inputs!$D$90,Inputs!$C$90*Inputs!$K$9*(1+Inputs!$K$12)^B199),"Error - Check Input") +IFERROR(IF(OR(Inputs!$C$93=0,Inputs!$C$93="",ISERROR(Inputs!$C$93)),Inputs!$D$93,Inputs!$C$93*Inputs!$K$9*(1+Inputs!$K$12)^B199),"Error - Check Input") -> 38281.113 | F199: Net Profit After Sale | H199: =IF($B$77=Inputs!$B$18,_xlfn.XLOOKUP(Inputs!$K$10,'Forecast (By Year)'!$F$4:$F$55,'Forecast (By Year)'!$Y$4:$Y$55),_xlfn.XLOOKUP(Inputs!$K$10,'Forecast (By Year)'!$AD$4:$AD$55,'Forecast (By Year)'!$AW$4:$AW$55)) -> 856703.56 | I199: Gross Profit less Cumulative Cash Flow
B200: 9 | C200: =IFERROR(IF(OR(Inputs!$C$84=0,Inputs!$C$84="",ISERROR(Inputs!$C$84)),Inputs!$D$84,Inputs!$C$84*Inputs!$K$9*(1+Inputs!$K$12)^B200),"Error - Check Input") +IFERROR(IF(OR(Inputs!$C$85=0,Inputs!$C$85="",ISERROR(Inputs!$C$85)),Inputs!$D$85,Inputs!$C$85*Inputs!$K$9*(1+Inputs!$K$12)^B200),"Error - Check Input") +IFERROR(IF(OR(Inputs!$C$86=0,Inputs!$C$86="",ISERROR(Inputs!$C$86)),Inputs!$D$86,Inputs!$C$86*Inputs!$K$9*(1+Inputs!$K$12)^B200),"Error - Check Input") +IFERROR(IF(OR(Inputs!$C$87=0,Inputs!$C$87="",ISERROR(Inputs!$C$87)),Inputs!$D$87,Inputs!$C$87*Inputs!$K$9*(1+Inputs!$K$12)^B200),"Error - Check Input") +IFERROR(IF(OR(Inputs!$C$88=0,Inputs!$C$88="",ISERROR(Inputs!$C$88)),Inputs!$D$88,Inputs!$C$88*Inputs!$K$9*(1+Inputs!$K$12)^B200),"Error - Check Input") +IFERROR(IF(OR(Inputs!$C$89=0,Inputs!$C$89="",ISERROR(Inputs!$C$89)),Inputs!$D$89,Inputs!$C$89*Inputs!$K$9*(1+Inputs!$K$12)^B200),"Error - Check Input") +IFERROR(IF(OR(Inputs!$C$90=0,Inputs!$C$90="",ISERROR(Inputs!$C$90)),Inputs!$D$90,Inputs!$C$90*Inputs!$K$9*(1+Inputs!$K$12)^B200),"Error - Check Input") +IFERROR(IF(OR(Inputs!$C$93=0,Inputs!$C$93="",ISERROR(Inputs!$C$93)),Inputs!$D$93,Inputs!$C$93*Inputs!$K$9*(1+Inputs!$K$12)^B200),"Error - Check Input") -> 38418.741 | F200: Gross Annualized ROI | H200: =IF($B$77=Inputs!$B$18,_xlfn.XLOOKUP(Inputs!$K$10,'Forecast (By Year)'!$F$4:$F$55,'Forecast (By Year)'!$X$4:$X$55),_xlfn.XLOOKUP(Inputs!$K$10,'Forecast (By Year)'!$AD$4:$AD$55,'Forecast (By Year)'!$AV$4:$AV$55)) -> 0.054897131 | I200: (Gross Profit/Purchasing Costs Required)/Holding Period
B201: 10 | C201: =IFERROR(IF(OR(Inputs!$C$84=0,Inputs!$C$84="",ISERROR(Inputs!$C$84)),Inputs!$D$84,Inputs!$C$84*Inputs!$K$9*(1+Inputs!$K$12)^B201),"Error - Check Input") +IFERROR(IF(OR(Inputs!$C$85=0,Inputs!$C$85="",ISERROR(Inputs!$C$85)),Inputs!$D$85,Inputs!$C$85*Inputs!$K$9*(1+Inputs!$K$12)^B201),"Error - Check Input") +IFERROR(IF(OR(Inputs!$C$86=0,Inputs!$C$86="",ISERROR(Inputs!$C$86)),Inputs!$D$86,Inputs!$C$86*Inputs!$K$9*(1+Inputs!$K$12)^B201),"Error - Check Input") +IFERROR(IF(OR(Inputs!$C$87=0,Inputs!$C$87="",ISERROR(Inputs!$C$87)),Inputs!$D$87,Inputs!$C$87*Inputs!$K$9*(1+Inputs!$K$12)^B201),"Error - Check Input") +IFERROR(IF(OR(Inputs!$C$88=0,Inputs!$C$88="",ISERROR(Inputs!$C$88)),Inputs!$D$88,Inputs!$C$88*Inputs!$K$9*(1+Inputs!$K$12)^B201),"Error - Check Input") +IFERROR(IF(OR(Inputs!$C$89=0,Inputs!$C$89="",ISERROR(Inputs!$C$89)),Inputs!$D$89,Inputs!$C$89*Inputs!$K$9*(1+Inputs!$K$12)^B201),"Error - Check Input") +IFERROR(IF(OR(Inputs!$C$90=0,Inputs!$C$90="",ISERROR(Inputs!$C$90)),Inputs!$D$90,Inputs!$C$90*Inputs!$K$9*(1+Inputs!$K$12)^B201),"Error - Check Input") +IFERROR(IF(OR(Inputs!$C$93=0,Inputs!$C$93="",ISERROR(Inputs!$C$93)),Inputs!$D$93,Inputs!$C$93*Inputs!$K$9*(1+Inputs!$K$12)^B201),"Error - Check Input") -> 38556.93 | F201: Net Annualized ROI | H201: =IF($B$77=Inputs!$B$18,_xlfn.XLOOKUP(Inputs!$K$10,'Forecast (By Year)'!$F$4:$F$55,'Forecast (By Year)'!$AA$4:$AA$55),_xlfn.XLOOKUP(Inputs!$K$10,'Forecast (By Year)'!$AD$4:$AD$55,'Forecast (By Year)'!$AY$4:$AY$55)) -> 0.10701925 | I201: (Net Profit/Purchasing Costs Required)/Holding Period
B202: 11 | C202: =IFERROR(IF(OR(Inputs!$C$84=0,Inputs!$C$84="",ISERROR(Inputs!$C$84)),Inputs!$D$84,Inputs!$C$84*Inputs!$K$9*(1+Inputs!$K$12)^B202),"Error - Check Input") +IFERROR(IF(OR(Inputs!$C$85=0,Inputs!$C$85="",ISERROR(Inputs!$C$85)),Inputs!$D$85,Inputs!$C$85*Inputs!$K$9*(1+Inputs!$K$12)^B202),"Error - Check Input") +IFERROR(IF(OR(Inputs!$C$86=0,Inputs!$C$86="",ISERROR(Inputs!$C$86)),Inputs!$D$86,Inputs!$C$86*Inputs!$K$9*(1+Inputs!$K$12)^B202),"Error - Check Input") +IFERROR(IF(OR(Inputs!$C$87=0,Inputs!$C$87="",ISERROR(Inputs!$C$87)),Inputs!$D$87,Inputs!$C$87*Inputs!$K$9*(1+Inputs!$K$12)^B202),"Error - Check Input") +IFERROR(IF(OR(Inputs!$C$88=0,Inputs!$C$88="",ISERROR(Inputs!$C$88)),Inputs!$D$88,Inputs!$C$88*Inputs!$K$9*(1+Inputs!$K$12)^B202),"Error - Check Input") +IFERROR(IF(OR(Inputs!$C$89=0,Inputs!$C$89="",ISERROR(Inputs!$C$89)),Inputs!$D$89,Inputs!$C$89*Inputs!$K$9*(1+Inputs!$K$12)^B202),"Error - Check Input") +IFERROR(IF(OR(Inputs!$C$90=0,Inputs!$C$90="",ISERROR(Inputs!$C$90)),Inputs!$D$90,Inputs!$C$90*Inputs!$K$9*(1+Inputs!$K$12)^B202),"Error - Check Input") +IFERROR(IF(OR(Inputs!$C$93=0,Inputs!$C$93="",ISERROR(Inputs!$C$93)),Inputs!$D$93,Inputs!$C$93*Inputs!$K$9*(1+Inputs!$K$12)^B202),"Error - Check Input") -> 38695.683 | F202: Gross Annualized ROE | H202: =(H198/H197)/Inputs!$K$10 -> 0.042119582 | I202: (Gross Profit/Est. Equity Value)/Holding Period
B203: 12 | C203: =IFERROR(IF(OR(Inputs!$C$84=0,Inputs!$C$84="",ISERROR(Inputs!$C$84)),Inputs!$D$84,Inputs!$C$84*Inputs!$K$9*(1+Inputs!$K$12)^B203),"Error - Check Input") +IFERROR(IF(OR(Inputs!$C$85=0,Inputs!$C$85="",ISERROR(Inputs!$C$85)),Inputs!$D$85,Inputs!$C$85*Inputs!$K$9*(1+Inputs!$K$12)^B203),"Error - Check Input") +IFERROR(IF(OR(Inputs!$C$86=0,Inputs!$C$86="",ISERROR(Inputs!$C$86)),Inputs!$D$86,Inputs!$C$86*Inputs!$K$9*(1+Inputs!$K$12)^B203),"Error - Check Input") +IFERROR(IF(OR(Inputs!$C$87=0,Inputs!$C$87="",ISERROR(Inputs!$C$87)),Inputs!$D$87,Inputs!$C$87*Inputs!$K$9*(1+Inputs!$K$12)^B203),"Error - Check Input") +IFERROR(IF(OR(Inputs!$C$88=0,Inputs!$C$88="",ISERROR(Inputs!$C$88)),Inputs!$D$88,Inputs!$C$88*Inputs!$K$9*(1+Inputs!$K$12)^B203),"Error - Check Input") +IFERROR(IF(OR(Inputs!$C$89=0,Inputs!$C$89="",ISERROR(Inputs!$C$89)),Inputs!$D$89,Inputs!$C$89*Inputs!$K$9*(1+Inputs!$K$12)^B203),"Error - Check Input") +IFERROR(IF(OR(Inputs!$C$90=0,Inputs!$C$90="",ISERROR(Inputs!$C$90)),Inputs!$D$90,Inputs!$C$90*Inputs!$K$9*(1+Inputs!$K$12)^B203),"Error - Check Input") +IFERROR(IF(OR(Inputs!$C$93=0,Inputs!$C$93="",ISERROR(Inputs!$C$93)),Inputs!$D$93,Inputs!$C$93*Inputs!$K$9*(1+Inputs!$K$12)^B203),"Error - Check Input") -> 38835 | F203: Net Annualized ROE | H203: =(H199/H197)/Inputs!$K$10 -> 0.08211005 | I203: (Net Profit/Est. Equity Value)/Holding Period
B204: 13 | C204: =IFERROR(IF(OR(Inputs!$C$84=0,Inputs!$C$84="",ISERROR(Inputs!$C$84)),Inputs!$D$84,Inputs!$C$84*Inputs!$K$9*(1+Inputs!$K$12)^B204),"Error - Check Input") +IFERROR(IF(OR(Inputs!$C$85=0,Inputs!$C$85="",ISERROR(Inputs!$C$85)),Inputs!$D$85,Inputs!$C$85*Inputs!$K$9*(1+Inputs!$K$12)^B204),"Error - Check Input") +IFERROR(IF(OR(Inputs!$C$86=0,Inputs!$C$86="",ISERROR(Inputs!$C$86)),Inputs!$D$86,Inputs!$C$86*Inputs!$K$9*(1+Inputs!$K$12)^B204),"Error - Check Input") +IFERROR(IF(OR(Inputs!$C$87=0,Inputs!$C$87="",ISERROR(Inputs!$C$87)),Inputs!$D$87,Inputs!$C$87*Inputs!$K$9*(1+Inputs!$K$12)^B204),"Error - Check Input") +IFERROR(IF(OR(Inputs!$C$88=0,Inputs!$C$88="",ISERROR(Inputs!$C$88)),Inputs!$D$88,Inputs!$C$88*Inputs!$K$9*(1+Inputs!$K$12)^B204),"Error - Check Input") +IFERROR(IF(OR(Inputs!$C$89=0,Inputs!$C$89="",ISERROR(Inputs!$C$89)),Inputs!$D$89,Inputs!$C$89*Inputs!$K$9*(1+Inputs!$K$12)^B204),"Error - Check Input") +IFERROR(IF(OR(Inputs!$C$90=0,Inputs!$C$90="",ISERROR(Inputs!$C$90)),Inputs!$D$90,Inputs!$C$90*Inputs!$K$9*(1+Inputs!$K$12)^B204),"Error - Check Input") +IFERROR(IF(OR(Inputs!$C$93=0,Inputs!$C$93="",ISERROR(Inputs!$C$93)),Inputs!$D$93,Inputs!$C$93*Inputs!$K$9*(1+Inputs!$K$12)^B204),"Error - Check Input") -> 38974.885 | F204: Capitalization Rate | H204: =IF($B$77=Inputs!$B$18,_xlfn.XLOOKUP(Inputs!$K$10,'Forecast (By Year)'!$F$4:$F$55,'Forecast (By Year)'!$T$4:$T$55),_xlfn.XLOOKUP(Inputs!$K$10,'Forecast (By Year)'!$AD$4:$AD$55,'Forecast (By Year)'!$AR$4:$AR$55))/$H$195 -> 0.044839481 | I204: Annual Operating Income/Total Purchase Price
B205: 14 | C205: =IFERROR(IF(OR(Inputs!$C$84=0,Inputs!$C$84="",ISERROR(Inputs!$C$84)),Inputs!$D$84,Inputs!$C$84*Inputs!$K$9*(1+Inputs!$K$12)^B205),"Error - Check Input") +IFERROR(IF(OR(Inputs!$C$85=0,Inputs!$C$85="",ISERROR(Inputs!$C$85)),Inputs!$D$85,Inputs!$C$85*Inputs!$K$9*(1+Inputs!$K$12)^B205),"Error - Check Input") +IFERROR(IF(OR(Inputs!$C$86=0,Inputs!$C$86="",ISERROR(Inputs!$C$86)),Inputs!$D$86,Inputs!$C$86*Inputs!$K$9*(1+Inputs!$K$12)^B205),"Error - Check Input") +IFERROR(IF(OR(Inputs!$C$87=0,Inputs!$C$87="",ISERROR(Inputs!$C$87)),Inputs!$D$87,Inputs!$C$87*Inputs!$K$9*(1+Inputs!$K$12)^B205),"Error - Check Input") +IFERROR(IF(OR(Inputs!$C$88=0,Inputs!$C$88="",ISERROR(Inputs!$C$88)),Inputs!$D$88,Inputs!$C$88*Inputs!$K$9*(1+Inputs!$K$12)^B205),"Error - Check Input") +IFERROR(IF(OR(Inputs!$C$89=0,Inputs!$C$89="",ISERROR(Inputs!$C$89)),Inputs!$D$89,Inputs!$C$89*Inputs!$K$9*(1+Inputs!$K$12)^B205),"Error - Check Input") +IFERROR(IF(OR(Inputs!$C$90=0,Inputs!$C$90="",ISERROR(Inputs!$C$90)),Inputs!$D$90,Inputs!$C$90*Inputs!$K$9*(1+Inputs!$K$12)^B205),"Error - Check Input") +IFERROR(IF(OR(Inputs!$C$93=0,Inputs!$C$93="",ISERROR(Inputs!$C$93)),Inputs!$D$93,Inputs!$C$93*Inputs!$K$9*(1+Inputs!$K$12)^B205),"Error - Check Input") -> 39115.34 | F205: DSCR | H205: =IF($B$77=Inputs!$B$18,_xlfn.XLOOKUP(Inputs!$K$10,'Forecast (By Year)'!$F$4:$F$55,'Forecast (By Year)'!$I$4:$I$55),_xlfn.XLOOKUP(Inputs!$K$10,'Forecast (By Year)'!$AD$4:$AD$55,'Forecast (By Year)'!$AG$4:$AG$55))/$H$190 -> 1251.9714 | I205: After Tax Cash Flow/Debt Service
B206: 15 | C206: =IFERROR(IF(OR(Inputs!$C$84=0,Inputs!$C$84="",ISERROR(Inputs!$C$84)),Inputs!$D$84,Inputs!$C$84*Inputs!$K$9*(1+Inputs!$K$12)^B206),"Error - Check Input") +IFERROR(IF(OR(Inputs!$C$85=0,Inputs!$C$85="",ISERROR(Inputs!$C$85)),Inputs!$D$85,Inputs!$C$85*Inputs!$K$9*(1+Inputs!$K$12)^B206),"Error - Check Input") +IFERROR(IF(OR(Inputs!$C$86=0,Inputs!$C$86="",ISERROR(Inputs!$C$86)),Inputs!$D$86,Inputs!$C$86*Inputs!$K$9*(1+Inputs!$K$12)^B206),"Error - Check Input") +IFERROR(IF(OR(Inputs!$C$87=0,Inputs!$C$87="",ISERROR(Inputs!$C$87)),Inputs!$D$87,Inputs!$C$87*Inputs!$K$9*(1+Inputs!$K$12)^B206),"Error - Check Input") +IFERROR(IF(OR(Inputs!$C$88=0,Inputs!$C$88="",ISERROR(Inputs!$C$88)),Inputs!$D$88,Inputs!$C$88*Inputs!$K$9*(1+Inputs!$K$12)^B206),"Error - Check Input") +IFERROR(IF(OR(Inputs!$C$89=0,Inputs!$C$89="",ISERROR(Inputs!$C$89)),Inputs!$D$89,Inputs!$C$89*Inputs!$K$9*(1+Inputs!$K$12)^B206),"Error - Check Input") +IFERROR(IF(OR(Inputs!$C$90=0,Inputs!$C$90="",ISERROR(Inputs!$C$90)),Inputs!$D$90,Inputs!$C$90*Inputs!$K$9*(1+Inputs!$K$12)^B206),"Error - Check Input") +IFERROR(IF(OR(Inputs!$C$93=0,Inputs!$C$93="",ISERROR(Inputs!$C$93)),Inputs!$D$93,Inputs!$C$93*Inputs!$K$9*(1+Inputs!$K$12)^B206),"Error - Check Input") -> 39256.367 | F206: LTV | H206: =$H$191/$H$195 -> 0 | I206: Loan Balance/Est. Property Value
B207: 16 | C207: =IFERROR(IF(OR(Inputs!$C$84=0,Inputs!$C$84="",ISERROR(Inputs!$C$84)),Inputs!$D$84,Inputs!$C$84*Inputs!$K$9*(1+Inputs!$K$12)^B207),"Error - Check Input") +IFERROR(IF(OR(Inputs!$C$85=0,Inputs!$C$85="",ISERROR(Inputs!$C$85)),Inputs!$D$85,Inputs!$C$85*Inputs!$K$9*(1+Inputs!$K$12)^B207),"Error - Check Input") +IFERROR(IF(OR(Inputs!$C$86=0,Inputs!$C$86="",ISERROR(Inputs!$C$86)),Inputs!$D$86,Inputs!$C$86*Inputs!$K$9*(1+Inputs!$K$12)^B207),"Error - Check Input") +IFERROR(IF(OR(Inputs!$C$87=0,Inputs!$C$87="",ISERROR(Inputs!$C$87)),Inputs!$D$87,Inputs!$C$87*Inputs!$K$9*(1+Inputs!$K$12)^B207),"Error - Check Input") +IFERROR(IF(OR(Inputs!$C$88=0,Inputs!$C$88="",ISERROR(Inputs!$C$88)),Inputs!$D$88,Inputs!$C$88*Inputs!$K$9*(1+Inputs!$K$12)^B207),"Error - Check Input") +IFERROR(IF(OR(Inputs!$C$89=0,Inputs!$C$89="",ISERROR(Inputs!$C$89)),Inputs!$D$89,Inputs!$C$89*Inputs!$K$9*(1+Inputs!$K$12)^B207),"Error - Check Input") +IFERROR(IF(OR(Inputs!$C$90=0,Inputs!$C$90="",ISERROR(Inputs!$C$90)),Inputs!$D$90,Inputs!$C$90*Inputs!$K$9*(1+Inputs!$K$12)^B207),"Error - Check Input") +IFERROR(IF(OR(Inputs!$C$93=0,Inputs!$C$93="",ISERROR(Inputs!$C$93)),Inputs!$D$93,Inputs!$C$93*Inputs!$K$9*(1+Inputs!$K$12)^B207),"Error - Check Input") -> 39397.969 | F207: LTC | H207: =$H$191/Inputs!$C$6 -> 0 | I207: Loan Balance/Purchase Price
B208: 17 | C208: =IFERROR(IF(OR(Inputs!$C$84=0,Inputs!$C$84="",ISERROR(Inputs!$C$84)),Inputs!$D$84,Inputs!$C$84*Inputs!$K$9*(1+Inputs!$K$12)^B208),"Error - Check Input") +IFERROR(IF(OR(Inputs!$C$85=0,Inputs!$C$85="",ISERROR(Inputs!$C$85)),Inputs!$D$85,Inputs!$C$85*Inputs!$K$9*(1+Inputs!$K$12)^B208),"Error - Check Input") +IFERROR(IF(OR(Inputs!$C$86=0,Inputs!$C$86="",ISERROR(Inputs!$C$86)),Inputs!$D$86,Inputs!$C$86*Inputs!$K$9*(1+Inputs!$K$12)^B208),"Error - Check Input") +IFERROR(IF(OR(Inputs!$C$87=0,Inputs!$C$87="",ISERROR(Inputs!$C$87)),Inputs!$D$87,Inputs!$C$87*Inputs!$K$9*(1+Inputs!$K$12)^B208),"Error - Check Input") +IFERROR(IF(OR(Inputs!$C$88=0,Inputs!$C$88="",ISERROR(Inputs!$C$88)),Inputs!$D$88,Inputs!$C$88*Inputs!$K$9*(1+Inputs!$K$12)^B208),"Error - Check Input") +IFERROR(IF(OR(Inputs!$C$89=0,Inputs!$C$89="",ISERROR(Inputs!$C$89)),Inputs!$D$89,Inputs!$C$89*Inputs!$K$9*(1+Inputs!$K$12)^B208),"Error - Check Input") +IFERROR(IF(OR(Inputs!$C$90=0,Inputs!$C$90="",ISERROR(Inputs!$C$90)),Inputs!$D$90,Inputs!$C$90*Inputs!$K$9*(1+Inputs!$K$12)^B208),"Error - Check Input") +IFERROR(IF(OR(Inputs!$C$93=0,Inputs!$C$93="",ISERROR(Inputs!$C$93)),Inputs!$D$93,Inputs!$C$93*Inputs!$K$9*(1+Inputs!$K$12)^B208),"Error - Check Input") -> 39540.148
B209: 18 | C209: =IFERROR(IF(OR(Inputs!$C$84=0,Inputs!$C$84="",ISERROR(Inputs!$C$84)),Inputs!$D$84,Inputs!$C$84*Inputs!$K$9*(1+Inputs!$K$12)^B209),"Error - Check Input") +IFERROR(IF(OR(Inputs!$C$85=0,Inputs!$C$85="",ISERROR(Inputs!$C$85)),Inputs!$D$85,Inputs!$C$85*Inputs!$K$9*(1+Inputs!$K$12)^B209),"Error - Check Input") +IFERROR(IF(OR(Inputs!$C$86=0,Inputs!$C$86="",ISERROR(Inputs!$C$86)),Inputs!$D$86,Inputs!$C$86*Inputs!$K$9*(1+Inputs!$K$12)^B209),"Error - Check Input") +IFERROR(IF(OR(Inputs!$C$87=0,Inputs!$C$87="",ISERROR(Inputs!$C$87)),Inputs!$D$87,Inputs!$C$87*Inputs!$K$9*(1+Inputs!$K$12)^B209),"Error - Check Input") +IFERROR(IF(OR(Inputs!$C$88=0,Inputs!$C$88="",ISERROR(Inputs!$C$88)),Inputs!$D$88,Inputs!$C$88*Inputs!$K$9*(1+Inputs!$K$12)^B209),"Error - Check Input") +IFERROR(IF(OR(Inputs!$C$89=0,Inputs!$C$89="",ISERROR(Inputs!$C$89)),Inputs!$D$89,Inputs!$C$89*Inputs!$K$9*(1+Inputs!$K$12)^B209),"Error - Check Input") +IFERROR(IF(OR(Inputs!$C$90=0,Inputs!$C$90="",ISERROR(Inputs!$C$90)),Inputs!$D$90,Inputs!$C$90*Inputs!$K$9*(1+Inputs!$K$12)^B209),"Error - Check Input") +IFERROR(IF(OR(Inputs!$C$93=0,Inputs!$C$93="",ISERROR(Inputs!$C$93)),Inputs!$D$93,Inputs!$C$93*Inputs!$K$9*(1+Inputs!$K$12)^B209),"Error - Check Input") -> 39682.905 | F209: Year 1 Before Tax
B210: 19 | C210: =IFERROR(IF(OR(Inputs!$C$84=0,Inputs!$C$84="",ISERROR(Inputs!$C$84)),Inputs!$D$84,Inputs!$C$84*Inputs!$K$9*(1+Inputs!$K$12)^B210),"Error - Check Input") +IFERROR(IF(OR(Inputs!$C$85=0,Inputs!$C$85="",ISERROR(Inputs!$C$85)),Inputs!$D$85,Inputs!$C$85*Inputs!$K$9*(1+Inputs!$K$12)^B210),"Error - Check Input") +IFERROR(IF(OR(Inputs!$C$86=0,Inputs!$C$86="",ISERROR(Inputs!$C$86)),Inputs!$D$86,Inputs!$C$86*Inputs!$K$9*(1+Inputs!$K$12)^B210),"Error - Check Input") +IFERROR(IF(OR(Inputs!$C$87=0,Inputs!$C$87="",ISERROR(Inputs!$C$87)),Inputs!$D$87,Inputs!$C$87*Inputs!$K$9*(1+Inputs!$K$12)^B210),"Error - Check Input") +IFERROR(IF(OR(Inputs!$C$88=0,Inputs!$C$88="",ISERROR(Inputs!$C$88)),Inputs!$D$88,Inputs!$C$88*Inputs!$K$9*(1+Inputs!$K$12)^B210),"Error - Check Input") +IFERROR(IF(OR(Inputs!$C$89=0,Inputs!$C$89="",ISERROR(Inputs!$C$89)),Inputs!$D$89,Inputs!$C$89*Inputs!$K$9*(1+Inputs!$K$12)^B210),"Error - Check Input") +IFERROR(IF(OR(Inputs!$C$90=0,Inputs!$C$90="",ISERROR(Inputs!$C$90)),Inputs!$D$90,Inputs!$C$90*Inputs!$K$9*(1+Inputs!$K$12)^B210),"Error - Check Input") +IFERROR(IF(OR(Inputs!$C$93=0,Inputs!$C$93="",ISERROR(Inputs!$C$93)),Inputs!$D$93,Inputs!$C$93*Inputs!$K$9*(1+Inputs!$K$12)^B210),"Error - Check Input") -> 39826.245 | F210: Cash on Cash Return | H210: =IF($B$77=Inputs!$B$18,_xlfn.XLOOKUP(1,'Forecast (By Year)'!$F$3:$F$55,'Forecast (By Year)'!$R$3:$R$55)/Inputs!$K$18,_xlfn.XLOOKUP(1,'Forecast (By Year)'!$AD$3:$AD$55,'Forecast (By Year)'!$AP$3:$AP$55)/Inputs!$K$18) -> 0.046102908 | I210: Annual Before Tax Cash Flow/Purchasing Costs
B211: 20 | C211: =IFERROR(IF(OR(Inputs!$C$84=0,Inputs!$C$84="",ISERROR(Inputs!$C$84)),Inputs!$D$84,Inputs!$C$84*Inputs!$K$9*(1+Inputs!$K$12)^B211),"Error - Check Input") +IFERROR(IF(OR(Inputs!$C$85=0,Inputs!$C$85="",ISERROR(Inputs!$C$85)),Inputs!$D$85,Inputs!$C$85*Inputs!$K$9*(1+Inputs!$K$12)^B211),"Error - Check Input") +IFERROR(IF(OR(Inputs!$C$86=0,Inputs!$C$86="",ISERROR(Inputs!$C$86)),Inputs!$D$86,Inputs!$C$86*Inputs!$K$9*(1+Inputs!$K$12)^B211),"Error - Check Input") +IFERROR(IF(OR(Inputs!$C$87=0,Inputs!$C$87="",ISERROR(Inputs!$C$87)),Inputs!$D$87,Inputs!$C$87*Inputs!$K$9*(1+Inputs!$K$12)^B211),"Error - Check Input") +IFERROR(IF(OR(Inputs!$C$88=0,Inputs!$C$88="",ISERROR(Inputs!$C$88)),Inputs!$D$88,Inputs!$C$88*Inputs!$K$9*(1+Inputs!$K$12)^B211),"Error - Check Input") +IFERROR(IF(OR(Inputs!$C$89=0,Inputs!$C$89="",ISERROR(Inputs!$C$89)),Inputs!$D$89,Inputs!$C$89*Inputs!$K$9*(1+Inputs!$K$12)^B211),"Error - Check Input") +IFERROR(IF(OR(Inputs!$C$90=0,Inputs!$C$90="",ISERROR(Inputs!$C$90)),Inputs!$D$90,Inputs!$C$90*Inputs!$K$9*(1+Inputs!$K$12)^B211),"Error - Check Input") +IFERROR(IF(OR(Inputs!$C$93=0,Inputs!$C$93="",ISERROR(Inputs!$C$93)),Inputs!$D$93,Inputs!$C$93*Inputs!$K$9*(1+Inputs!$K$12)^B211),"Error - Check Input") -> 39970.168 | F211: Yield on Cost | H211: =IF($B$77=Inputs!$B$18,_xlfn.XLOOKUP(1,'Forecast (By Year)'!$F$3:$F$55,'Forecast (By Year)'!$R$3:$R$55)/Inputs!$K$5,_xlfn.XLOOKUP(1,'Forecast (By Year)'!$AD$3:$AD$55,'Forecast (By Year)'!$AP$3:$AP$55)/Inputs!$K$5) -> 0.04920964 | I211: Annual Before Tax Cash Flow/Total Purchase Price
B212: 21 | C212: =IFERROR(IF(OR(Inputs!$C$84=0,Inputs!$C$84="",ISERROR(Inputs!$C$84)),Inputs!$D$84,Inputs!$C$84*Inputs!$K$9*(1+Inputs!$K$12)^B212),"Error - Check Input") +IFERROR(IF(OR(Inputs!$C$85=0,Inputs!$C$85="",ISERROR(Inputs!$C$85)),Inputs!$D$85,Inputs!$C$85*Inputs!$K$9*(1+Inputs!$K$12)^B212),"Error - Check Input") +IFERROR(IF(OR(Inputs!$C$86=0,Inputs!$C$86="",ISERROR(Inputs!$C$86)),Inputs!$D$86,Inputs!$C$86*Inputs!$K$9*(1+Inputs!$K$12)^B212),"Error - Check Input") +IFERROR(IF(OR(Inputs!$C$87=0,Inputs!$C$87="",ISERROR(Inputs!$C$87)),Inputs!$D$87,Inputs!$C$87*Inputs!$K$9*(1+Inputs!$K$12)^B212),"Error - Check Input") +IFERROR(IF(OR(Inputs!$C$88=0,Inputs!$C$88="",ISERROR(Inputs!$C$88)),Inputs!$D$88,Inputs!$C$88*Inputs!$K$9*(1+Inputs!$K$12)^B212),"Error - Check Input") +IFERROR(IF(OR(Inputs!$C$89=0,Inputs!$C$89="",ISERROR(Inputs!$C$89)),Inputs!$D$89,Inputs!$C$89*Inputs!$K$9*(1+Inputs!$K$12)^B212),"Error - Check Input") +IFERROR(IF(OR(Inputs!$C$90=0,Inputs!$C$90="",ISERROR(Inputs!$C$90)),Inputs!$D$90,Inputs!$C$90*Inputs!$K$9*(1+Inputs!$K$12)^B212),"Error - Check Input") +IFERROR(IF(OR(Inputs!$C$93=0,Inputs!$C$93="",ISERROR(Inputs!$C$93)),Inputs!$D$93,Inputs!$C$93*Inputs!$K$9*(1+Inputs!$K$12)^B212),"Error - Check Input") -> 40114.678 | F212: Yield on Value | H212: =IF($B$77=Inputs!$B$18,_xlfn.XLOOKUP(1,'Forecast (By Year)'!$F$3:$F$55,'Forecast (By Year)'!$R$3:$R$55)/Inputs!$K$9,_xlfn.XLOOKUP(1,'Forecast (By Year)'!$AD$3:$AD$55,'Forecast (By Year)'!$AP$3:$AP$55)/Inputs!$K$9) -> 0.045144954 | I212: Annual Before Tax Cash Flow/Yr 1 Market Value or ARV
B213: 22 | C213: =IFERROR(IF(OR(Inputs!$C$84=0,Inputs!$C$84="",ISERROR(Inputs!$C$84)),Inputs!$D$84,Inputs!$C$84*Inputs!$K$9*(1+Inputs!$K$12)^B213),"Error - Check Input") +IFERROR(IF(OR(Inputs!$C$85=0,Inputs!$C$85="",ISERROR(Inputs!$C$85)),Inputs!$D$85,Inputs!$C$85*Inputs!$K$9*(1+Inputs!$K$12)^B213),"Error - Check Input") +IFERROR(IF(OR(Inputs!$C$86=0,Inputs!$C$86="",ISERROR(Inputs!$C$86)),Inputs!$D$86,Inputs!$C$86*Inputs!$K$9*(1+Inputs!$K$12)^B213),"Error - Check Input") +IFERROR(IF(OR(Inputs!$C$87=0,Inputs!$C$87="",ISERROR(Inputs!$C$87)),Inputs!$D$87,Inputs!$C$87*Inputs!$K$9*(1+Inputs!$K$12)^B213),"Error - Check Input") +IFERROR(IF(OR(Inputs!$C$88=0,Inputs!$C$88="",ISERROR(Inputs!$C$88)),Inputs!$D$88,Inputs!$C$88*Inputs!$K$9*(1+Inputs!$K$12)^B213),"Error - Check Input") +IFERROR(IF(OR(Inputs!$C$89=0,Inputs!$C$89="",ISERROR(Inputs!$C$89)),Inputs!$D$89,Inputs!$C$89*Inputs!$K$9*(1+Inputs!$K$12)^B213),"Error - Check Input") +IFERROR(IF(OR(Inputs!$C$90=0,Inputs!$C$90="",ISERROR(Inputs!$C$90)),Inputs!$D$90,Inputs!$C$90*Inputs!$K$9*(1+Inputs!$K$12)^B213),"Error - Check Input") +IFERROR(IF(OR(Inputs!$C$93=0,Inputs!$C$93="",ISERROR(Inputs!$C$93)),Inputs!$D$93,Inputs!$C$93*Inputs!$K$9*(1+Inputs!$K$12)^B213),"Error - Check Input") -> 40259.777 | F213: Year 1 After Tax
B214: 23 | C214: =IFERROR(IF(OR(Inputs!$C$84=0,Inputs!$C$84="",ISERROR(Inputs!$C$84)),Inputs!$D$84,Inputs!$C$84*Inputs!$K$9*(1+Inputs!$K$12)^B214),"Error - Check Input") +IFERROR(IF(OR(Inputs!$C$85=0,Inputs!$C$85="",ISERROR(Inputs!$C$85)),Inputs!$D$85,Inputs!$C$85*Inputs!$K$9*(1+Inputs!$K$12)^B214),"Error - Check Input") +IFERROR(IF(OR(Inputs!$C$86=0,Inputs!$C$86="",ISERROR(Inputs!$C$86)),Inputs!$D$86,Inputs!$C$86*Inputs!$K$9*(1+Inputs!$K$12)^B214),"Error - Check Input") +IFERROR(IF(OR(Inputs!$C$87=0,Inputs!$C$87="",ISERROR(Inputs!$C$87)),Inputs!$D$87,Inputs!$C$87*Inputs!$K$9*(1+Inputs!$K$12)^B214),"Error - Check Input") +IFERROR(IF(OR(Inputs!$C$88=0,Inputs!$C$88="",ISERROR(Inputs!$C$88)),Inputs!$D$88,Inputs!$C$88*Inputs!$K$9*(1+Inputs!$K$12)^B214),"Error - Check Input") +IFERROR(IF(OR(Inputs!$C$89=0,Inputs!$C$89="",ISERROR(Inputs!$C$89)),Inputs!$D$89,Inputs!$C$89*Inputs!$K$9*(1+Inputs!$K$12)^B214),"Error - Check Input") +IFERROR(IF(OR(Inputs!$C$90=0,Inputs!$C$90="",ISERROR(Inputs!$C$90)),Inputs!$D$90,Inputs!$C$90*Inputs!$K$9*(1+Inputs!$K$12)^B214),"Error - Check Input") +IFERROR(IF(OR(Inputs!$C$93=0,Inputs!$C$93="",ISERROR(Inputs!$C$93)),Inputs!$D$93,Inputs!$C$93*Inputs!$K$9*(1+Inputs!$K$12)^B214),"Error - Check Input") -> 40405.467 | F214: Cash on Cash Return | H214: =IF($B$77=Inputs!$B$18,_xlfn.XLOOKUP(1,'Forecast (By Year)'!$F$3:$F$55,'Forecast (By Year)'!$T$3:$T$55)/Inputs!$K$18,_xlfn.XLOOKUP(1,'Forecast (By Year)'!$AD$3:$AD$55,'Forecast (By Year)'!$AR$3:$AR$55)/Inputs!$K$18) -> 0.046102908 | I214: Annual After Tax Cash Flow/Purchasing Costs
B215: 24 | C215: =IFERROR(IF(OR(Inputs!$C$84=0,Inputs!$C$84="",ISERROR(Inputs!$C$84)),Inputs!$D$84,Inputs!$C$84*Inputs!$K$9*(1+Inputs!$K$12)^B215),"Error - Check Input") +IFERROR(IF(OR(Inputs!$C$85=0,Inputs!$C$85="",ISERROR(Inputs!$C$85)),Inputs!$D$85,Inputs!$C$85*Inputs!$K$9*(1+Inputs!$K$12)^B215),"Error - Check Input") +IFERROR(IF(OR(Inputs!$C$86=0,Inputs!$C$86="",ISERROR(Inputs!$C$86)),Inputs!$D$86,Inputs!$C$86*Inputs!$K$9*(1+Inputs!$K$12)^B215),"Error - Check Input") +IFERROR(IF(OR(Inputs!$C$87=0,Inputs!$C$87="",ISERROR(Inputs!$C$87)),Inputs!$D$87,Inputs!$C$87*Inputs!$K$9*(1+Inputs!$K$12)^B215),"Error - Check Input") +IFERROR(IF(OR(Inputs!$C$88=0,Inputs!$C$88="",ISERROR(Inputs!$C$88)),Inputs!$D$88,Inputs!$C$88*Inputs!$K$9*(1+Inputs!$K$12)^B215),"Error - Check Input") +IFERROR(IF(OR(Inputs!$C$89=0,Inputs!$C$89="",ISERROR(Inputs!$C$89)),Inputs!$D$89,Inputs!$C$89*Inputs!$K$9*(1+Inputs!$K$12)^B215),"Error - Check Input") +IFERROR(IF(OR(Inputs!$C$90=0,Inputs!$C$90="",ISERROR(Inputs!$C$90)),Inputs!$D$90,Inputs!$C$90*Inputs!$K$9*(1+Inputs!$K$12)^B215),"Error - Check Input") +IFERROR(IF(OR(Inputs!$C$93=0,Inputs!$C$93="",ISERROR(Inputs!$C$93)),Inputs!$D$93,Inputs!$C$93*Inputs!$K$9*(1+Inputs!$K$12)^B215),"Error - Check Input") -> 40551.75 | F215: Yield on Cost | H215: =IF($B$77=Inputs!$B$18,_xlfn.XLOOKUP(1,'Forecast (By Year)'!$F$3:$F$55,'Forecast (By Year)'!$T$3:$T$55)/Inputs!$K$5,_xlfn.XLOOKUP(1,'Forecast (By Year)'!$AD$3:$AD$55,'Forecast (By Year)'!$AR$3:$AR$55)/Inputs!$K$5) -> 0.04920964 | I215: Annual After Tax Cash Flow/Total Purchase Price
B216: 25 | C216: =IFERROR(IF(OR(Inputs!$C$84=0,Inputs!$C$84="",ISERROR(Inputs!$C$84)),Inputs!$D$84,Inputs!$C$84*Inputs!$K$9*(1+Inputs!$K$12)^B216),"Error - Check Input") +IFERROR(IF(OR(Inputs!$C$85=0,Inputs!$C$85="",ISERROR(Inputs!$C$85)),Inputs!$D$85,Inputs!$C$85*Inputs!$K$9*(1+Inputs!$K$12)^B216),"Error - Check Input") +IFERROR(IF(OR(Inputs!$C$86=0,Inputs!$C$86="",ISERROR(Inputs!$C$86)),Inputs!$D$86,Inputs!$C$86*Inputs!$K$9*(1+Inputs!$K$12)^B216),"Error - Check Input") +IFERROR(IF(OR(Inputs!$C$87=0,Inputs!$C$87="",ISERROR(Inputs!$C$87)),Inputs!$D$87,Inputs!$C$87*Inputs!$K$9*(1+Inputs!$K$12)^B216),"Error - Check Input") +IFERROR(IF(OR(Inputs!$C$88=0,Inputs!$C$88="",ISERROR(Inputs!$C$88)),Inputs!$D$88,Inputs!$C$88*Inputs!$K$9*(1+Inputs!$K$12)^B216),"Error - Check Input") +IFERROR(IF(OR(Inputs!$C$89=0,Inputs!$C$89="",ISERROR(Inputs!$C$89)),Inputs!$D$89,Inputs!$C$89*Inputs!$K$9*(1+Inputs!$K$12)^B216),"Error - Check Input") +IFERROR(IF(OR(Inputs!$C$90=0,Inputs!$C$90="",ISERROR(Inputs!$C$90)),Inputs!$D$90,Inputs!$C$90*Inputs!$K$9*(1+Inputs!$K$12)^B216),"Error - Check Input") +IFERROR(IF(OR(Inputs!$C$93=0,Inputs!$C$93="",ISERROR(Inputs!$C$93)),Inputs!$D$93,Inputs!$C$93*Inputs!$K$9*(1+Inputs!$K$12)^B216),"Error - Check Input") -> 40698.629 | F216: Yield on Value | H216: =IF($B$77=Inputs!$B$18,_xlfn.XLOOKUP(1,'Forecast (By Year)'!$F$3:$F$55,'Forecast (By Year)'!$T$3:$T$55)/Inputs!$K$9,_xlfn.XLOOKUP(1,'Forecast (By Year)'!$AD$3:$AD$55,'Forecast (By Year)'!$AR$3:$AR$55)/Inputs!$K$9) -> 0.045144954 | I216: Annual After Tax Cash Flow/Yr 1 Market Value or ARV
B217: 26 | C217: =IFERROR(IF(OR(Inputs!$C$84=0,Inputs!$C$84="",ISERROR(Inputs!$C$84)),Inputs!$D$84,Inputs!$C$84*Inputs!$K$9*(1+Inputs!$K$12)^B217),"Error - Check Input") +IFERROR(IF(OR(Inputs!$C$85=0,Inputs!$C$85="",ISERROR(Inputs!$C$85)),Inputs!$D$85,Inputs!$C$85*Inputs!$K$9*(1+Inputs!$K$12)^B217),"Error - Check Input") +IFERROR(IF(OR(Inputs!$C$86=0,Inputs!$C$86="",ISERROR(Inputs!$C$86)),Inputs!$D$86,Inputs!$C$86*Inputs!$K$9*(1+Inputs!$K$12)^B217),"Error - Check Input") +IFERROR(IF(OR(Inputs!$C$87=0,Inputs!$C$87="",ISERROR(Inputs!$C$87)),Inputs!$D$87,Inputs!$C$87*Inputs!$K$9*(1+Inputs!$K$12)^B217),"Error - Check Input") +IFERROR(IF(OR(Inputs!$C$88=0,Inputs!$C$88="",ISERROR(Inputs!$C$88)),Inputs!$D$88,Inputs!$C$88*Inputs!$K$9*(1+Inputs!$K$12)^B217),"Error - Check Input") +IFERROR(IF(OR(Inputs!$C$89=0,Inputs!$C$89="",ISERROR(Inputs!$C$89)),Inputs!$D$89,Inputs!$C$89*Inputs!$K$9*(1+Inputs!$K$12)^B217),"Error - Check Input") +IFERROR(IF(OR(Inputs!$C$90=0,Inputs!$C$90="",ISERROR(Inputs!$C$90)),Inputs!$D$90,Inputs!$C$90*Inputs!$K$9*(1+Inputs!$K$12)^B217),"Error - Check Input") +IFERROR(IF(OR(Inputs!$C$93=0,Inputs!$C$93="",ISERROR(Inputs!$C$93)),Inputs!$D$93,Inputs!$C$93*Inputs!$K$9*(1+Inputs!$K$12)^B217),"Error - Check Input") -> 40846.107 | F217: ="Year "&Inputs!$K$10&" Before Tax" -> Year 5 Before Tax
B218: 27 | C218: =IFERROR(IF(OR(Inputs!$C$84=0,Inputs!$C$84="",ISERROR(Inputs!$C$84)),Inputs!$D$84,Inputs!$C$84*Inputs!$K$9*(1+Inputs!$K$12)^B218),"Error - Check Input") +IFERROR(IF(OR(Inputs!$C$85=0,Inputs!$C$85="",ISERROR(Inputs!$C$85)),Inputs!$D$85,Inputs!$C$85*Inputs!$K$9*(1+Inputs!$K$12)^B218),"Error - Check Input") +IFERROR(IF(OR(Inputs!$C$86=0,Inputs!$C$86="",ISERROR(Inputs!$C$86)),Inputs!$D$86,Inputs!$C$86*Inputs!$K$9*(1+Inputs!$K$12)^B218),"Error - Check Input") +IFERROR(IF(OR(Inputs!$C$87=0,Inputs!$C$87="",ISERROR(Inputs!$C$87)),Inputs!$D$87,Inputs!$C$87*Inputs!$K$9*(1+Inputs!$K$12)^B218),"Error - Check Input") +IFERROR(IF(OR(Inputs!$C$88=0,Inputs!$C$88="",ISERROR(Inputs!$C$88)),Inputs!$D$88,Inputs!$C$88*Inputs!$K$9*(1+Inputs!$K$12)^B218),"Error - Check Input") +IFERROR(IF(OR(Inputs!$C$89=0,Inputs!$C$89="",ISERROR(Inputs!$C$89)),Inputs!$D$89,Inputs!$C$89*Inputs!$K$9*(1+Inputs!$K$12)^B218),"Error - Check Input") +IFERROR(IF(OR(Inputs!$C$90=0,Inputs!$C$90="",ISERROR(Inputs!$C$90)),Inputs!$D$90,Inputs!$C$90*Inputs!$K$9*(1+Inputs!$K$12)^B218),"Error - Check Input") +IFERROR(IF(OR(Inputs!$C$93=0,Inputs!$C$93="",ISERROR(Inputs!$C$93)),Inputs!$D$93,Inputs!$C$93*Inputs!$K$9*(1+Inputs!$K$12)^B218),"Error - Check Input") -> 40994.186 | F218: Cash on Cash Return | H218: =IF($B$77=Inputs!$B$18,_xlfn.XLOOKUP(Inputs!$K$10,'Forecast (By Year)'!$F$3:$F$55,'Forecast (By Year)'!$R$3:$R$55)/Inputs!$K$18,_xlfn.XLOOKUP(Inputs!$K$10,'Forecast (By Year)'!$AD$3:$AD$55,'Forecast (By Year)'!$AP$3:$AP$55)/Inputs!$K$18) -> 0.058442149 | I218: Annual Before Tax Cash Flow/Purchasing Costs
B219: 28 | C219: =IFERROR(IF(OR(Inputs!$C$84=0,Inputs!$C$84="",ISERROR(Inputs!$C$84)),Inputs!$D$84,Inputs!$C$84*Inputs!$K$9*(1+Inputs!$K$12)^B219),"Error - Check Input") +IFERROR(IF(OR(Inputs!$C$85=0,Inputs!$C$85="",ISERROR(Inputs!$C$85)),Inputs!$D$85,Inputs!$C$85*Inputs!$K$9*(1+Inputs!$K$12)^B219),"Error - Check Input") +IFERROR(IF(OR(Inputs!$C$86=0,Inputs!$C$86="",ISERROR(Inputs!$C$86)),Inputs!$D$86,Inputs!$C$86*Inputs!$K$9*(1+Inputs!$K$12)^B219),"Error - Check Input") +IFERROR(IF(OR(Inputs!$C$87=0,Inputs!$C$87="",ISERROR(Inputs!$C$87)),Inputs!$D$87,Inputs!$C$87*Inputs!$K$9*(1+Inputs!$K$12)^B219),"Error - Check Input") +IFERROR(IF(OR(Inputs!$C$88=0,Inputs!$C$88="",ISERROR(Inputs!$C$88)),Inputs!$D$88,Inputs!$C$88*Inputs!$K$9*(1+Inputs!$K$12)^B219),"Error - Check Input") +IFERROR(IF(OR(Inputs!$C$89=0,Inputs!$C$89="",ISERROR(Inputs!$C$89)),Inputs!$D$89,Inputs!$C$89*Inputs!$K$9*(1+Inputs!$K$12)^B219),"Error - Check Input") +IFERROR(IF(OR(Inputs!$C$90=0,Inputs!$C$90="",ISERROR(Inputs!$C$90)),Inputs!$D$90,Inputs!$C$90*Inputs!$K$9*(1+Inputs!$K$12)^B219),"Error - Check Input") +IFERROR(IF(OR(Inputs!$C$93=0,Inputs!$C$93="",ISERROR(Inputs!$C$93)),Inputs!$D$93,Inputs!$C$93*Inputs!$K$9*(1+Inputs!$K$12)^B219),"Error - Check Input") -> 41142.867 | F219: Yield on Cost | H219: =IF($B$77=Inputs!$B$18,_xlfn.XLOOKUP(Inputs!$K$10,'Forecast (By Year)'!$F$3:$F$55,'Forecast (By Year)'!$R$3:$R$55)/Inputs!$K$5,_xlfn.XLOOKUP(Inputs!$K$10,'Forecast (By Year)'!$AD$3:$AD$55,'Forecast (By Year)'!$AP$3:$AP$55)/Inputs!$K$5) -> 0.062380385 | I219: Annual Before Tax Cash Flow/Total Purchase Price
B220: 29 | C220: =IFERROR(IF(OR(Inputs!$C$84=0,Inputs!$C$84="",ISERROR(Inputs!$C$84)),Inputs!$D$84,Inputs!$C$84*Inputs!$K$9*(1+Inputs!$K$12)^B220),"Error - Check Input") +IFERROR(IF(OR(Inputs!$C$85=0,Inputs!$C$85="",ISERROR(Inputs!$C$85)),Inputs!$D$85,Inputs!$C$85*Inputs!$K$9*(1+Inputs!$K$12)^B220),"Error - Check Input") +IFERROR(IF(OR(Inputs!$C$86=0,Inputs!$C$86="",ISERROR(Inputs!$C$86)),Inputs!$D$86,Inputs!$C$86*Inputs!$K$9*(1+Inputs!$K$12)^B220),"Error - Check Input") +IFERROR(IF(OR(Inputs!$C$87=0,Inputs!$C$87="",ISERROR(Inputs!$C$87)),Inputs!$D$87,Inputs!$C$87*Inputs!$K$9*(1+Inputs!$K$12)^B220),"Error - Check Input") +IFERROR(IF(OR(Inputs!$C$88=0,Inputs!$C$88="",ISERROR(Inputs!$C$88)),Inputs!$D$88,Inputs!$C$88*Inputs!$K$9*(1+Inputs!$K$12)^B220),"Error - Check Input") +IFERROR(IF(OR(Inputs!$C$89=0,Inputs!$C$89="",ISERROR(Inputs!$C$89)),Inputs!$D$89,Inputs!$C$89*Inputs!$K$9*(1+Inputs!$K$12)^B220),"Error - Check Input") +IFERROR(IF(OR(Inputs!$C$90=0,Inputs!$C$90="",ISERROR(Inputs!$C$90)),Inputs!$D$90,Inputs!$C$90*Inputs!$K$9*(1+Inputs!$K$12)^B220),"Error - Check Input") +IFERROR(IF(OR(Inputs!$C$93=0,Inputs!$C$93="",ISERROR(Inputs!$C$93)),Inputs!$D$93,Inputs!$C$93*Inputs!$K$9*(1+Inputs!$K$12)^B220),"Error - Check Input") -> 41292.155 | F220: Yield on Value | H220: =IF($B$77=Inputs!$B$18,_xlfn.XLOOKUP(Inputs!$K$10,'Forecast (By Year)'!$F$3:$F$55,'Forecast (By Year)'!$R$3:$R$55)/Inputs!$K$9,_xlfn.XLOOKUP(Inputs!$K$10,'Forecast (By Year)'!$AD$3:$AD$55,'Forecast (By Year)'!$AP$3:$AP$55)/Inputs!$K$9) -> 0.057227803 | I220: Annual Before Tax Cash Flow/Est. Property Value
B221: 30 | C221: =IFERROR(IF(OR(Inputs!$C$84=0,Inputs!$C$84="",ISERROR(Inputs!$C$84)),Inputs!$D$84,Inputs!$C$84*Inputs!$K$9*(1+Inputs!$K$12)^B221),"Error - Check Input") +IFERROR(IF(OR(Inputs!$C$85=0,Inputs!$C$85="",ISERROR(Inputs!$C$85)),Inputs!$D$85,Inputs!$C$85*Inputs!$K$9*(1+Inputs!$K$12)^B221),"Error - Check Input") +IFERROR(IF(OR(Inputs!$C$86=0,Inputs!$C$86="",ISERROR(Inputs!$C$86)),Inputs!$D$86,Inputs!$C$86*Inputs!$K$9*(1+Inputs!$K$12)^B221),"Error - Check Input") +IFERROR(IF(OR(Inputs!$C$87=0,Inputs!$C$87="",ISERROR(Inputs!$C$87)),Inputs!$D$87,Inputs!$C$87*Inputs!$K$9*(1+Inputs!$K$12)^B221),"Error - Check Input") +IFERROR(IF(OR(Inputs!$C$88=0,Inputs!$C$88="",ISERROR(Inputs!$C$88)),Inputs!$D$88,Inputs!$C$88*Inputs!$K$9*(1+Inputs!$K$12)^B221),"Error - Check Input") +IFERROR(IF(OR(Inputs!$C$89=0,Inputs!$C$89="",ISERROR(Inputs!$C$89)),Inputs!$D$89,Inputs!$C$89*Inputs!$K$9*(1+Inputs!$K$12)^B221),"Error - Check Input") +IFERROR(IF(OR(Inputs!$C$90=0,Inputs!$C$90="",ISERROR(Inputs!$C$90)),Inputs!$D$90,Inputs!$C$90*Inputs!$K$9*(1+Inputs!$K$12)^B221),"Error - Check Input") +IFERROR(IF(OR(Inputs!$C$93=0,Inputs!$C$93="",ISERROR(Inputs!$C$93)),Inputs!$D$93,Inputs!$C$93*Inputs!$K$9*(1+Inputs!$K$12)^B221),"Error - Check Input") -> 41442.051 | F221: ="Year "&Inputs!$K$10&" After Tax" -> Year 5 After Tax
...

Sheet Mortgage Calculators (By Month)
B2: PRINCIPAL & INTEREST LOAN (P&I) | I2: INTEREST ONLY LOAN (IO) | P2: MORTGAGE CALCULATOR - PRINCIPAL & INTEREST (COMPARISON) | W2: MORTGAGE CALCULATOR - INTEREST ONLY (COMPARISON)
B3: Total Price | C3: =Inputs!K5 -> 1499950 | I3: Total Price | J3: =C3 -> 1499950 | P3: Total Price | Q3: =C3 -> 1499950 | W3: Total Price | X3: =J3 -> 1499950
B4: Down Payment (%) | C4: =Inputs!K6 -> 1 | I4: Down Payment (%) | J4: =C4 -> 1 | P4: Down Payment (%) | Q4: =C4 -> 1 | W4: Down Payment (%) | X4: =J4 -> 1
B5: Down Payment ($) | C5: =C4*C3 -> 1499950 | I5: Down Payment ($) | J5: =J4*J3 -> 1499950 | P5: Down Payment ($) | Q5: =Q4*Q3 -> 1499950 | W5: Down Payment ($) | X5: =X4*X3 -> 1499950
B6: Principal Amount | C6: =C3-C5 -> 0 | I6: Principal Amount | J6: =J3-J5 -> 0 | P6: Principal Amount | Q6: =Q3-Q5 -> 0 | W6: Principal Amount | X6: =X3-X5 -> 0
B7: Annual Interest Rate | C7: =Inputs!K35 -> 0.045 | I7: Annual Interest Rate | J7: =Inputs!K42 -> 0.0475 | P7: Annual Interest Rate | Q7: 0.06 | W7: Annual Interest Rate | X7: 0.062
B8: Equivalent Monthly Interest Rate | C8: =C7/12 -> 0.00375 | I8: Equivalent Monthly Interest Rate | J8: =J7/12 -> 0.0039583333 | P8: Equivalent Monthly Interest Rate | Q8: =Q7/12 -> 0.005 | W8: Equivalent Monthly Interest Rate | X8: =X7/12 -> 0.0051666667
B9: Loan Duration (Years) | C9: =Inputs!K37 -> 30 | I9: Interest Only Duration (Years) | J9: =Inputs!K44 -> 5 | P9: Loan Duration (Years) | Q9: =C9 -> 30 | W9: Interest Only Duration (Years) | X9: =J9 -> 5
B10: Fees | C10: =Inputs!C21 -> 100 | D10: =Inputs!D21 -> per annum | I10: Standard Interest Rate | J10: =Inputs!K45 -> 0.045 | P10: Fees | Q10: =C10 -> 100 | R10: =D10 -> per annum | W10: Standard Interest Rate | X10: 0.06
I11: Equivalent Monthly Interest Rate | J11: =J10/12 -> 0.00375 | W11: Equivalent Monthly Interest Rate | X11: =X10/12 -> 0.005
B12: Monthly Loan Payment | C12: =-PMT(C8,C9*12,C6)+$C$10*_xlfn.XLOOKUP($D$10,'RE Calculations'!$B$12:$B$16,'RE Calculations'!$C$12:$C$16,"ERROR - Check Input")/12 -> 8.3333333 | I12: Total Loan Duration (Years) | J12: =Inputs!K47 -> 30 | P12: Monthly Loan Payment | Q12: =-PMT(Q8,Q9*12,Q6)+$Q$10*_xlfn.XLOOKUP($R$10,'RE Calculations'!$B$12:$B$16,'RE Calculations'!$C$12:$C$16,"ERROR - Check Input")/12 -> 8.3333333 | W12: Total Loan Duration (Years) | X12: =J12 -> 30
B13: Check | C13: =C6*((C8*((1+C8)^(C9*12)))/(((1+C8)^(C9*12))-1))+$C$10*_xlfn.XLOOKUP($D$10,'RE Calculations'!$B$12:$B$16,'RE Calculations'!$C$12:$C$16,"ERROR - Check Input")/12 -> 8.3333333 | I13: Fees | J13: =Inputs!C28 -> 120 | K13: =Inputs!D28 -> per annum | P13: Check | Q13: =Q6*((Q8*((1+Q8)^(Q9*12)))/(((1+Q8)^(Q9*12))-1))+$Q$10*_xlfn.XLOOKUP($R$10,'RE Calculations'!$B$12:$B$16,'RE Calculations'!$C$12:$C$16,"ERROR - Check Input")/12 -> 8.3333333 | W13: Fees | X13: =J13 -> 120 | Y13: =K13 -> per annum
I15: ="Montly Loan Payment (First "&J9&" Years)" -> Montly Loan Payment (First 5 Years) | J15: =J7*J6/12+$J$13*_xlfn.XLOOKUP($K$13,'RE Calculations'!$B$12:$B$16,'RE Calculations'!$C$12:$C$16,"ERROR - Check Input")/12 -> 10 | W15: ="Montly Loan Payment (First "&X9&" Years)" -> Montly Loan Payment (First 5 Years) | X15: =X7*X6/12+$X$13*_xlfn.XLOOKUP($Y$13,'RE Calculations'!$B$12:$B$16,'RE Calculations'!$C$12:$C$16,"ERROR - Check Input")/12 -> 10
I16: ="Montly Loan Payment (After "&J9&" Years)" -> Montly Loan Payment (After 5 Years) | J16: =-PMT(J11,(J12-J9)*12,J6)+$J$13*_xlfn.XLOOKUP($K$13,'RE Calculations'!$B$12:$B$16,'RE Calculations'!$C$12:$C$16,"ERROR - Check Input")/12 -> 10 | W16: ="Montly Loan Payment (After "&X9&" Years)" -> Montly Loan Payment (After 5 Years) | X16: =-PMT(X11,(X12-X9)*12,X6)+$X$13*_xlfn.XLOOKUP($Y$13,'RE Calculations'!$B$12:$B$16,'RE Calculations'!$C$12:$C$16,"ERROR - Check Input")/12 -> 10
I17: Check | J17: =J6*((J11*((1+J11)^((J12-J9)*12)))/(((1+J11)^((J12-J9)*12))-1))+$J$13*_xlfn.XLOOKUP($K$13,'RE Calculations'!$B$12:$B$16,'RE Calculations'!$C$12:$C$16,"ERROR - Check Input")/12 -> 10 | W17: Check | X17: =X6*((X11*((1+X11)^((X12-X9)*12)))/(((1+X11)^((X12-X9)*12))-1))+$X$13*_xlfn.XLOOKUP($Y$13,'RE Calculations'!$B$12:$B$16,'RE Calculations'!$C$12:$C$16,"ERROR - Check Input")/12 -> 10
B19: AMORTIZATION SCHEDULE | C19: Total | D19: Total | E19: Total | I19: AMORTIZATION SCHEDULE | J19: Total | K19: Total | L19: Total | P19: AMORTIZATION SCHEDULE | Q19: Total | R19: Total | S19: Total | W19: AMORTIZATION SCHEDULE | X19: Total | Y19: Total | Z19: Total
C20: =SUMIF(C23:C623,">0") -> 0 | D20: =SUMIF(D23:D623,">0") -> 0 | E20: =SUMIF(E23:E623,">0") -> 3000 | J20: =SUMIF(J23:J623,">0") -> 10 | K20: =SUMIF(K23:K623,">0") -> 0 | L20: =SUMIF(L23:L623,">0") -> 3600 | Q20: =SUMIF(Q23:Q623,">0") -> 8.3333333 | R20: =SUMIF(R23:R623,">0") -> 0 | S20: =SUMIF(S23:S623,">0") -> 3000 | X20: =SUMIF(X23:X623,">0") -> 10 | Y20: =SUMIF(Y23:Y623,">0") -> 0 | Z20: =SUMIF(Z23:Z623,">0") -> 3600
B21: Payment Number (Month) | C21: Payment | D21: Principal | E21: =IF($C$10=0,"Interest","Interest + Fees") -> Interest + Fees | F21: Balance | I21: Payment Number (Month) | J21: Payment | K21: Principal | L21: =IF($J$13=0,"Interest","Interest + Fees") -> Interest + Fees | M21: Balance | P21: Payment Number (Month) | Q21: Payment | R21: Principal | S21: =IF($Q$10=0,"Interest","Interest + Fees") -> Interest + Fees | T21: Balance | W21: Payment Number (Month) | X21: Payment | Y21: Principal | Z21: =IF($X$13=0,"Interest","Interest + Fees") -> Interest + Fees | AA21: Balance
B22: 0 | C22: 0 | D22: 0 | E22: 0 | F22: =C6-D22 -> 0 | I22: 0 | J22: 0 | K22: 0 | L22: 0 | M22: =J6-K22 -> 0 | P22: 0 | Q22: 0 | R22: 0 | S22: 0 | T22: =Q6-R22 -> 0 | W22: 0 | X22: 0 | Y22: 0 | Z22: 0 | AA22: =X6-Y22 -> 0
B23: 1 | C23: =IF(F22>0.01,-PMT($C$8,$C$9*12,$C$6)+$C$10*_xlfn.XLOOKUP($D$10,'RE Calculations'!$B$12:$B$16,'RE Calculations'!$C$12:$C$16,"ERROR - Check Input")/12,0) -> 0 | D23: =IFERROR(-PPMT($C$8,B23,$C$9*12,$C$6),0) -> 0 | E23: =IFERROR(-IPMT($C$8,B23,$C$9*12,$C$6)+$C$10*_xlfn.XLOOKUP($D$10,'RE Calculations'!$B$12:$B$16,'RE Calculations'!$C$12:$C$16,"ERROR - Check Input")/12,0) -> 8.3333333 | F23: =IFERROR(F22-D23,0) -> 0 | I23: 1 | J23: =IF(I23<=($J$9*12),$J$15,-PMT($J$11,($J$12-$J$9)*12,$J$6)+$J$13*_xlfn.XLOOKUP($K$13,'RE Calculations'!$B$12:$B$16,'RE Calculations'!$C$12:$C$16,"ERROR - Check Input")/12) -> 10 | K23: =IF(I23<=($J$9*12),0,IFERROR(-PPMT($J$11,I23-$J$9*12,($J$12-$J$9)*12,$J$6),0)) -> 0 | L23: =IF(I23<=($J$9*12),$J$15,IFERROR(-IPMT($J$11,I23-$J$9*12,($J$12-$J$9)*12,$J$6)+$J$13*_xlfn.XLOOKUP($K$13,'RE Calculations'!$B$12:$B$16,'RE Calculations'!$C$12:$C$16,"ERROR - Check Input")/12,0)) -> 10 | M23: =IFERROR(M22-K23,0) -> 0 | P23: 1 | Q23: =-PMT($Q$8,$Q$9*12,$Q$6)+$Q$10*_xlfn.XLOOKUP($R$10,'RE Calculations'!$B$12:$B$16,'RE Calculations'!$C$12:$C$16,"ERROR - Check Input")/12 -> 8.3333333 | R23: =IFERROR(-PPMT($Q$8,P23,$Q$9*12,$Q$6),0) -> 0 | S23: =IFERROR(-IPMT($Q$8,P23,$Q$9*12,$Q$6)+$Q$10*_xlfn.XLOOKUP($R$10,'RE Calculations'!$B$12:$B$16,'RE Calculations'!$C$12:$C$16,"ERROR - Check Input")/12,0) -> 8.3333333 | T23: =IFERROR(T22-R23,0) -> 0 | W23: 1 | X23: =IF(W23<=($X$9*12),$X$15,-PMT($X$11,($X$12-$X$9)*12,$X$6)+$X$13*_xlfn.XLOOKUP($Y$13,'RE Calculations'!$B$12:$B$16,'RE Calculations'!$C$12:$C$16,"ERROR - Check Input")/12) -> 10 | Y23: =IF(W23<=($X$9*12),0,IFERROR(-PPMT($X$11,W23-$X$9*12,($X$12-$X$9)*12,$X$6),0)) -> 0 | Z23: =IF(W23<=($X$9*12),$X$15,IFERROR(-IPMT($X$11,W23-$X$9*12,($X$12-$X$9)*12,$X$6)+$X$13*_xlfn.XLOOKUP($Y$13,'RE Calculations'!$B$12:$B$16,'RE Calculations'!$C$12:$C$16,"ERROR - Check Input")/12,0)) -> 10 | AA23: =IFERROR(AA22-Y23,0) -> 0
B24: 2 | C24: =IF(F23>0.01,-PMT($C$8,$C$9*12,$C$6)+$C$10*_xlfn.XLOOKUP($D$10,'RE Calculations'!$B$12:$B$16,'RE Calculations'!$C$12:$C$16,"ERROR - Check Input")/12,0) -> 0 | D24: =IFERROR(-PPMT($C$8,B24,$C$9*12,$C$6),0) -> 0 | E24: =IFERROR(-IPMT($C$8,B24,$C$9*12,$C$6)+$C$10*_xlfn.XLOOKUP($D$10,'RE Calculations'!$B$12:$B$16,'RE Calculations'!$C$12:$C$16,"ERROR - Check Input")/12,0) -> 8.3333333 | F24: =IFERROR(F23-D24,0) -> 0 | I24: 2 | J24: =IF(M23>0.01,IF(I24<=($J$9*12),$J$15,-PMT($J$11,($J$12-$J$9)*12,$J$6)+$J$13*_xlfn.XLOOKUP($K$13,'RE Calculations'!$B$12:$B$16,'RE Calculations'!$C$12:$C$16,"ERROR - Check Input")/12),0) -> 0 | K24: =IF(I24<=($J$9*12),0,IFERROR(-PPMT($J$11,I24-$J$9*12,($J$12-$J$9)*12,$J$6),0)) -> 0 | L24: =IF(I24<=($J$9*12),$J$15,IFERROR(-IPMT($J$11,I24-$J$9*12,($J$12-$J$9)*12,$J$6)+$J$13*_xlfn.XLOOKUP($K$13,'RE Calculations'!$B$12:$B$16,'RE Calculations'!$C$12:$C$16,"ERROR - Check Input")/12,0)) -> 10 | M24: =IFERROR(M23-K24,0) -> 0 | P24: 2 | Q24: =IF(T23>0.01,-PMT($Q$8,$Q$9*12,$Q$6)+$Q$10*_xlfn.XLOOKUP($R$10,'RE Calculations'!$B$12:$B$16,'RE Calculations'!$C$12:$C$16,"ERROR - Check Input")/12,0) -> 0 | R24: =IFERROR(-PPMT($Q$8,P24,$Q$9*12,$Q$6),0) -> 0 | S24: =IFERROR(-IPMT($Q$8,P24,$Q$9*12,$Q$6)+$Q$10*_xlfn.XLOOKUP($R$10,'RE Calculations'!$B$12:$B$16,'RE Calculations'!$C$12:$C$16,"ERROR - Check Input")/12,0) -> 8.3333333 | T24: =IFERROR(T23-R24,0) -> 0 | W24: 2 | X24: =IF(AA23>0.01,IF(W24<=($X$9*12),$X$15,-PMT($X$11,($X$12-$X$9)*12,$X$6)+$X$13*_xlfn.XLOOKUP($Y$13,'RE Calculations'!$B$12:$B$16,'RE Calculations'!$C$12:$C$16,"ERROR - Check Input")/12),0) -> 0 | Y24: =IF(W24<=($X$9*12),0,IFERROR(-PPMT($X$11,W24-$X$9*12,($X$12-$X$9)*12,$X$6),0)) -> 0 | Z24: =IF(W24<=($X$9*12),$X$15,IFERROR(-IPMT($X$11,W24-$X$9*12,($X$12-$X$9)*12,$X$6)+$X$13*_xlfn.XLOOKUP($Y$13,'RE Calculations'!$B$12:$B$16,'RE Calculations'!$C$12:$C$16,"ERROR - Check Input")/12,0)) -> 10 | AA24: =IFERROR(AA23-Y24,0) -> 0
B25: 3 | C25: =IF(F24>0.01,-PMT($C$8,$C$9*12,$C$6)+$C$10*_xlfn.XLOOKUP($D$10,'RE Calculations'!$B$12:$B$16,'RE Calculations'!$C$12:$C$16,"ERROR - Check Input")/12,0) -> 0 | D25: =IFERROR(-PPMT($C$8,B25,$C$9*12,$C$6),0) -> 0 | E25: =IFERROR(-IPMT($C$8,B25,$C$9*12,$C$6)+$C$10*_xlfn.XLOOKUP($D$10,'RE Calculations'!$B$12:$B$16,'RE Calculations'!$C$12:$C$16,"ERROR - Check Input")/12,0) -> 8.3333333 | F25: =IFERROR(F24-D25,0) -> 0 | I25: 3 | J25: =IF(M24>0.01,IF(I25<=($J$9*12),$J$15,-PMT($J$11,($J$12-$J$9)*12,$J$6)+$J$13*_xlfn.XLOOKUP($K$13,'RE Calculations'!$B$12:$B$16,'RE Calculations'!$C$12:$C$16,"ERROR - Check Input")/12),0) -> 0 | K25: =IF(I25<=($J$9*12),0,IFERROR(-PPMT($J$11,I25-$J$9*12,($J$12-$J$9)*12,$J$6),0)) -> 0 | L25: =IF(I25<=($J$9*12),$J$15,IFERROR(-IPMT($J$11,I25-$J$9*12,($J$12-$J$9)*12,$J$6)+$J$13*_xlfn.XLOOKUP($K$13,'RE Calculations'!$B$12:$B$16,'RE Calculations'!$C$12:$C$16,"ERROR - Check Input")/12,0)) -> 10 | M25: =IFERROR(M24-K25,0) -> 0 | P25: 3 | Q25: =IF(T24>0.01,-PMT($Q$8,$Q$9*12,$Q$6)+$Q$10*_xlfn.XLOOKUP($R$10,'RE Calculations'!$B$12:$B$16,'RE Calculations'!$C$12:$C$16,"ERROR - Check Input")/12,0) -> 0 | R25: =IFERROR(-PPMT($Q$8,P25,$Q$9*12,$Q$6),0) -> 0 | S25: =IFERROR(-IPMT($Q$8,P25,$Q$9*12,$Q$6)+$Q$10*_xlfn.XLOOKUP($R$10,'RE Calculations'!$B$12:$B$16,'RE Calculations'!$C$12:$C$16,"ERROR - Check Input")/12,0) -> 8.3333333 | T25: =IFERROR(T24-R25,0) -> 0 | W25: 3 | X25: =IF(AA24>0.01,IF(W25<=($X$9*12),$X$15,-PMT($X$11,($X$12-$X$9)*12,$X$6)+$X$13*_xlfn.XLOOKUP($Y$13,'RE Calculations'!$B$12:$B$16,'RE Calculations'!$C$12:$C$16,"ERROR - Check Input")/12),0) -> 0 | Y25: =IF(W25<=($X$9*12),0,IFERROR(-PPMT($X$11,W25-$X$9*12,($X$12-$X$9)*12,$X$6),0)) -> 0 | Z25: =IF(W25<=($X$9*12),$X$15,IFERROR(-IPMT($X$11,W25-$X$9*12,($X$12-$X$9)*12,$X$6)+$X$13*_xlfn.XLOOKUP($Y$13,'RE Calculations'!$B$12:$B$16,'RE Calculations'!$C$12:$C$16,"ERROR - Check Input")/12,0)) -> 10 | AA25: =IFERROR(AA24-Y25,0) -> 0
B26: 4 | C26: =IF(F25>0.01,-PMT($C$8,$C$9*12,$C$6)+$C$10*_xlfn.XLOOKUP($D$10,'RE Calculations'!$B$12:$B$16,'RE Calculations'!$C$12:$C$16,"ERROR - Check Input")/12,0) -> 0 | D26: =IFERROR(-PPMT($C$8,B26,$C$9*12,$C$6),0) -> 0 | E26: =IFERROR(-IPMT($C$8,B26,$C$9*12,$C$6)+$C$10*_xlfn.XLOOKUP($D$10,'RE Calculations'!$B$12:$B$16,'RE Calculations'!$C$12:$C$16,"ERROR - Check Input")/12,0) -> 8.3333333 | F26: =IFERROR(F25-D26,0) -> 0 | I26: 4 | J26: =IF(M25>0.01,IF(I26<=($J$9*12),$J$15,-PMT($J$11,($J$12-$J$9)*12,$J$6)+$J$13*_xlfn.XLOOKUP($K$13,'RE Calculations'!$B$12:$B$16,'RE Calculations'!$C$12:$C$16,"ERROR - Check Input")/12),0) -> 0 | K26: =IF(I26<=($J$9*12),0,IFERROR(-PPMT($J$11,I26-$J$9*12,($J$12-$J$9)*12,$J$6),0)) -> 0 | L26: =IF(I26<=($J$9*12),$J$15,IFERROR(-IPMT($J$11,I26-$J$9*12,($J$12-$J$9)*12,$J$6)+$J$13*_xlfn.XLOOKUP($K$13,'RE Calculations'!$B$12:$B$16,'RE Calculations'!$C$12:$C$16,"ERROR - Check Input")/12,0)) -> 10 | M26: =IFERROR(M25-K26,0) -> 0 | P26: 4 | Q26: =IF(T25>0.01,-PMT($Q$8,$Q$9*12,$Q$6)+$Q$10*_xlfn.XLOOKUP($R$10,'RE Calculations'!$B$12:$B$16,'RE Calculations'!$C$12:$C$16,"ERROR - Check Input")/12,0) -> 0 | R26: =IFERROR(-PPMT($Q$8,P26,$Q$9*12,$Q$6),0) -> 0 | S26: =IFERROR(-IPMT($Q$8,P26,$Q$9*12,$Q$6)+$Q$10*_xlfn.XLOOKUP($R$10,'RE Calculations'!$B$12:$B$16,'RE Calculations'!$C$12:$C$16,"ERROR - Check Input")/12,0) -> 8.3333333 | T26: =IFERROR(T25-R26,0) -> 0 | W26: 4 | X26: =IF(AA25>0.01,IF(W26<=($X$9*12),$X$15,-PMT($X$11,($X$12-$X$9)*12,$X$6)+$X$13*_xlfn.XLOOKUP($Y$13,'RE Calculations'!$B$12:$B$16,'RE Calculations'!$C$12:$C$16,"ERROR - Check Input")/12),0) -> 0 | Y26: =IF(W26<=($X$9*12),0,IFERROR(-PPMT($X$11,W26-$X$9*12,($X$12-$X$9)*12,$X$6),0)) -> 0 | Z26: =IF(W26<=($X$9*12),$X$15,IFERROR(-IPMT($X$11,W26-$X$9*12,($X$12-$X$9)*12,$X$6)+$X$13*_xlfn.XLOOKUP($Y$13,'RE Calculations'!$B$12:$B$16,'RE Calculations'!$C$12:$C$16,"ERROR - Check Input")/12,0)) -> 10 | AA26: =IFERROR(AA25-Y26,0) -> 0
B27: 5 | C27: =IF(F26>0.01,-PMT($C$8,$C$9*12,$C$6)+$C$10*_xlfn.XLOOKUP($D$10,'RE Calculations'!$B$12:$B$16,'RE Calculations'!$C$12:$C$16,"ERROR - Check Input")/12,0) -> 0 | D27: =IFERROR(-PPMT($C$8,B27,$C$9*12,$C$6),0) -> 0 | E27: =IFERROR(-IPMT($C$8,B27,$C$9*12,$C$6)+$C$10*_xlfn.XLOOKUP($D$10,'RE Calculations'!$B$12:$B$16,'RE Calculations'!$C$12:$C$16,"ERROR - Check Input")/12,0) -> 8.3333333 | F27: =IFERROR(F26-D27,0) -> 0 | I27: 5 | J27: =IF(M26>0.01,IF(I27<=($J$9*12),$J$15,-PMT($J$11,($J$12-$J$9)*12,$J$6)+$J$13*_xlfn.XLOOKUP($K$13,'RE Calculations'!$B$12:$B$16,'RE Calculations'!$C$12:$C$16,"ERROR - Check Input")/12),0) -> 0 | K27: =IF(I27<=($J$9*12),0,IFERROR(-PPMT($J$11,I27-$J$9*12,($J$12-$J$9)*12,$J$6),0)) -> 0 | L27: =IF(I27<=($J$9*12),$J$15,IFERROR(-IPMT($J$11,I27-$J$9*12,($J$12-$J$9)*12,$J$6)+$J$13*_xlfn.XLOOKUP($K$13,'RE Calculations'!$B$12:$B$16,'RE Calculations'!$C$12:$C$16,"ERROR - Check Input")/12,0)) -> 10 | M27: =IFERROR(M26-K27,0) -> 0 | P27: 5 | Q27: =IF(T26>0.01,-PMT($Q$8,$Q$9*12,$Q$6)+$Q$10*_xlfn.XLOOKUP($R$10,'RE Calculations'!$B$12:$B$16,'RE Calculations'!$C$12:$C$16,"ERROR - Check Input")/12,0) -> 0 | R27: =IFERROR(-PPMT($Q$8,P27,$Q$9*12,$Q$6),0) -> 0 | S27: =IFERROR(-IPMT($Q$8,P27,$Q$9*12,$Q$6)+$Q$10*_xlfn.XLOOKUP($R$10,'RE Calculations'!$B$12:$B$16,'RE Calculations'!$C$12:$C$16,"ERROR - Check Input")/12,0) -> 8.3333333 | T27: =IFERROR(T26-R27,0) -> 0 | W27: 5 | X27: =IF(AA26>0.01,IF(W27<=($X$9*12),$X$15,-PMT($X$11,($X$12-$X$9)*12,$X$6)+$X$13*_xlfn.XLOOKUP($Y$13,'RE Calculations'!$B$12:$B$16,'RE Calculations'!$C$12:$C$16,"ERROR - Check Input")/12),0) -> 0 | Y27: =IF(W27<=($X$9*12),0,IFERROR(-PPMT($X$11,W27-$X$9*12,($X$12-$X$9)*12,$X$6),0)) -> 0 | Z27: =IF(W27<=($X$9*12),$X$15,IFERROR(-IPMT($X$11,W27-$X$9*12,($X$12-$X$9)*12,$X$6)+$X$13*_xlfn.XLOOKUP($Y$13,'RE Calculations'!$B$12:$B$16,'RE Calculations'!$C$12:$C$16,"ERROR - Check Input")/12,0)) -> 10 | AA27: =IFERROR(AA26-Y27,0) -> 0
B28: 6 | C28: =IF(F27>0.01,-PMT($C$8,$C$9*12,$C$6)+$C$10*_xlfn.XLOOKUP($D$10,'RE Calculations'!$B$12:$B$16,'RE Calculations'!$C$12:$C$16,"ERROR - Check Input")/12,0) -> 0 | D28: =IFERROR(-PPMT($C$8,B28,$C$9*12,$C$6),0) -> 0 | E28: =IFERROR(-IPMT($C$8,B28,$C$9*12,$C$6)+$C$10*_xlfn.XLOOKUP($D$10,'RE Calculations'!$B$12:$B$16,'RE Calculations'!$C$12:$C$16,"ERROR - Check Input")/12,0) -> 8.3333333 | F28: =IFERROR(F27-D28,0) -> 0 | I28: 6 | J28: =IF(M27>0.01,IF(I28<=($J$9*12),$J$15,-PMT($J$11,($J$12-$J$9)*12,$J$6)+$J$13*_xlfn.XLOOKUP($K$13,'RE Calculations'!$B$12:$B$16,'RE Calculations'!$C$12:$C$16,"ERROR - Check Input")/12),0) -> 0 | K28: =IF(I28<=($J$9*12),0,IFERROR(-PPMT($J$11,I28-$J$9*12,($J$12-$J$9)*12,$J$6),0)) -> 0 | L28: =IF(I28<=($J$9*12),$J$15,IFERROR(-IPMT($J$11,I28-$J$9*12,($J$12-$J$9)*12,$J$6)+$J$13*_xlfn.XLOOKUP($K$13,'RE Calculations'!$B$12:$B$16,'RE Calculations'!$C$12:$C$16,"ERROR - Check Input")/12,0)) -> 10 | M28: =IFERROR(M27-K28,0) -> 0 | P28: 6 | Q28: =IF(T27>0.01,-PMT($Q$8,$Q$9*12,$Q$6)+$Q$10*_xlfn.XLOOKUP($R$10,'RE Calculations'!$B$12:$B$16,'RE Calculations'!$C$12:$C$16,"ERROR - Check Input")/12,0) -> 0 | R28: =IFERROR(-PPMT($Q$8,P28,$Q$9*12,$Q$6),0) -> 0 | S28: =IFERROR(-IPMT($Q$8,P28,$Q$9*12,$Q$6)+$Q$10*_xlfn.XLOOKUP($R$10,'RE Calculations'!$B$12:$B$16,'RE Calculations'!$C$12:$C$16,"ERROR - Check Input")/12,0) -> 8.3333333 | T28: =IFERROR(T27-R28,0) -> 0 | W28: 6 | X28: =IF(AA27>0.01,IF(W28<=($X$9*12),$X$15,-PMT($X$11,($X$12-$X$9)*12,$X$6)+$X$13*_xlfn.XLOOKUP($Y$13,'RE Calculations'!$B$12:$B$16,'RE Calculations'!$C$12:$C$16,"ERROR - Check Input")/12),0) -> 0 | Y28: =IF(W28<=($X$9*12),0,IFERROR(-PPMT($X$11,W28-$X$9*12,($X$12-$X$9)*12,$X$6),0)) -> 0 | Z28: =IF(W28<=($X$9*12),$X$15,IFERROR(-IPMT($X$11,W28-$X$9*12,($X$12-$X$9)*12,$X$6)+$X$13*_xlfn.XLOOKUP($Y$13,'RE Calculations'!$B$12:$B$16,'RE Calculations'!$C$12:$C$16,"ERROR - Check Input")/12,0)) -> 10 | AA28: =IFERROR(AA27-Y28,0) -> 0
B29: 7 | C29: =IF(F28>0.01,-PMT($C$8,$C$9*12,$C$6)+$C$10*_xlfn.XLOOKUP($D$10,'RE Calculations'!$B$12:$B$16,'RE Calculations'!$C$12:$C$16,"ERROR - Check Input")/12,0) -> 0 | D29: =IFERROR(-PPMT($C$8,B29,$C$9*12,$C$6),0) -> 0 | E29: =IFERROR(-IPMT($C$8,B29,$C$9*12,$C$6)+$C$10*_xlfn.XLOOKUP($D$10,'RE Calculations'!$B$12:$B$16,'RE Calculations'!$C$12:$C$16,"ERROR - Check Input")/12,0) -> 8.3333333 | F29: =IFERROR(F28-D29,0) -> 0 | I29: 7 | J29: =IF(M28>0.01,IF(I29<=($J$9*12),$J$15,-PMT($J$11,($J$12-$J$9)*12,$J$6)+$J$13*_xlfn.XLOOKUP($K$13,'RE Calculations'!$B$12:$B$16,'RE Calculations'!$C$12:$C$16,"ERROR - Check Input")/12),0) -> 0 | K29: =IF(I29<=($J$9*12),0,IFERROR(-PPMT($J$11,I29-$J$9*12,($J$12-$J$9)*12,$J$6),0)) -> 0 | L29: =IF(I29<=($J$9*12),$J$15,IFERROR(-IPMT($J$11,I29-$J$9*12,($J$12-$J$9)*12,$J$6)+$J$13*_xlfn.XLOOKUP($K$13,'RE Calculations'!$B$12:$B$16,'RE Calculations'!$C$12:$C$16,"ERROR - Check Input")/12,0)) -> 10 | M29: =IFERROR(M28-K29,0) -> 0 | P29: 7 | Q29: =IF(T28>0.01,-PMT($Q$8,$Q$9*12,$Q$6)+$Q$10*_xlfn.XLOOKUP($R$10,'RE Calculations'!$B$12:$B$16,'RE Calculations'!$C$12:$C$16,"ERROR - Check Input")/12,0) -> 0 | R29: =IFERROR(-PPMT($Q$8,P29,$Q$9*12,$Q$6),0) -> 0 | S29: =IFERROR(-IPMT($Q$8,P29,$Q$9*12,$Q$6)+$Q$10*_xlfn.XLOOKUP($R$10,'RE Calculations'!$B$12:$B$16,'RE Calculations'!$C$12:$C$16,"ERROR - Check Input")/12,0) -> 8.3333333 | T29: =IFERROR(T28-R29,0) -> 0 | W29: 7 | X29: =IF(AA28>0.01,IF(W29<=($X$9*12),$X$15,-PMT($X$11,($X$12-$X$9)*12,$X$6)+$X$13*_xlfn.XLOOKUP($Y$13,'RE Calculations'!$B$12:$B$16,'RE Calculations'!$C$12:$C$16,"ERROR - Check Input")/12),0) -> 0 | Y29: =IF(W29<=($X$9*12),0,IFERROR(-PPMT($X$11,W29-$X$9*12,($X$12-$X$9)*12,$X$6),0)) -> 0 | Z29: =IF(W29<=($X$9*12),$X$15,IFERROR(-IPMT($X$11,W29-$X$9*12,($X$12-$X$9)*12,$X$6)+$X$13*_xlfn.XLOOKUP($Y$13,'RE Calculations'!$B$12:$B$16,'RE Calculations'!$C$12:$C$16,"ERROR - Check Input")/12,0)) -> 10 | AA29: =IFERROR(AA28-Y29,0) -> 0
B30: 8 | C30: =IF(F29>0.01,-PMT($C$8,$C$9*12,$C$6)+$C$10*_xlfn.XLOOKUP($D$10,'RE Calculations'!$B$12:$B$16,'RE Calculations'!$C$12:$C$16,"ERROR - Check Input")/12,0) -> 0 | D30: =IFERROR(-PPMT($C$8,B30,$C$9*12,$C$6),0) -> 0 | E30: =IFERROR(-IPMT($C$8,B30,$C$9*12,$C$6)+$C$10*_xlfn.XLOOKUP($D$10,'RE Calculations'!$B$12:$B$16,'RE Calculations'!$C$12:$C$16,"ERROR - Check Input")/12,0) -> 8.3333333 | F30: =IFERROR(F29-D30,0) -> 0 | I30: 8 | J30: =IF(M29>0.01,IF(I30<=($J$9*12),$J$15,-PMT($J$11,($J$12-$J$9)*12,$J$6)+$J$13*_xlfn.XLOOKUP($K$13,'RE Calculations'!$B$12:$B$16,'RE Calculations'!$C$12:$C$16,"ERROR - Check Input")/12),0) -> 0 | K30: =IF(I30<=($J$9*12),0,IFERROR(-PPMT($J$11,I30-$J$9*12,($J$12-$J$9)*12,$J$6),0)) -> 0 | L30: =IF(I30<=($J$9*12),$J$15,IFERROR(-IPMT($J$11,I30-$J$9*12,($J$12-$J$9)*12,$J$6)+$J$13*_xlfn.XLOOKUP($K$13,'RE Calculations'!$B$12:$B$16,'RE Calculations'!$C$12:$C$16,"ERROR - Check Input")/12,0)) -> 10 | M30: =IFERROR(M29-K30,0) -> 0 | P30: 8 | Q30: =IF(T29>0.01,-PMT($Q$8,$Q$9*12,$Q$6)+$Q$10*_xlfn.XLOOKUP($R$10,'RE Calculations'!$B$12:$B$16,'RE Calculations'!$C$12:$C$16,"ERROR - Check Input")/12,0) -> 0 | R30: =IFERROR(-PPMT($Q$8,P30,$Q$9*12,$Q$6),0) -> 0 | S30: =IFERROR(-IPMT($Q$8,P30,$Q$9*12,$Q$6)+$Q$10*_xlfn.XLOOKUP($R$10,'RE Calculations'!$B$12:$B$16,'RE Calculations'!$C$12:$C$16,"ERROR - Check Input")/12,0) -> 8.3333333 | T30: =IFERROR(T29-R30,0) -> 0 | W30: 8 | X30: =IF(AA29>0.01,IF(W30<=($X$9*12),$X$15,-PMT($X$11,($X$12-$X$9)*12,$X$6)+$X$13*_xlfn.XLOOKUP($Y$13,'RE Calculations'!$B$12:$B$16,'RE Calculations'!$C$12:$C$16,"ERROR - Check Input")/12),0) -> 0 | Y30: =IF(W30<=($X$9*12),0,IFERROR(-PPMT($X$11,W30-$X$9*12,($X$12-$X$9)*12,$X$6),0)) -> 0 | Z30: =IF(W30<=($X$9*12),$X$15,IFERROR(-IPMT($X$11,W30-$X$9*12,($X$12-$X$9)*12,$X$6)+$X$13*_xlfn.XLOOKUP($Y$13,'RE Calculations'!$B$12:$B$16,'RE Calculations'!$C$12:$C$16,"ERROR - Check Input")/12,0)) -> 10 | AA30: =IFERROR(AA29-Y30,0) -> 0
B31: 9 | C31: =IF(F30>0.01,-PMT($C$8,$C$9*12,$C$6)+$C$10*_xlfn.XLOOKUP($D$10,'RE Calculations'!$B$12:$B$16,'RE Calculations'!$C$12:$C$16,"ERROR - Check Input")/12,0) -> 0 | D31: =IFERROR(-PPMT($C$8,B31,$C$9*12,$C$6),0) -> 0 | E31: =IFERROR(-IPMT($C$8,B31,$C$9*12,$C$6)+$C$10*_xlfn.XLOOKUP($D$10,'RE Calculations'!$B$12:$B$16,'RE Calculations'!$C$12:$C$16,"ERROR - Check Input")/12,0) -> 8.3333333 | F31: =IFERROR(F30-D31,0) -> 0 | I31: 9 | J31: =IF(M30>0.01,IF(I31<=($J$9*12),$J$15,-PMT($J$11,($J$12-$J$9)*12,$J$6)+$J$13*_xlfn.XLOOKUP($K$13,'RE Calculations'!$B$12:$B$16,'RE Calculations'!$C$12:$C$16,"ERROR - Check Input")/12),0) -> 0 | K31: =IF(I31<=($J$9*12),0,IFERROR(-PPMT($J$11,I31-$J$9*12,($J$12-$J$9)*12,$J$6),0)) -> 0 | L31: =IF(I31<=($J$9*12),$J$15,IFERROR(-IPMT($J$11,I31-$J$9*12,($J$12-$J$9)*12,$J$6)+$J$13*_xlfn.XLOOKUP($K$13,'RE Calculations'!$B$12:$B$16,'RE Calculations'!$C$12:$C$16,"ERROR - Check Input")/12,0)) -> 10 | M31: =IFERROR(M30-K31,0) -> 0 | P31: 9 | Q31: =IF(T30>0.01,-PMT($Q$8,$Q$9*12,$Q$6)+$Q$10*_xlfn.XLOOKUP($R$10,'RE Calculations'!$B$12:$B$16,'RE Calculations'!$C$12:$C$16,"ERROR - Check Input")/12,0) -> 0 | R31: =IFERROR(-PPMT($Q$8,P31,$Q$9*12,$Q$6),0) -> 0 | S31: =IFERROR(-IPMT($Q$8,P31,$Q$9*12,$Q$6)+$Q$10*_xlfn.XLOOKUP($R$10,'RE Calculations'!$B$12:$B$16,'RE Calculations'!$C$12:$C$16,"ERROR - Check Input")/12,0) -> 8.3333333 | T31: =IFERROR(T30-R31,0) -> 0 | W31: 9 | X31: =IF(AA30>0.01,IF(W31<=($X$9*12),$X$15,-PMT($X$11,($X$12-$X$9)*12,$X$6)+$X$13*_xlfn.XLOOKUP($Y$13,'RE Calculations'!$B$12:$B$16,'RE Calculations'!$C$12:$C$16,"ERROR - Check Input")/12),0) -> 0 | Y31: =IF(W31<=($X$9*12),0,IFERROR(-PPMT($X$11,W31-$X$9*12,($X$12-$X$9)*12,$X$6),0)) -> 0 | Z31: =IF(W31<=($X$9*12),$X$15,IFERROR(-IPMT($X$11,W31-$X$9*12,($X$12-$X$9)*12,$X$6)+$X$13*_xlfn.XLOOKUP($Y$13,'RE Calculations'!$B$12:$B$16,'RE Calculations'!$C$12:$C$16,"ERROR - Check Input")/12,0)) -> 10 | AA31: =IFERROR(AA30-Y31,0) -> 0
B32: 10 | C32: =IF(F31>0.01,-PMT($C$8,$C$9*12,$C$6)+$C$10*_xlfn.XLOOKUP($D$10,'RE Calculations'!$B$12:$B$16,'RE Calculations'!$C$12:$C$16,"ERROR - Check Input")/12,0) -> 0 | D32: =IFERROR(-PPMT($C$8,B32,$C$9*12,$C$6),0) -> 0 | E32: =IFERROR(-IPMT($C$8,B32,$C$9*12,$C$6)+$C$10*_xlfn.XLOOKUP($D$10,'RE Calculations'!$B$12:$B$16,'RE Calculations'!$C$12:$C$16,"ERROR - Check Input")/12,0) -> 8.3333333 | F32: =IFERROR(F31-D32,0) -> 0 | I32: 10 | J32: =IF(M31>0.01,IF(I32<=($J$9*12),$J$15,-PMT($J$11,($J$12-$J$9)*12,$J$6)+$J$13*_xlfn.XLOOKUP($K$13,'RE Calculations'!$B$12:$B$16,'RE Calculations'!$C$12:$C$16,"ERROR - Check Input")/12),0) -> 0 | K32: =IF(I32<=($J$9*12),0,IFERROR(-PPMT($J$11,I32-$J$9*12,($J$12-$J$9)*12,$J$6),0)) -> 0 | L32: =IF(I32<=($J$9*12),$J$15,IFERROR(-IPMT($J$11,I32-$J$9*12,($J$12-$J$9)*12,$J$6)+$J$13*_xlfn.XLOOKUP($K$13,'RE Calculations'!$B$12:$B$16,'RE Calculations'!$C$12:$C$16,"ERROR - Check Input")/12,0)) -> 10 | M32: =IFERROR(M31-K32,0) -> 0 | P32: 10 | Q32: =IF(T31>0.01,-PMT($Q$8,$Q$9*12,$Q$6)+$Q$10*_xlfn.XLOOKUP($R$10,'RE Calculations'!$B$12:$B$16,'RE Calculations'!$C$12:$C$16,"ERROR - Check Input")/12,0) -> 0 | R32: =IFERROR(-PPMT($Q$8,P32,$Q$9*12,$Q$6),0) -> 0 | S32: =IFERROR(-IPMT($Q$8,P32,$Q$9*12,$Q$6)+$Q$10*_xlfn.XLOOKUP($R$10,'RE Calculations'!$B$12:$B$16,'RE Calculations'!$C$12:$C$16,"ERROR - Check Input")/12,0) -> 8.3333333 | T32: =IFERROR(T31-R32,0) -> 0 | W32: 10 | X32: =IF(AA31>0.01,IF(W32<=($X$9*12),$X$15,-PMT($X$11,($X$12-$X$9)*12,$X$6)+$X$13*_xlfn.XLOOKUP($Y$13,'RE Calculations'!$B$12:$B$16,'RE Calculations'!$C$12:$C$16,"ERROR - Check Input")/12),0) -> 0 | Y32: =IF(W32<=($X$9*12),0,IFERROR(-PPMT($X$11,W32-$X$9*12,($X$12-$X$9)*12,$X$6),0)) -> 0 | Z32: =IF(W32<=($X$9*12),$X$15,IFERROR(-IPMT($X$11,W32-$X$9*12,($X$12-$X$9)*12,$X$6)+$X$13*_xlfn.XLOOKUP($Y$13,'RE Calculations'!$B$12:$B$16,'RE Calculations'!$C$12:$C$16,"ERROR - Check Input")/12,0)) -> 10 | AA32: =IFERROR(AA31-Y32,0) -> 0
B33: 11 | C33: =IF(F32>0.01,-PMT($C$8,$C$9*12,$C$6)+$C$10*_xlfn.XLOOKUP($D$10,'RE Calculations'!$B$12:$B$16,'RE Calculations'!$C$12:$C$16,"ERROR - Check Input")/12,0) -> 0 | D33: =IFERROR(-PPMT($C$8,B33,$C$9*12,$C$6),0) -> 0 | E33: =IFERROR(-IPMT($C$8,B33,$C$9*12,$C$6)+$C$10*_xlfn.XLOOKUP($D$10,'RE Calculations'!$B$12:$B$16,'RE Calculations'!$C$12:$C$16,"ERROR - Check Input")/12,0) -> 8.3333333 | F33: =IFERROR(F32-D33,0) -> 0 | I33: 11 | J33: =IF(M32>0.01,IF(I33<=($J$9*12),$J$15,-PMT($J$11,($J$12-$J$9)*12,$J$6)+$J$13*_xlfn.XLOOKUP($K$13,'RE Calculations'!$B$12:$B$16,'RE Calculations'!$C$12:$C$16,"ERROR - Check Input")/12),0) -> 0 | K33: =IF(I33<=($J$9*12),0,IFERROR(-PPMT($J$11,I33-$J$9*12,($J$12-$J$9)*12,$J$6),0)) -> 0 | L33: =IF(I33<=($J$9*12),$J$15,IFERROR(-IPMT($J$11,I33-$J$9*12,($J$12-$J$9)*12,$J$6)+$J$13*_xlfn.XLOOKUP($K$13,'RE Calculations'!$B$12:$B$16,'RE Calculations'!$C$12:$C$16,"ERROR - Check Input")/12,0)) -> 10 | M33: =IFERROR(M32-K33,0) -> 0 | P33: 11 | Q33: =IF(T32>0.01,-PMT($Q$8,$Q$9*12,$Q$6)+$Q$10*_xlfn.XLOOKUP($R$10,'RE Calculations'!$B$12:$B$16,'RE Calculations'!$C$12:$C$16,"ERROR - Check Input")/12,0) -> 0 | R33: =IFERROR(-PPMT($Q$8,P33,$Q$9*12,$Q$6),0) -> 0 | S33: =IFERROR(-IPMT($Q$8,P33,$Q$9*12,$Q$6)+$Q$10*_xlfn.XLOOKUP($R$10,'RE Calculations'!$B$12:$B$16,'RE Calculations'!$C$12:$C$16,"ERROR - Check Input")/12,0) -> 8.3333333 | T33: =IFERROR(T32-R33,0) -> 0 | W33: 11 | X33: =IF(AA32>0.01,IF(W33<=($X$9*12),$X$15,-PMT($X$11,($X$12-$X$9)*12,$X$6)+$X$13*_xlfn.XLOOKUP($Y$13,'RE Calculations'!$B$12:$B$16,'RE Calculations'!$C$12:$C$16,"ERROR - Check Input")/12),0) -> 0 | Y33: =IF(W33<=($X$9*12),0,IFERROR(-PPMT($X$11,W33-$X$9*12,($X$12-$X$9)*12,$X$6),0)) -> 0 | Z33: =IF(W33<=($X$9*12),$X$15,IFERROR(-IPMT($X$11,W33-$X$9*12,($X$12-$X$9)*12,$X$6)+$X$13*_xlfn.XLOOKUP($Y$13,'RE Calculations'!$B$12:$B$16,'RE Calculations'!$C$12:$C$16,"ERROR - Check Input")/12,0)) -> 10 | AA33: =IFERROR(AA32-Y33,0) -> 0
B34: 12 | C34: =IF(F33>0.01,-PMT($C$8,$C$9*12,$C$6)+$C$10*_xlfn.XLOOKUP($D$10,'RE Calculations'!$B$12:$B$16,'RE Calculations'!$C$12:$C$16,"ERROR - Check Input")/12,0) -> 0 | D34: =IFERROR(-PPMT($C$8,B34,$C$9*12,$C$6),0) -> 0 | E34: =IFERROR(-IPMT($C$8,B34,$C$9*12,$C$6)+$C$10*_xlfn.XLOOKUP($D$10,'RE Calculations'!$B$12:$B$16,'RE Calculations'!$C$12:$C$16,"ERROR - Check Input")/12,0) -> 8.3333333 | F34: =IFERROR(F33-D34,0) -> 0 | I34: 12 | J34: =IF(M33>0.01,IF(I34<=($J$9*12),$J$15,-PMT($J$11,($J$12-$J$9)*12,$J$6)+$J$13*_xlfn.XLOOKUP($K$13,'RE Calculations'!$B$12:$B$16,'RE Calculations'!$C$12:$C$16,"ERROR - Check Input")/12),0) -> 0 | K34: =IF(I34<=($J$9*12),0,IFERROR(-PPMT($J$11,I34-$J$9*12,($J$12-$J$9)*12,$J$6),0)) -> 0 | L34: =IF(I34<=($J$9*12),$J$15,IFERROR(-IPMT($J$11,I34-$J$9*12,($J$12-$J$9)*12,$J$6)+$J$13*_xlfn.XLOOKUP($K$13,'RE Calculations'!$B$12:$B$16,'RE Calculations'!$C$12:$C$16,"ERROR - Check Input")/12,0)) -> 10 | M34: =IFERROR(M33-K34,0) -> 0 | P34: 12 | Q34: =IF(T33>0.01,-PMT($Q$8,$Q$9*12,$Q$6)+$Q$10*_xlfn.XLOOKUP($R$10,'RE Calculations'!$B$12:$B$16,'RE Calculations'!$C$12:$C$16,"ERROR - Check Input")/12,0) -> 0 | R34: =IFERROR(-PPMT($Q$8,P34,$Q$9*12,$Q$6),0) -> 0 | S34: =IFERROR(-IPMT($Q$8,P34,$Q$9*12,$Q$6)+$Q$10*_xlfn.XLOOKUP($R$10,'RE Calculations'!$B$12:$B$16,'RE Calculations'!$C$12:$C$16,"ERROR - Check Input")/12,0) -> 8.3333333 | T34: =IFERROR(T33-R34,0) -> 0 | W34: 12 | X34: =IF(AA33>0.01,IF(W34<=($X$9*12),$X$15,-PMT($X$11,($X$12-$X$9)*12,$X$6)+$X$13*_xlfn.XLOOKUP($Y$13,'RE Calculations'!$B$12:$B$16,'RE Calculations'!$C$12:$C$16,"ERROR - Check Input")/12),0) -> 0 | Y34: =IF(W34<=($X$9*12),0,IFERROR(-PPMT($X$11,W34-$X$9*12,($X$12-$X$9)*12,$X$6),0)) -> 0 | Z34: =IF(W34<=($X$9*12),$X$15,IFERROR(-IPMT($X$11,W34-$X$9*12,($X$12-$X$9)*12,$X$6)+$X$13*_xlfn.XLOOKUP($Y$13,'RE Calculations'!$B$12:$B$16,'RE Calculations'!$C$12:$C$16,"ERROR - Check Input")/12,0)) -> 10 | AA34: =IFERROR(AA33-Y34,0) -> 0
B35: 13 | C35: =IF(F34>0.01,-PMT($C$8,$C$9*12,$C$6)+$C$10*_xlfn.XLOOKUP($D$10,'RE Calculations'!$B$12:$B$16,'RE Calculations'!$C$12:$C$16,"ERROR - Check Input")/12,0) -> 0 | D35: =IFERROR(-PPMT($C$8,B35,$C$9*12,$C$6),0) -> 0 | E35: =IFERROR(-IPMT($C$8,B35,$C$9*12,$C$6)+$C$10*_xlfn.XLOOKUP($D$10,'RE Calculations'!$B$12:$B$16,'RE Calculations'!$C$12:$C$16,"ERROR - Check Input")/12,0) -> 8.3333333 | F35: =IFERROR(F34-D35,0) -> 0 | I35: 13 | J35: =IF(M34>0.01,IF(I35<=($J$9*12),$J$15,-PMT($J$11,($J$12-$J$9)*12,$J$6)+$J$13*_xlfn.XLOOKUP($K$13,'RE Calculations'!$B$12:$B$16,'RE Calculations'!$C$12:$C$16,"ERROR - Check Input")/12),0) -> 0 | K35: =IF(I35<=($J$9*12),0,IFERROR(-PPMT($J$11,I35-$J$9*12,($J$12-$J$9)*12,$J$6),0)) -> 0 | L35: =IF(I35<=($J$9*12),$J$15,IFERROR(-IPMT($J$11,I35-$J$9*12,($J$12-$J$9)*12,$J$6)+$J$13*_xlfn.XLOOKUP($K$13,'RE Calculations'!$B$12:$B$16,'RE Calculations'!$C$12:$C$16,"ERROR - Check Input")/12,0)) -> 10 | M35: =IFERROR(M34-K35,0) -> 0 | P35: 13 | Q35: =IF(T34>0.01,-PMT($Q$8,$Q$9*12,$Q$6)+$Q$10*_xlfn.XLOOKUP($R$10,'RE Calculations'!$B$12:$B$16,'RE Calculations'!$C$12:$C$16,"ERROR - Check Input")/12,0) -> 0 | R35: =IFERROR(-PPMT($Q$8,P35,$Q$9*12,$Q$6),0) -> 0 | S35: =IFERROR(-IPMT($Q$8,P35,$Q$9*12,$Q$6)+$Q$10*_xlfn.XLOOKUP($R$10,'RE Calculations'!$B$12:$B$16,'RE Calculations'!$C$12:$C$16,"ERROR - Check Input")/12,0) -> 8.3333333 | T35: =IFERROR(T34-R35,0) -> 0 | W35: 13 | X35: =IF(AA34>0.01,IF(W35<=($X$9*12),$X$15,-PMT($X$11,($X$12-$X$9)*12,$X$6)+$X$13*_xlfn.XLOOKUP($Y$13,'RE Calculations'!$B$12:$B$16,'RE Calculations'!$C$12:$C$16,"ERROR - Check Input")/12),0) -> 0 | Y35: =IF(W35<=($X$9*12),0,IFERROR(-PPMT($X$11,W35-$X$9*12,($X$12-$X$9)*12,$X$6),0)) -> 0 | Z35: =IF(W35<=($X$9*12),$X$15,IFERROR(-IPMT($X$11,W35-$X$9*12,($X$12-$X$9)*12,$X$6)+$X$13*_xlfn.XLOOKUP($Y$13,'RE Calculations'!$B$12:$B$16,'RE Calculations'!$C$12:$C$16,"ERROR - Check Input")/12,0)) -> 10 | AA35: =IFERROR(AA34-Y35,0) -> 0
... B623: 601 | C623: =IF(F622>0.01,-PMT($C$8,$C$9*12,$C$6)+$C$10*_xlfn.XLOOKUP($D$10,'RE Calculations'!$B$12:$B$16,'RE Calculations'!$C$12:$C$16,"ERROR - Check Input")/12,0) -> 0 | D623: =IFERROR(-PPMT($C$8,B623,$C$9*12,$C$6),0) -> 0 | E623: =IFERROR(-IPMT($C$8,B623,$C$9*12,$C$6)+$C$10*_xlfn.XLOOKUP($D$10,'RE Calculations'!$B$12:$B$16,'RE Calculations'!$C$12:$C$16,"ERROR - Check Input")/12,0) -> 0 | F623: =IFERROR(F622-D623,0) -> 0 | I623: 601 | J623: =IF(M622>0.01,IF(I623<=($J$9*12),$J$15,-PMT($J$11,($J$12-$J$9)*12,$J$6)+$J$13*_xlfn.XLOOKUP($K$13,'RE Calculations'!$B$12:$B$16,'RE Calculations'!$C$12:$C$16,"ERROR - Check Input")/12),0) -> 0 | K623: =IF(I623<=($J$9*12),0,IFERROR(-PPMT($J$11,I623-$J$9*12,($J$12-$J$9)*12,$J$6),0)) -> 0 | L623: =IF(I623<=($J$9*12),$J$15,IFERROR(-IPMT($J$11,I623-$J$9*12,($J$12-$J$9)*12,$J$6)+$J$13*_xlfn.XLOOKUP($K$13,'RE Calculations'!$B$12:$B$16,'RE Calculations'!$C$12:$C$16,"ERROR - Check Input")/12,0)) -> 0 | M623: =IFERROR(M622-K623,0) -> 0 | P623: 601 | Q623: =IF(T622>0.01,-PMT($Q$8,$Q$9*12,$Q$6)+$Q$10*_xlfn.XLOOKUP($R$10,'RE Calculations'!$B$12:$B$16,'RE Calculations'!$C$12:$C$16,"ERROR - Check Input")/12,0) -> 0 | R623: =IFERROR(-PPMT($Q$8,P623,$Q$9*12,$Q$6),0) -> 0 | S623: =IFERROR(-IPMT($Q$8,P623,$Q$9*12,$Q$6)+$Q$10*_xlfn.XLOOKUP($R$10,'RE Calculations'!$B$12:$B$16,'RE Calculations'!$C$12:$C$16,"ERROR - Check Input")/12,0) -> 0 | T623: =IFERROR(T622-R623,0) -> 0 | W623: 601 | X623: =IF(AA622>0.01,IF(W623<=($X$9*12),$X$15,-PMT($X$11,($X$12-$X$9)*12,$X$6)+$X$13*_xlfn.XLOOKUP($Y$13,'RE Calculations'!$B$12:$B$16,'RE Calculations'!$C$12:$C$16,"ERROR - Check Input")/12),0) -> 0 | Y623: =IF(W623<=($X$9*12),0,IFERROR(-PPMT($X$11,W623-$X$9*12,($X$12-$X$9)*12,$X$6),0)) -> 0 | Z623: =IF(W623<=($X$9*12),$X$15,IFERROR(-IPMT($X$11,W623-$X$9*12,($X$12-$X$9)*12,$X$6)+$X$13*_xlfn.XLOOKUP($Y$13,'RE Calculations'!$B$12:$B$16,'RE Calculations'!$C$12:$C$16,"ERROR - Check Input")/12,0)) -> 0 | AA623: =IFERROR(AA622-Y623,0) -> 0

Sheet Mortgage Calculators (By Year)
P1: Note: Please input comparison values in 'Mortgage Calculators (By Month)' sheet | W1: Note: Please input comparison values in 'Mortgage Calculators (By Month)' sheet
B2: PRINCIPAL & INTEREST LOAN (P&I) | I2: INTEREST ONLY LOAN (IO) | P2: MORTGAGE CALCULATOR - PRINCIPAL & INTEREST (COMPARISON) | W2: MORTGAGE CALCULATOR - INTEREST ONLY (COMPARISON)
B3: Total Price | C3: ='Mortgage Calculators (By Month)'!C3 -> 1499950 | I3: Total Price | J3: ='Mortgage Calculators (By Month)'!J3 -> 1499950 | P3: Total Price | Q3: ='Mortgage Calculators (By Month)'!Q3 -> 1499950 | W3: Total Price | X3: ='Mortgage Calculators (By Month)'!X3 -> 1499950
B4: Down Payment (%) | C4: ='Mortgage Calculators (By Month)'!C4 -> 1 | I4: Down Payment (%) | J4: ='Mortgage Calculators (By Month)'!J4 -> 1 | P4: Down Payment (%) | Q4: ='Mortgage Calculators (By Month)'!Q4 -> 1 | W4: Down Payment (%) | X4: ='Mortgage Calculators (By Month)'!X4 -> 1
B5: Down Payment ($) | C5: ='Mortgage Calculators (By Month)'!C5 -> 1499950 | I5: Down Payment ($) | J5: ='Mortgage Calculators (By Month)'!J5 -> 1499950 | P5: Down Payment ($) | Q5: ='Mortgage Calculators (By Month)'!Q5 -> 1499950 | W5: Down Payment ($) | X5: ='Mortgage Calculators (By Month)'!X5 -> 1499950
B6: Principal Amount | C6: ='Mortgage Calculators (By Month)'!C6 -> 0 | I6: Principal Amount | J6: ='Mortgage Calculators (By Month)'!J6 -> 0 | P6: Principal Amount | Q6: ='Mortgage Calculators (By Month)'!Q6 -> 0 | W6: Principal Amount | X6: ='Mortgage Calculators (By Month)'!X6 -> 0
B7: Annual Interest Rate | C7: ='Mortgage Calculators (By Month)'!C7 -> 0.045 | I7: Annual Interest Rate | J7: ='Mortgage Calculators (By Month)'!J7 -> 0.0475 | P7: Annual Interest Rate | Q7: ='Mortgage Calculators (By Month)'!Q7 -> 0.06 | W7: Annual Interest Rate | X7: ='Mortgage Calculators (By Month)'!X7 -> 0.062
B8: Equivalent Monthly Interest Rate | C8: ='Mortgage Calculators (By Month)'!C8 -> 0.00375 | I8: Equivalent Monthly Interest Rate | J8: ='Mortgage Calculators (By Month)'!J8 -> 0.0039583333 | P8: Equivalent Monthly Interest Rate | Q8: ='Mortgage Calculators (By Month)'!Q8 -> 0.005 | W8: Equivalent Monthly Interest Rate | X8: ='Mortgage Calculators (By Month)'!X8 -> 0.0051666667
B9: Loan Duration (Years) | C9: ='Mortgage Calculators (By Month)'!C9 -> 30 | I9: Interest Only Duration (Years) | J9: ='Mortgage Calculators (By Month)'!J9 -> 5 | P9: Loan Duration (Years) | Q9: ='Mortgage Calculators (By Month)'!Q9 -> 30 | W9: Interest Only Duration (Years) | X9: ='Mortgage Calculators (By Month)'!X9 -> 5
B10: Fees | C10: ='Mortgage Calculators (By Month)'!C10 -> 100 | D10: ='Mortgage Calculators (By Month)'!D10 -> per annum | I10: Standard Interest Rate | J10: ='Mortgage Calculators (By Month)'!J10 -> 0.045 | P10: Fees | Q10: ='Mortgage Calculators (By Month)'!Q10 -> 100 | R10: ='Mortgage Calculators (By Month)'!R10 -> per annum | W10: Standard Interest Rate | X10: ='Mortgage Calculators (By Month)'!X10 -> 0.06
I11: Equivalent Monthly Interest Rate | J11: ='Mortgage Calculators (By Month)'!J11 -> 0.00375 | W11: Equivalent Monthly Interest Rate | X11: ='Mortgage Calculators (By Month)'!X11 -> 0.005
B12: Monthly Loan Payment | C12: ='Mortgage Calculators (By Month)'!C12 -> 8.3333333 | I12: Total Loan Duration (Years) | J12: ='Mortgage Calculators (By Month)'!J12 -> 30 | P12: Monthly Loan Payment | Q12: ='Mortgage Calculators (By Month)'!Q12 -> 8.3333333 | W12: Total Loan Duration (Years) | X12: ='Mortgage Calculators (By Month)'!X12 -> 30
B13: Check | C13: ='Mortgage Calculators (By Month)'!C13 -> 8.3333333 | I13: Fees | J13: ='Mortgage Calculators (By Month)'!J13 -> 120 | K13: ='Mortgage Calculators (By Month)'!K13 -> per annum | P13: Check | Q13: ='Mortgage Calculators (By Month)'!Q13 -> 8.3333333 | W13: Fees | X13: ='Mortgage Calculators (By Month)'!X13 -> 120 | Y13: ='Mortgage Calculators (By Month)'!Y13 -> per annum
I15: ="Montly Loan Payment (First "&J9&" Years)" -> Montly Loan Payment (First 5 Years) | J15: ='Mortgage Calculators (By Month)'!J15 -> 10 | W15: ="Montly Loan Payment (First "&X9&" Years)" -> Montly Loan Payment (First 5 Years) | X15: ='Mortgage Calculators (By Month)'!X15 -> 10
I16: ="Montly Loan Payment (After "&J9&" Years)" -> Montly Loan Payment (After 5 Years) | J16: ='Mortgage Calculators (By Month)'!J16 -> 10 | W16: ="Montly Loan Payment (After "&X9&" Years)" -> Montly Loan Payment (After 5 Years) | X16: ='Mortgage Calculators (By Month)'!X16 -> 10
I17: Check | J17: ='Mortgage Calculators (By Month)'!J17 -> 10 | W17: Check | X17: ='Mortgage Calculators (By Month)'!X17 -> 10
B19: AMORTIZATION SCHEDULE | C19: Total | D19: Total | E19: Total | I19: AMORTIZATION SCHEDULE | J19: Total | K19: Total | L19: Total | P19: AMORTIZATION SCHEDULE | Q19: Total | R19: Total | S19: Total | W19: AMORTIZATION SCHEDULE | X19: Total | Y19: Total | Z19: Total
C20: =SUMIF(C23:C73,">0") -> 0 | D20: =SUMIF(D23:D73,">0") -> 0 | E20: =SUMIF(E23:E73,">0") -> 3000 | J20: =SUMIF(J23:J73,">0") -> 10 | K20: =SUMIF(K23:K73,">0") -> 0 | L20: =SUMIF(L23:L73,">0") -> 3600 | Q20: =SUMIF(Q23:Q73,">0") -> 8.3333333 | R20: =SUMIF(R23:R73,">0") -> 0 | S20: =SUMIF(S23:S73,">0") -> 3000 | X20: =SUMIF(X23:X73,">0") -> 10 | Y20: =SUMIF(Y23:Y73,">0") -> 0 | Z20: =SUMIF(Z23:Z73,">0") -> 3600
B21: Year | C21: Payment | D21: Principal | E21: =IF($C$10=0,"Interest","Interest + Fees") -> Interest + Fees | F21: Balance | I21: Year | J21: Payment | K21: Principal | L21: =IF($J$13=0,"Interest","Interest + Fees") -> Interest + Fees | M21: Balance | P21: Year | Q21: Payment | R21: Principal | S21: =IF($Q$10=0,"Interest","Interest + Fees") -> Interest + Fees | T21: Balance | W21: Year | X21: Payment | Y21: Principal | Z21: =IF($X$13=0,"Interest","Interest + Fees") -> Interest + Fees | AA21: Balance
B22: 0 | C22: 0 | D22: 0 | E22: 0 | F22: =C6-D22 -> 0 | I22: 0 | J22: 0 | K22: 0 | L22: 0 | M22: =J6-K22 -> 0 | P22: 0 | Q22: 0 | R22: 0 | S22: 0 | T22: =Q6-R22 -> 0 | W22: 0 | X22: 0 | Y22: 0 | Z22: 0 | AA22: =X6-Y22 -> 0
B23: 1 | C23: =IF($B23<=$C$9,SUMIFS('Mortgage Calculators (By Month)'!$C$23:$C$623,'Mortgage Calculators (By Month)'!$B$23:$B$623,"<="&$B23*12,'Mortgage Calculators (By Month)'!$B$23:$B$623,">"&0),0) -> 0 | D23: =IF($B23<=$C$9,SUMIFS('Mortgage Calculators (By Month)'!$D$23:$D$623,'Mortgage Calculators (By Month)'!$B$23:$B$623,"<="&$B23*12,'Mortgage Calculators (By Month)'!$B$23:$B$623,">"&0),0) -> 0 | E23: =IF($B23<=$C$9,SUMIFS('Mortgage Calculators (By Month)'!$E$23:$E$623,'Mortgage Calculators (By Month)'!$B$23:$B$623,"<="&$B23*12,'Mortgage Calculators (By Month)'!$B$23:$B$623,">"&0),0) -> 100 | F23: =IFERROR(F22-D23,0) -> 0 | I23: 1 | J23: =IF($I23<=$J$12,SUMIFS('Mortgage Calculators (By Month)'!$J$23:$J$623,'Mortgage Calculators (By Month)'!$I$23:$I$623,"<="&$I23*12,'Mortgage Calculators (By Month)'!$I$23:$I$623,">"&0),0) -> 10 | K23: =IF($I23<=$J$12,SUMIFS('Mortgage Calculators (By Month)'!$K$23:$K$623,'Mortgage Calculators (By Month)'!$I$23:$I$623,"<="&$I23*12,'Mortgage Calculators (By Month)'!$I$23:$I$623,">"&0),0) -> 0 | L23: =IF($I23<=$J$12,SUMIFS('Mortgage Calculators (By Month)'!$L$23:$L$623,'Mortgage Calculators (By Month)'!$I$23:$I$623,"<="&$I23*12,'Mortgage Calculators (By Month)'!$I$23:$I$623,">"&0),0) -> 120 | M23: =IFERROR(M22-K23,0) -> 0 | P23: 1 | Q23: =IF($P23<=$Q$9,SUMIFS('Mortgage Calculators (By Month)'!$Q$23:$Q$623,'Mortgage Calculators (By Month)'!$P$23:$P$623,"<="&$P23*12,'Mortgage Calculators (By Month)'!$P$23:$P$623,">"&0),0) -> 8.3333333 | R23: =IF($P23<=$Q$9,SUMIFS('Mortgage Calculators (By Month)'!$R$23:$R$623,'Mortgage Calculators (By Month)'!$P$23:$P$623,"<="&$P23*12,'Mortgage Calculators (By Month)'!$P$23:$P$623,">"&0),0) -> 0 | S23: =IF($P23<=$Q$9,SUMIFS('Mortgage Calculators (By Month)'!$S$23:$S$623,'Mortgage Calculators (By Month)'!$P$23:$P$623,"<="&$P23*12,'Mortgage Calculators (By Month)'!$P$23:$P$623,">"&0),0) -> 100 | T23: =IFERROR(T22-R23,0) -> 0 | W23: 1 | X23: =IF($W23<=$X$12,SUMIFS('Mortgage Calculators (By Month)'!$X$23:$X$623,'Mortgage Calculators (By Month)'!$W$23:$W$623,"<="&$W23*12,'Mortgage Calculators (By Month)'!$W$23:$W$623,">"&0),0) -> 10 | Y23: =IF($W23<=$X$12,SUMIFS('Mortgage Calculators (By Month)'!$Y$23:$Y$623,'Mortgage Calculators (By Month)'!$W$23:$W$623,"<="&$W23*12,'Mortgage Calculators (By Month)'!$W$23:$W$623,">"&0),0) -> 0 | Z23: =IF($W23<=$X$12,SUMIFS('Mortgage Calculators (By Month)'!$Z$23:$Z$623,'Mortgage Calculators (By Month)'!$W$23:$W$623,"<="&$W23*12,'Mortgage Calculators (By Month)'!$W$23:$W$623,">"&0),0) -> 120 | AA23: =IFERROR(AA22-Y23,0) -> 0
B24: 2 | C24: =IF($B24<=$C$9,SUMIFS('Mortgage Calculators (By Month)'!$C$23:$C$623,'Mortgage Calculators (By Month)'!$B$23:$B$623,"<="&$B24*12,'Mortgage Calculators (By Month)'!$B$23:$B$623,">"&$B23*12),0) -> 0 | D24: =IF($B24<=$C$9,SUMIFS('Mortgage Calculators (By Month)'!$D$23:$D$623,'Mortgage Calculators (By Month)'!$B$23:$B$623,"<="&$B24*12,'Mortgage Calculators (By Month)'!$B$23:$B$623,">"&$B23*12),0) -> 0 | E24: =IF($B24<=$C$9,SUMIFS('Mortgage Calculators (By Month)'!$E$23:$E$623,'Mortgage Calculators (By Month)'!$B$23:$B$623,"<="&$B24*12,'Mortgage Calculators (By Month)'!$B$23:$B$623,">"&$B23*12),0) -> 100 | F24: =IFERROR(F23-D24,0) -> 0 | I24: 2 | J24: =IF($I24<=$J$12,SUMIFS('Mortgage Calculators (By Month)'!$J$23:$J$623,'Mortgage Calculators (By Month)'!$I$23:$I$623,"<="&$I24*12,'Mortgage Calculators (By Month)'!$I$23:$I$623,">"&$I23*12),0) -> 0 | K24: =IF($I24<=$J$12,SUMIFS('Mortgage Calculators (By Month)'!$K$23:$K$623,'Mortgage Calculators (By Month)'!$I$23:$I$623,"<="&$I24*12,'Mortgage Calculators (By Month)'!$I$23:$I$623,">"&$I23*12),0) -> 0 | L24: =IF($I24<=$J$12,SUMIFS('Mortgage Calculators (By Month)'!$L$23:$L$623,'Mortgage Calculators (By Month)'!$I$23:$I$623,"<="&$I24*12,'Mortgage Calculators (By Month)'!$I$23:$I$623,">"&$I23*12),0) -> 120 | M24: =IFERROR(M23-K24,0) -> 0 | P24: 2 | Q24: =IF($P24<=$Q$9,SUMIFS('Mortgage Calculators (By Month)'!$Q$23:$Q$623,'Mortgage Calculators (By Month)'!$P$23:$P$623,"<="&$P24*12,'Mortgage Calculators (By Month)'!$P$23:$P$623,">"&$P23*12),0) -> 0 | R24: =IF($P24<=$Q$9,SUMIFS('Mortgage Calculators (By Month)'!$R$23:$R$623,'Mortgage Calculators (By Month)'!$P$23:$P$623,"<="&$P24*12,'Mortgage Calculators (By Month)'!$P$23:$P$623,">"&$P23*12),0) -> 0 | S24: =IF($P24<=$Q$9,SUMIFS('Mortgage Calculators (By Month)'!$S$23:$S$623,'Mortgage Calculators (By Month)'!$P$23:$P$623,"<="&$P24*12,'Mortgage Calculators (By Month)'!$P$23:$P$623,">"&$P23*12),0) -> 100 | T24: =IFERROR(T23-R24,0) -> 0 | W24: 2 | X24: =IF($W24<=$X$12,SUMIFS('Mortgage Calculators (By Month)'!$X$23:$X$623,'Mortgage Calculators (By Month)'!$W$23:$W$623,"<="&$W24*12,'Mortgage Calculators (By Month)'!$W$23:$W$623,">"&$W23*12),0) -> 0 | Y24: =IF($W24<=$X$12,SUMIFS('Mortgage Calculators (By Month)'!$Y$23:$Y$623,'Mortgage Calculators (By Month)'!$W$23:$W$623,"<="&$W24*12,'Mortgage Calculators (By Month)'!$W$23:$W$623,">"&$W23*12),0) -> 0 | Z24: =IF($W24<=$X$12,SUMIFS('Mortgage Calculators (By Month)'!$Z$23:$Z$623,'Mortgage Calculators (By Month)'!$W$23:$W$623,"<="&$W24*12,'Mortgage Calculators (By Month)'!$W$23:$W$623,">"&$W23*12),0) -> 120 | AA24: =IFERROR(AA23-Y24,0) -> 0
B25: 3 | C25: =IF($B25<=$C$9,SUMIFS('Mortgage Calculators (By Month)'!$C$23:$C$623,'Mortgage Calculators (By Month)'!$B$23:$B$623,"<="&$B25*12,'Mortgage Calculators (By Month)'!$B$23:$B$623,">"&$B24*12),0) -> 0 | D25: =IF($B25<=$C$9,SUMIFS('Mortgage Calculators (By Month)'!$D$23:$D$623,'Mortgage Calculators (By Month)'!$B$23:$B$623,"<="&$B25*12,'Mortgage Calculators (By Month)'!$B$23:$B$623,">"&$B24*12),0) -> 0 | E25: =IF($B25<=$C$9,SUMIFS('Mortgage Calculators (By Month)'!$E$23:$E$623,'Mortgage Calculators (By Month)'!$B$23:$B$623,"<="&$B25*12,'Mortgage Calculators (By Month)'!$B$23:$B$623,">"&$B24*12),0) -> 100 | F25: =IFERROR(F24-D25,0) -> 0 | I25: 3 | J25: =IF($I25<=$J$12,SUMIFS('Mortgage Calculators (By Month)'!$J$23:$J$623,'Mortgage Calculators (By Month)'!$I$23:$I$623,"<="&$I25*12,'Mortgage Calculators (By Month)'!$I$23:$I$623,">"&$I24*12),0) -> 0 | K25: =IF($I25<=$J$12,SUMIFS('Mortgage Calculators (By Month)'!$K$23:$K$623,'Mortgage Calculators (By Month)'!$I$23:$I$623,"<="&$I25*12,'Mortgage Calculators (By Month)'!$I$23:$I$623,">"&$I24*12),0) -> 0 | L25: =IF($I25<=$J$12,SUMIFS('Mortgage Calculators (By Month)'!$L$23:$L$623,'Mortgage Calculators (By Month)'!$I$23:$I$623,"<="&$I25*12,'Mortgage Calculators (By Month)'!$I$23:$I$623,">"&$I24*12),0) -> 120 | M25: =IFERROR(M24-K25,0) -> 0 | P25: 3 | Q25: =IF($P25<=$Q$9,SUMIFS('Mortgage Calculators (By Month)'!$Q$23:$Q$623,'Mortgage Calculators (By Month)'!$P$23:$P$623,"<="&$P25*12,'Mortgage Calculators (By Month)'!$P$23:$P$623,">"&$P24*12),0) -> 0 | R25: =IF($P25<=$Q$9,SUMIFS('Mortgage Calculators (By Month)'!$R$23:$R$623,'Mortgage Calculators (By Month)'!$P$23:$P$623,"<="&$P25*12,'Mortgage Calculators (By Month)'!$P$23:$P$623,">"&$P24*12),0) -> 0 | S25: =IF($P25<=$Q$9,SUMIFS('Mortgage Calculators (By Month)'!$S$23:$S$623,'Mortgage Calculators (By Month)'!$P$23:$P$623,"<="&$P25*12,'Mortgage Calculators (By Month)'!$P$23:$P$623,">"&$P24*12),0) -> 100 | T25: =IFERROR(T24-R25,0) -> 0 | W25: 3 | X25: =IF($W25<=$X$12,SUMIFS('Mortgage Calculators (By Month)'!$X$23:$X$623,'Mortgage Calculators (By Month)'!$W$23:$W$623,"<="&$W25*12,'Mortgage Calculators (By Month)'!$W$23:$W$623,">"&$W24*12),0) -> 0 | Y25: =IF($W25<=$X$12,SUMIFS('Mortgage Calculators (By Month)'!$Y$23:$Y$623,'Mortgage Calculators (By Month)'!$W$23:$W$623,"<="&$W25*12,'Mortgage Calculators (By Month)'!$W$23:$W$623,">"&$W24*12),0) -> 0 | Z25: =IF($W25<=$X$12,SUMIFS('Mortgage Calculators (By Month)'!$Z$23:$Z$623,'Mortgage Calculators (By Month)'!$W$23:$W$623,"<="&$W25*12,'Mortgage Calculators (By Month)'!$W$23:$W$623,">"&$W24*12),0) -> 120 | AA25: =IFERROR(AA24-Y25,0) -> 0
B26: 4 | C26: =IF($B26<=$C$9,SUMIFS('Mortgage Calculators (By Month)'!$C$23:$C$623,'Mortgage Calculators (By Month)'!$B$23:$B$623,"<="&$B26*12,'Mortgage Calculators (By Month)'!$B$23:$B$623,">"&$B25*12),0) -> 0 | D26: =IF($B26<=$C$9,SUMIFS('Mortgage Calculators (By Month)'!$D$23:$D$623,'Mortgage Calculators (By Month)'!$B$23:$B$623,"<="&$B26*12,'Mortgage Calculators (By Month)'!$B$23:$B$623,">"&$B25*12),0) -> 0 | E26: =IF($B26<=$C$9,SUMIFS('Mortgage Calculators (By Month)'!$E$23:$E$623,'Mortgage Calculators (By Month)'!$B$23:$B$623,"<="&$B26*12,'Mortgage Calculators (By Month)'!$B$23:$B$623,">"&$B25*12),0) -> 100 | F26: =IFERROR(F25-D26,0) -> 0 | I26: 4 | J26: =IF($I26<=$J$12,SUMIFS('Mortgage Calculators (By Month)'!$J$23:$J$623,'Mortgage Calculators (By Month)'!$I$23:$I$623,"<="&$I26*12,'Mortgage Calculators (By Month)'!$I$23:$I$623,">"&$I25*12),0) -> 0 | K26: =IF($I26<=$J$12,SUMIFS('Mortgage Calculators (By Month)'!$K$23:$K$623,'Mortgage Calculators (By Month)'!$I$23:$I$623,"<="&$I26*12,'Mortgage Calculators (By Month)'!$I$23:$I$623,">"&$I25*12),0) -> 0 | L26: =IF($I26<=$J$12,SUMIFS('Mortgage Calculators (By Month)'!$L$23:$L$623,'Mortgage Calculators (By Month)'!$I$23:$I$623,"<="&$I26*12,'Mortgage Calculators (By Month)'!$I$23:$I$623,">"&$I25*12),0) -> 120 | M26: =IFERROR(M25-K26,0) -> 0 | P26: 4 | Q26: =IF($P26<=$Q$9,SUMIFS('Mortgage Calculators (By Month)'!$Q$23:$Q$623,'Mortgage Calculators (By Month)'!$P$23:$P$623,"<="&$P26*12,'Mortgage Calculators (By Month)'!$P$23:$P$623,">"&$P25*12),0) -> 0 | R26: =IF($P26<=$Q$9,SUMIFS('Mortgage Calculators (By Month)'!$R$23:$R$623,'Mortgage Calculators (By Month)'!$P$23:$P$623,"<="&$P26*12,'Mortgage Calculators (By Month)'!$P$23:$P$623,">"&$P25*12),0) -> 0 | S26: =IF($P26<=$Q$9,SUMIFS('Mortgage Calculators (By Month)'!$S$23:$S$623,'Mortgage Calculators (By Month)'!$P$23:$P$623,"<="&$P26*12,'Mortgage Calculators (By Month)'!$P$23:$P$623,">"&$P25*12),0) -> 100 | T26: =IFERROR(T25-R26,0) -> 0 | W26: 4 | X26: =IF($W26<=$X$12,SUMIFS('Mortgage Calculators (By Month)'!$X$23:$X$623,'Mortgage Calculators (By Month)'!$W$23:$W$623,"<="&$W26*12,'Mortgage Calculators (By Month)'!$W$23:$W$623,">"&$W25*12),0) -> 0 | Y26: =IF($W26<=$X$12,SUMIFS('Mortgage Calculators (By Month)'!$Y$23:$Y$623,'Mortgage Calculators (By Month)'!$W$23:$W$623,"<="&$W26*12,'Mortgage Calculators (By Month)'!$W$23:$W$623,">"&$W25*12),0) -> 0 | Z26: =IF($W26<=$X$12,SUMIFS('Mortgage Calculators (By Month)'!$Z$23:$Z$623,'Mortgage Calculators (By Month)'!$W$23:$W$623,"<="&$W26*12,'Mortgage Calculators (By Month)'!$W$23:$W$623,">"&$W25*12),0) -> 120 | AA26: =IFERROR(AA25-Y26,0) -> 0
B27: 5 | C27: =IF($B27<=$C$9,SUMIFS('Mortgage Calculators (By Month)'!$C$23:$C$623,'Mortgage Calculators (By Month)'!$B$23:$B$623,"<="&$B27*12,'Mortgage Calculators (By Month)'!$B$23:$B$623,">"&$B26*12),0) -> 0 | D27: =IF($B27<=$C$9,SUMIFS('Mortgage Calculators (By Month)'!$D$23:$D$623,'Mortgage Calculators (By Month)'!$B$23:$B$623,"<="&$B27*12,'Mortgage Calculators (By Month)'!$B$23:$B$623,">"&$B26*12),0) -> 0 | E27: =IF($B27<=$C$9,SUMIFS('Mortgage Calculators (By Month)'!$E$23:$E$623,'Mortgage Calculators (By Month)'!$B$23:$B$623,"<="&$B27*12,'Mortgage Calculators (By Month)'!$B$23:$B$623,">"&$B26*12),0) -> 100 | F27: =IFERROR(F26-D27,0) -> 0 | I27: 5 | J27: =IF($I27<=$J$12,SUMIFS('Mortgage Calculators (By Month)'!$J$23:$J$623,'Mortgage Calculators (By Month)'!$I$23:$I$623,"<="&$I27*12,'Mortgage Calculators (By Month)'!$I$23:$I$623,">"&$I26*12),0) -> 0 | K27: =IF($I27<=$J$12,SUMIFS('Mortgage Calculators (By Month)'!$K$23:$K$623,'Mortgage Calculators (By Month)'!$I$23:$I$623,"<="&$I27*12,'Mortgage Calculators (By Month)'!$I$23:$I$623,">"&$I26*12),0) -> 0 | L27: =IF($I27<=$J$12,SUMIFS('Mortgage Calculators (By Month)'!$L$23:$L$623,'Mortgage Calculators (By Month)'!$I$23:$I$623,"<="&$I27*12,'Mortgage Calculators (By Month)'!$I$23:$I$623,">"&$I26*12),0) -> 120 | M27: =IFERROR(M26-K27,0) -> 0 | P27: 5 | Q27: =IF($P27<=$Q$9,SUMIFS('Mortgage Calculators (By Month)'!$Q$23:$Q$623,'Mortgage Calculators (By Month)'!$P$23:$P$623,"<="&$P27*12,'Mortgage Calculators (By Month)'!$P$23:$P$623,">"&$P26*12),0) -> 0 | R27: =IF($P27<=$Q$9,SUMIFS('Mortgage Calculators (By Month)'!$R$23:$R$623,'Mortgage Calculators (By Month)'!$P$23:$P$623,"<="&$P27*12,'Mortgage Calculators (By Month)'!$P$23:$P$623,">"&$P26*12),0) -> 0 | S27: =IF($P27<=$Q$9,SUMIFS('Mortgage Calculators (By Month)'!$S$23:$S$623,'Mortgage Calculators (By Month)'!$P$23:$P$623,"<="&$P27*12,'Mortgage Calculators (By Month)'!$P$23:$P$623,">"&$P26*12),0) -> 100 | T27: =IFERROR(T26-R27,0) -> 0 | W27: 5 | X27: =IF($W27<=$X$12,SUMIFS('Mortgage Calculators (By Month)'!$X$23:$X$623,'Mortgage Calculators (By Month)'!$W$23:$W$623,"<="&$W27*12,'Mortgage Calculators (By Month)'!$W$23:$W$623,">"&$W26*12),0) -> 0 | Y27: =IF($W27<=$X$12,SUMIFS('Mortgage Calculators (By Month)'!$Y$23:$Y$623,'Mortgage Calculators (By Month)'!$W$23:$W$623,"<="&$W27*12,'Mortgage Calculators (By Month)'!$W$23:$W$623,">"&$W26*12),0) -> 0 | Z27: =IF($W27<=$X$12,SUMIFS('Mortgage Calculators (By Month)'!$Z$23:$Z$623,'Mortgage Calculators (By Month)'!$W$23:$W$623,"<="&$W27*12,'Mortgage Calculators (By Month)'!$W$23:$W$623,">"&$W26*12),0) -> 120 | AA27: =IFERROR(AA26-Y27,0) -> 0
